Workbook

Sheet READ ME
A1: Canal Zone GIS - relational model (places / sources / attestations) + density + map modes
A3: TAB COLOURS (bottom of the window):
A4: Red = enter your core data here: Coordinates, places, sources, attestations.
A5: Orange = you add to these occasionally: Corpus, Coverage, relations, Lists, Feature Checklist.
A6: Grey / uncoloured = auto-calculated or reference only - do not type in these.
A7: - New tabs: "Map Modes + Rendering" (the 6 views as an app spec) and an updated Selection Matrix on archival visibility.
A9: The archival-density caution (your insight, kept central):
A10: Density = how visible a place is in surviving archives, NOT how historically important it was. Displaced and Afro-Caribbean
A11: communities were systematically under-recorded, so thin density often marks the MOST important silences. The model never
A12: equates density with importance - there is deliberately no "importance" score.
A14: "Unmapped but known" is built in:
A15: Any place with spatial_certainty = Unknown keeps its full record and its render_as becomes "Unplotted (unlocated panel)".
... A22: Green columns are AUTO (formulas) - do not type in them. Coordinates stay blank until georeferenced (do not guess).

Sheet Coordinates
A1: Coordinate entry. place_id / name / scale fill IN AUTOMATICALLY from the places sheet. You only type lat + lng (yellow). Do NOT sort this sheet (rows track the places sheet by position).
A2: place_id | B2: name | C2: scale | D2: lat | E2: lng | F2: coord_source | G2: status
A3: =IF(places!$A2="","",places!$A2) -> CZ-001 | B3: =IF(places!$A2="","",places!$B2) -> Matachin | C3: =IF(places!$A2="","",places!$Y2) -> Town | D3: 9.10975 | E3: -79.70699 | F3: ICC1911 property map | G3: surveyed from ICC1911 georef, ±400m [CORRECTED 2026-09-08: earlier paste had a transcription error]
A4: =IF(places!$A3="","",places!$A3) -> CZ-002 | B4: =IF(places!$A3="","",places!$B3) -> Barbacoas | C4: =IF(places!$A3="","",places!$Y3) -> Town | D4: 9.10938 | E4: -79.76765 | F4: ICC Surveys 1905-06 Map No.2 | G4: surveyed from SURVEYS1908 georef (bridge site), ±250m
A5: =IF(places!$A4="","",places!$A4) -> CZ-003 | B5: =IF(places!$A4="","",places!$B4) -> Cruces | C5: =IF(places!$A4="","",places!$Y4) -> Town | D5: 9.124 | E5: -79.68765 | F5: ICC Surveys 1905-06 Map No.2 | G5: surveyed from SURVEYS1908 georef, ±250m
A6: =IF(places!$A5="","",places!$A5) -> CZ-004 | B6: =IF(places!$A5="","",places!$B5) -> Ahorca Lagarto | C6: =IF(places!$A5="","",places!$Y5) -> Town | D6: 9.21291 | E6: -79.876 | F6: ICC Surveys 1905-06 Map No.1 | G6: surveyed from SURVEYS1908 georef, ±250m
A7: =IF(places!$A6="","",places!$A6) -> CZ-005 | B7: =IF(places!$A6="","",places!$B6) -> Caimito | C7: =IF(places!$A6="","",places!$Y6) -> Town | D7: 9.13067 | E7: -79.77984 | F7: ICC1911 property map | G7: surveyed from ICC1911 georef (label), ±500m [CORRECTED 2026-09-08: earlier paste had a transcription error]
A8: =IF(places!$A7="","",places!$A7) -> CZ-006 | B8: =IF(places!$A7="","",places!$B7) -> Santa Cruz | C8: =IF(places!$A7="","",places!$Y7) -> Town | D8: 9.11687 | E8: -79.6977 | F8: ICC1911 property map | G8: surveyed from ICC1911 georef (label), ±400m [CORRECTED 2026-09-08: earlier paste had a transcription error]
A9: =IF(places!$A8="","",places!$A8) -> CZ-007 | B9: =IF(places!$A8="","",places!$B8) -> Bailamonos | C9: =IF(places!$A8="","",places!$Y8) -> Town | D9: 9.11008 | E9: -79.76486 | F9: 1862 Rio Chagres plano | G9: surveyed from CHAGRES1867 georef (tract, no pueblo symbol), ±800m
A10: =IF(places!$A9="","",places!$A9) -> CZ-008 | B10: =IF(places!$A9="","",places!$B9) -> Cruz de Juan Gallego | C10: =IF(places!$A9="","",places!$Y9) -> Town | D10: 9.20472 | E10: -79.86746 | F10: 1862 Rio Chagres plano | G10: surveyed from CHAGRES1867 georef (creek label only), ±1km
A11: =IF(places!$A10="","",places!$A10) -> CZ-009 | B11: =IF(places!$A10="","",places!$B10) -> Old Gatun | C11: =IF(places!$A10="","",places!$Y10) -> Town | D11: 9.26871 | E11: -79.92906 | F11: ICC Surveys 1905-06 Map No.1 | G11: surveyed from SURVEYS1908 georef (village drawn), ±250m
A12: =IF(places!$A11="","",places!$A11) -> CZ-010 | B12: =IF(places!$A11="","",places!$B11) -> New Gatun | C12: =IF(places!$A11="","",places!$Y11) -> Town | D12: 9.27471 | E12: -79.91621 | F12: ICC1911 property map | G12: surveyed from ICC1911 georef (building cluster), ±200m
A13: =IF(places!$A12="","",places!$A12) -> CZ-011 | B13: =IF(places!$A12="","",places!$B12) -> Empire | C13: =IF(places!$A12="","",places!$Y12) -> Town | D13: 9.061825 | E13: -79.671171 | F13: ICC Surveys 1905-06 Map No.3 | G13: surveyed from SURVEYS1908 Map No.3 georef (the arbitration source), ±150m; re-anchored EMPIRE plan footprint agrees within 230 m [replaced 2026-09-14: previous value was the stale pre-re-anchor EMPIRE-chain position the 2026-09-09 re-anchor never propagated to CZ-011 itself]
A14: =IF(places!$A13="","",places!$A13) -> CZ-012 | B14: =IF(places!$A13="","",places!$B13) -> Gorgona | C14: =IF(places!$A13="","",places!$Y13) -> Town | D14: 9.11401 | E14: -79.72415 | F14: Map of Gorgona 1908 (saloon) | G14: surveyed from GORGONA plan georef; SURVEYS1908 agrees within 100m, ±400m abs
... A18: =IF(places!$A17="","",places!$A17) -> CZ-016 | B18: =IF(places!$A17="","",places!$B17) -> Bohio | C18: =IF(places!$A17="","",places!$Y17) -> Town | D18: 9.1898 | E18: -79.85598 | F18: ICC Surveys 1905-06 Map No.1 | G18: surveyed from SURVEYS1908 georef (village drawn), ±250m
A19: =IF(places!$A18="","",places!$A18) -> CZ-101 | B19: =IF(places!$A18="","",places!$B18) -> Empire Hospital | C19: =IF(places!$A18="","",places!$Y18) -> Site/Institution | D19: 9.0715 | E19: -79.6818 | G19: placeholder
A20: =IF(places!$A19="","",places!$A19) -> CZ-102 | B20: =IF(places!$A19="","",places!$B19) -> Empire Commissary | C20: =IF(places!$A19="","",places!$Y19) -> Site/Institution | D20: 9.062558 | E20: -79.671553 | F20: General map of Empire (re-anchored) | G20: surveyed from EMPIRE plan georef re-anchored to SURVEYS1908_MAP3, +-200m
A21: =IF(places!$A20="","",places!$A20) -> CZ-103 | B21: =IF(places!$A20="","",places!$B20) -> Empire Clubhouse & Cinema | C21: =IF(places!$A20="","",places!$Y20) -> Building | D21: 9.0719 | E21: -79.6809 | G21: placeholder
A22: =IF(places!$A21="","",places!$A21) -> CZ-104 | B22: =IF(places!$A21="","",places!$B21) -> Empire Silver Quarters | C22: =IF(places!$A21="","",places!$Y21) -> Neighborhood | D22: 9.0702 | E22: -79.6822 | G22: placeholder
A23: =IF(places!$A22="","",places!$A22) -> CZ-105 | B23: =IF(places!$A22="","",places!$B22) -> Empire Gold Quarters | C23: =IF(places!$A22="","",places!$Y22) -> Neighborhood | D23: 9.0723 | E23: -79.68 | G23: placeholder
A24: =IF(places!$A23="","",places!$A23) -> CZ-106 | B24: =IF(places!$A23="","",places!$B23) -> Empire Plaza | C24: =IF(places!$A23="","",places!$Y23) -> Site/Institution | D24: 9.060552 | E24: -79.672322 | F24: General map of Empire (re-anchored) | G24: surveyed from EMPIRE plan georef re-anchored to SURVEYS1908_MAP3, +-200m
A25: =IF(places!$A24="","",places!$A24) -> CZ-201 | B25: =IF(places!$A24="","",places!$B24) -> Nuevo Emperador (present-day) | C25: =IF(places!$A24="","",places!$Y24) -> Town | D25: 9.07 | E25: -79.679 | G25: placeholder
A26: =IF(places!$A25="","",places!$A25) -> CZ-202 | B26: =IF(places!$A25="","",places!$B25) -> Modern roadway segment | C26: =IF(places!$A25="","",places!$Y25) -> Infrastructure | D26: 9.0695 | E26: -79.677 | G26: placeholder
A27: =IF(places!$A26="","",places!$A26) -> CZ-107 | B27: =IF(places!$A26="","",places!$B26) -> Empire Church / Chapel | C27: =IF(places!$A26="","",places!$Y26) -> Site/Institution | D27: 9.06283 | E27: -79.670234 | F27: General map of Empire (re-anchored) | G27: surveyed from EMPIRE plan georef re-anchored to SURVEYS1908_MAP3, +-200m (Cath. Church, 2nd-pass find)
A28: =IF(places!$A27="","",places!$A27) -> CZ-108 | B28: =IF(places!$A27="","",places!$B27) -> Empire Cemetery | C28: =IF(places!$A27="","",places!$Y27) -> Site/Institution | D28: 9.0698 | E28: -79.683 | G28: placeholder
A29: =IF(places!$A28="","",places!$A28) -> CZ-109 | B29: =IF(places!$A28="","",places!$B28) -> Empire School | C29: =IF(places!$A28="","",places!$Y28) -> Site/Institution | D29: 9.063286 | E29: -79.674734 | F29: General map of Empire (re-anchored) | G29: surveyed from EMPIRE plan georef re-anchored to SURVEYS1908_MAP3, +-200m
A30: =IF(places!$A29="","",places!$A29) -> CZ-017 | B30: =IF(places!$A29="","",places!$B29) -> Cristobal | C30: =IF(places!$A29="","",places!$Y29) -> Town | D30: 9.35589 | E30: -79.9006 | F30: ICC1911 property map | G30: surveyed from ICC1911 georef, ±300m
A31: =IF(places!$A30="","",places!$A30) -> CZ-018 | B31: =IF(places!$A30="","",places!$B30) -> Ancon | C31: =IF(places!$A30="","",places!$Y30) -> Town | D31: 8.95941 | E31: -79.56199 | F31: ICC1909 zone map | G31: surveyed from ICC1909 georef (town dot), ±300m [CORRECTED 2026-09-08: earlier paste had a transcription error]
A32: =IF(places!$A31="","",places!$A31) -> CZ-019 | B32: =IF(places!$A31="","",places!$B31) -> Rio Grande | C32: =IF(places!$A31="","",places!$Y31) -> Town | D32: 9.03223 | E32: -79.66239 | F32: ICC1909 zone map | G32: surveyed from ICC1909 georef, ±300m
A33: =IF(places!$A32="","",places!$A32) -> CZ-020 | B33: =IF(places!$A32="","",places!$B32) -> Pedro Miguel | C33: =IF(places!$A32="","",places!$Y32) -> Town | D33: 9.02378 | E33: -79.60107 | F33: ICC1909 zone map | G33: surveyed from ICC1909 georef (town dot), ±300m [CORRECTED 2026-09-08: earlier paste had a transcription error]
A34: =IF(places!$A33="","",places!$A33) -> CZ-021 | B34: =IF(places!$A33="","",places!$B33) -> La Boca | C34: =IF(places!$A33="","",places!$Y33) -> Town | D34: 8.94776 | E34: -79.56447 | F34: ICC1911 property map | G34: surveyed from ICC1911 georef (drawn town labeled BALBOA), ±300m
A35: =IF(places!$A34="","",places!$A34) -> CZ-022 | B35: =IF(places!$A34="","",places!$B34) -> Corozal | C35: =IF(places!$A34="","",places!$Y34) -> Town | D35: 8.97957 | E35: -79.56824 | F35: ICC1911 property map | G35: surveyed from ICC1911 georef, ±300m [CORRECTED 2026-09-08: earlier paste had a transcription error]
A36: =IF(places!$A35="","",places!$A35) -> CZ-023 | B36: =IF(places!$A35="","",places!$B35) -> Frijoles | C36: =IF(places!$A35="","",places!$Y35) -> Town | D36: 9.16964 | E36: -79.80337 | F36: ICC Surveys 1905-06 Map No.2 | G36: surveyed from SURVEYS1908 georef (occupied village; abandoned site also recorded), ±250m
A37: =IF(places!$A36="","",places!$A36) -> CZ-024 | B37: =IF(places!$A36="","",places!$B36) -> Paraiso | C37: =IF(places!$A36="","",places!$Y36) -> Town | D37: 9.02697 | E37: -79.62499 | F37: ICC1909 zone map | G37: surveyed from ICC1909 georef, ±300m
A38: =IF(places!$A37="","",places!$A37) -> CZ-025 | B38: =IF(places!$A37="","",places!$B37) -> San Pablo | C38: =IF(places!$A37="","",places!$Y37) -> Town | D38: 9.11867 | E38: -79.78701 | F38: ICC Surveys 1905-06 Map No.2 | G38: surveyed from SURVEYS1908 georef (probable village; label at fold), ±400m
A39: =IF(places!$A38="","",places!$A38) -> CZ-026 | B39: =IF(places!$A38="","",places!$B38) -> Tabernilla | C39: =IF(places!$A38="","",places!$Y38) -> Town | D39: 9.13351 | E39: -79.81839 | F39: ICC1911 property map | G39: surveyed from ICC1911 georef; NOTE sources disagree up to 1.2km - see candidate CSVs
A40: =IF(places!$A39="","",places!$A39) -> CZ-027 | B40: =IF(places!$A39="","",places!$B39) -> Gamboa | C40: =IF(places!$A39="","",places!$Y39) -> Town | D40: 9.11327 | E40: -79.69404 | F40: ICC Surveys 1905-06 Map No.2 | G40: surveyed from SURVEYS1908 georef, ±300m
... A56: =IF(places!$A55="","",places!$A55) -> CZ-044 | B56: =IF(places!$A55="","",places!$B55) -> Juan Grande | C56: =IF(places!$A55="","",places!$Y55) -> Town | D56: 9.11773 | E56: -79.7401 | F56: ICC Surveys 1905-06 Map No.2 | G56: surveyed from SURVEYS1908 georef, ±250m
A57: =IF(places!$A56="","",places!$A56) -> CZ-045 | B57: =IF(places!$A56="","",places!$B56) -> Gatuncillo | C57: =IF(places!$A56="","",places!$Y56) -> Town
A58: =IF(places!$A57="","",places!$A57) -> CZ-046 | B58: =IF(places!$A57="","",places!$B57) -> Balboa Heights | C58: =IF(places!$A57="","",places!$Y57) -> Town | D58: 8.961086 | E58: -79.557709 | F58: PACIFIC1947 (pcc00008) | G58: surveyed from the 1947 Pacific Terminal Cities georef (Administration Building), ±150m
A59: =IF(places!$A58="","",places!$A58) -> CZ-047 | B59: =IF(places!$A58="","",places!$B58) -> Chagres | C59: =IF(places!$A58="","",places!$Y58) -> Town | D59: 9.31083 | E59: -79.99787 | F59: ICC1911 property map | G59: surveyed from ICC1911 georef (village at Chagres mouth), ±300m [CORRECTED 2026-09-08: earlier paste had a transcription error]
A60: =IF(places!$A59="","",places!$A59) -> CZ-048 | B60: =IF(places!$A59="","",places!$B59) -> Palo Seco | C60: =IF(places!$A59="","",places!$Y59) -> Site/Institution | D60: 8.914292 | E60: -79.57066 | F60: CENSUS1940_PALOSECO (dwg 6100-90 boundary survey) | G60: tract centroid of the surveyed 346.75-acre colony boundary (graticule-true affine, residuals 3 m; internal bearing/distance checks 1-3%%). CORRECTED 2026-09-16: the M1947-derived point (8.914038,-79.557718) lies in the entrance-channel water ~1.4 km due E (its latitude was right; the longitude was off). Building compound not drawn on this boundary plot - tract-scale uncertainty +-400 m until a detailed plan surfaces.
A61: =IF(places!$A60="","",places!$A60) -> CZ-049 | B61: =IF(places!$A60="","",places!$B60) -> Darien | C61: =IF(places!$A60="","",places!$Y60) -> Town | D61: 9.11902 | E61: -79.774445 | F61: CZ 1947 zone map (1:100,000) | G61: surveyed from CZ1947 georef, +-150m
A62: =IF(places!$A61="","",places!$A61) -> CZ-050 | B62: =IF(places!$A61="","",places!$B61) -> Summit | C62: =IF(places!$A61="","",places!$Y61) -> Town | D62: 9.063583 | E62: -79.65358 | F62: CENSUS1940_SUMMIT (naId 5838616, graticule-true) | G62: station cluster (bldg 18B + Substation) on the relocated line, from the 1940 census sheet (+-15-40 m warp; unc 100 m). UPGRADED 2026-09-16 from the 1:100,000 M1947 symbol read, which sat 450 m N along the line - within 1:100k symbol slop, an upgrade not a conflict. The gardens road-web center lies 400 m E (A-2722); extent traced to footprints.geojson.
A63: =IF(places!$A62="","",places!$A62) -> CZ-051 | B63: =IF(places!$A62="","",places!$B62) -> Red Tank | C63: =IF(places!$A62="","",places!$Y62) -> Town | D63: 9.018107 | E63: -79.594194 | F63: CZ 1947 zone map (1:100,000) | G63: surveyed from CZ1947 georef, +-250m
A64: =IF(places!$A63="","",places!$A63) -> CZ-052 | B64: =IF(places!$A63="","",places!$B63) -> Camacho | C64: =IF(places!$A63="","",places!$Y63) -> Town | D64: 9.05199 | E64: -79.66356 | F64: ICC1911 property map | G64: surveyed from ICC1911 georef, ±400m
A65: =IF(places!$A64="","",places!$A64) -> CZ-053 | B65: =IF(places!$A64="","",places!$B64) -> Naos Island | C65: =IF(places!$A64="","",places!$Y64) -> Town | D65: 8.9151 | E65: -79.53248 | F65: ICC1911 property map | G65: surveyed from ICC1911 georef, ±400m
A66: =IF(places!$A65="","",places!$A65) -> CZ-054 | B66: =IF(places!$A65="","",places!$B65) -> El Vigia | C66: =IF(places!$A65="","",places!$Y65) -> Town | D66: 9.2178 | E66: -79.5923 | F66: ICC1909 zone map | G66: surveyed from ICC1909 georef (absence audit 2026-09-12), +-700m - FIRST FIX; off-anchor upper Chagres
A67: =IF(places!$A66="","",places!$A66) -> CZ-055 | B67: =IF(places!$A66="","",places!$B66) -> Diablo | C67: =IF(places!$A66="","",places!$Y66) -> Town | D67: 8.971828 | E67: -79.580679 | F67: CZ 1947 zone map (1:100,000) | G67: surveyed from CZ1947 georef, +-250m
A68: =IF(places!$A67="","",places!$A67) -> CZ-056 | B68: =IF(places!$A67="","",places!$B67) -> Agua Clara | C68: =IF(places!$A67="","",places!$Y67) -> Town
A69: =IF(places!$A68="","",places!$A68) -> CZ-057 | B69: =IF(places!$A68="","",places!$B68) -> Juan Mina | C69: =IF(places!$A68="","",places!$Y68) -> Town | D69: 9.1665 | E69: -79.6477 | F69: ICC1911 property map | G69: surveyed from ICC1911 georef (absence audit 2026-09-12), +-400m - FIRST FIX
A70: =IF(places!$A69="","",places!$A69) -> CZ-058 | B70: =IF(places!$A69="","",places!$B69) -> Enterprise | C70: =IF(places!$A69="","",places!$Y69) -> Town | D70: 9.03761 | E70: -79.64888 | F70: ICC1911 property map | G70: surveyed from ICC1911 georef, ±400m
A71: =IF(places!$A70="","",places!$A70) -> CZ-059 | B71: =IF(places!$A70="","",places!$B70) -> Whitehouse | C71: =IF(places!$A70="","",places!$Y70) -> Town | D71: 9.082689 | E71: -79.679139 | F71: Culebra Div. encampment plans 1907 | G71: surveyed from CULEBRACAMPS georef, +-200m (upgraded from ICC1909 +-300m; both claims in attestations)
A72: =IF(places!$A71="","",places!$A71) -> CZ-060 | B72: =IF(places!$A71="","",places!$B71) -> Vamos Vamos | C72: =IF(places!$A71="","",places!$Y71) -> Town | D72: 9.1903 | E72: -79.8818 | F72: CHAGRES1867 plano (1862) | G72: surveyed from CHAGRES1867 georef (absence audit 2026-09-13), +-800m - FIRST FIX; lower-river compression zone, treat as Low certainty
A73: =IF(places!$A72="","",places!$A72) -> CZ-061 | B73: =IF(places!$A72="","",places!$B72) -> Pena Blanca | C73: =IF(places!$A72="","",places!$Y72) -> Town | D73: 9.1789 | E73: -79.87034 | F73: ICC1909 zone map | G73: surveyed from ICC1909 georef, ±300m
A74: =IF(places!$A73="","",places!$A73) -> CZ-062 | B74: =IF(places!$A73="","",places!$B73) -> Cartagenita | C74: =IF(places!$A73="","",places!$Y73) -> Town | D74: 9.022738 | E74: -79.627856 | F74: Culebra Div. encampment plans 1907 | G74: surveyed from CULEBRACAMPS georef, +-250m (upgraded from ICC1909 +-300m; both claims in attestations)
A75: =IF(places!$A74="","",places!$A74) -> CZ-063 | B75: =IF(places!$A74="","",places!$B74) -> Palo Grande | C75: =IF(places!$A74="","",places!$Y74) -> Town | D75: 9.1362 | E75: -79.6727 | F75: ICC1909 zone map | G75: surveyed from ICC1909 georef (absence audit 2026-09-12), +-400m - FIRST FIX
A76: =IF(places!$A75="","",places!$A75) -> CZ-064 | B76: =IF(places!$A75="","",places!$B75) -> Cocoli | C76: =IF(places!$A75="","",places!$Y75) -> Town | D76: 8.98925 | E76: -79.5891 | F76: ICC1911 property map | G76: surveyed from ICC1911 georef, ±400m
A77: =IF(places!$A76="","",places!$A76) -> CZ-065 | B77: =IF(places!$A76="","",places!$B76) -> Margarita | C77: =IF(places!$A76="","",places!$Y76) -> Town | D77: 9.328791 | E77: -79.892112 | F77: CZ 1947 zone map (1:100,000) | G77: surveyed from CZ1947 georef, +-250m
A78: =IF(places!$A77="","",places!$A77) -> CZ-066 | B78: =IF(places!$A77="","",places!$B77) -> Coco Solo | C78: =IF(places!$A77="","",places!$Y77) -> Town | D78: 9.369818 | E78: -79.87231 | F78: CZ 1947 zone map (1:100,000) | G78: surveyed from CZ1947 georef, +-250m
A79: =IF(places!$A78="","",places!$A78) -> CZ-067 | B79: =IF(places!$A78="","",places!$B78) -> Fort Clayton | C79: =IF(places!$A78="","",places!$Y78) -> Town | D79: 9.003434 | E79: -79.588109 | F79: CZ 1947 zone map (1:100,000) | G79: surveyed from CZ1947 georef, +-250m
A80: =IF(places!$A79="","",places!$A79) -> CZ-068 | B80: =IF(places!$A79="","",places!$B79) -> Fort Davis | C80: =IF(places!$A79="","",places!$Y79) -> Town | D80: 9.295601 | E80: -79.892565 | F80: CZ 1947 zone map (1:100,000) | G80: surveyed from CZ1947 georef, +-250m
... A97: =IF(places!$A96="","",places!$A96) -> CZ-085 | B97: =IF(places!$A96="","",places!$B96) -> Palo Matias Viejo | C97: =IF(places!$A96="","",places!$Y96) -> Town | D97: 9.19856 | E97: -79.89502 | F97: ICC1909 zone map | G97: surveyed from ICC1909 georef, +-400m
A98: =IF(places!$A97="","",places!$A97) -> CZ-086 | B98: =IF(places!$A97="","",places!$B97) -> Whitehouse | C98: =IF(places!$A97="","",places!$Y97) -> Town
A99: =IF(places!$A98="","",places!$A98) -> CZ-087 | B99: =IF(places!$A98="","",places!$B98) -> Cartagena | C99: =IF(places!$A98="","",places!$Y98) -> Town
A100: =IF(places!$A99="","",places!$A99) -> CZ-110 | B100: =IF(places!$A99="","",places!$B99) -> Spanish Town | C100: =IF(places!$A99="","",places!$Y99) -> Town | D100: 9.02964 | E100: -79.62291 | F100: ICC1911 property map | G100: surveyed from ICC1911 georef (audit read 2026-09-12), +-350m
A101: =IF(places!$A100="","",places!$A100) -> CZ-111 | B101: =IF(places!$A100="","",places!$B100) -> Golden Green | C101: =IF(places!$A100="","",places!$Y100) -> Town | D101: 9.0556 | E101: -79.6624 | F101: ICC1911 property map | G101: surveyed from ICC1911 georef, +-350m [CORRECTED 2026-09-13 footprint pass: first read mis-assigned the dot cluster ~1.1km; label-adjacent dots re-verified]
A102: =IF(places!$A101="","",places!$A101) -> CZ-112 | B102: =IF(places!$A101="","",places!$B101) -> Carabali | C102: =IF(places!$A101="","",places!$Y101) -> Town | D102: 9.10458 | E102: -79.72207 | F102: ICC1911 property map | G102: surveyed from ICC1911 georef (audit read 2026-09-12), +-500m
A103: =IF(places!$A102="","",places!$A102) -> CZ-113 | B103: =IF(places!$A102="","",places!$B102) -> Casa Larga | C103: =IF(places!$A102="","",places!$Y102) -> Town | D103: 9.184 | E103: -79.565 | F103: ICC1909 zone map | G103: surveyed from ICC1909 georef (audit read 2026-09-12), +-500m - off-anchor upper Chagres
A104: =IF(places!$A103="","",places!$A103) -> CZ-114 | B104: =IF(places!$A103="","",places!$B103) -> San Juan | C104: =IF(places!$A103="","",places!$Y103) -> Town | D104: 9.2528 | E104: -79.5793 | F104: ICC1909 zone map | G104: surveyed from ICC1909 georef (audit read 2026-09-12), +-600m - off-anchor upper Chagres
A105: =IF(places!$A104="","",places!$A104) -> CZ-115 | B105: =IF(places!$A104="","",places!$B104) -> Tranquilla | C105: =IF(places!$A104="","",places!$Y104) -> Town | D105: 9.2383 | E105: -79.5664 | F105: ICC1909 zone map | G105: surveyed from ICC1909 georef (audit read 2026-09-12), +-600m - off-anchor upper Chagres
A106: =IF(places!$A105="","",places!$A105) -> CZ-116 | B106: =IF(places!$A105="","",places!$B105) -> Dos Bocas | C106: =IF(places!$A105="","",places!$Y105) -> Town | D106: 9.2379 | E106: -79.5777 | F106: ICC1909 zone map | G106: surveyed from ICC1909 georef (audit read 2026-09-12), +-700m - off-anchor upper Chagres
A107: =IF(places!$A106="","",places!$A106) -> CZ-117 | B107: =IF(places!$A106="","",places!$B106) -> Campanas | C107: =IF(places!$A106="","",places!$Y106) -> Town | D107: 9.2249 | E107: -79.5986 | F107: ICC1909 zone map | G107: surveyed from ICC1909 georef (audit read 2026-09-12), +-600m - off-anchor upper Chagres
A108: =IF(places!$A107="","",places!$A107) -> CZ-118 | B108: =IF(places!$A107="","",places!$B107) -> Empire Court House | C108: =IF(places!$A107="","",places!$Y107) -> Building | D108: 9.061692 | E108: -79.67224 | F108: General map of Empire (re-anchored) | G108: surveyed from EMPIRE plan georef re-anchored to SURVEYS1908_MAP3, +-200m
A109: =IF(places!$A108="","",places!$A108) -> CZ-119 | B109: =IF(places!$A108="","",places!$B108) -> Empire Freight House | C109: =IF(places!$A108="","",places!$Y108) -> Infrastructure | D109: 9.062414 | E109: -79.671114 | F109: General map of Empire (re-anchored) | G109: surveyed from EMPIRE plan georef re-anchored to SURVEYS1908_MAP3, +-200m
A110: =IF(places!$A109="","",places!$A109) -> CZ-120 | B110: =IF(places!$A109="","",places!$B109) -> Empire Base Ball Park | C110: =IF(places!$A109="","",places!$Y109) -> Site/Institution | D110: 9.06025 | E110: -79.67185 | F110: General map of Empire (re-anchored) | G110: surveyed from EMPIRE plan georef re-anchored to SURVEYS1908_MAP3, +-200m
A111: =IF(places!$A110="","",places!$A110) -> CZ-121 | B111: =IF(places!$A110="","",places!$B110) -> Empire I.C.C. Hotel | C111: =IF(places!$A110="","",places!$Y110) -> Building | D111: 9.062074 | E111: -79.66997 | F111: General map of Empire (re-anchored) | G111: surveyed from EMPIRE plan georef re-anchored to SURVEYS1908_MAP3, +-200m
... A161: =IF(places!$A160="","",places!$A160) -> CZ-171 | B161: =IF(places!$A160="","",places!$B160) -> Cocoli (townsite) | C161: =IF(places!$A160="","",places!$Y160) -> Town | D161: 8.976334 | E161: -79.60029 | F161: M1947 (read 2026-09-08) | G161: surveyed from M1947 georef, +-300m (repointed from CZ-064)
A162: =IF(places!$A161="","",places!$A161) -> CZ-172 | B162: =IF(places!$A161="","",places!$B161) -> Pedro Miguel (as-built) | C162: =IF(places!$A161="","",places!$Y161) -> Town
A163: =IF(places!$A162="","",places!$A162) -> CZ-173 | B163: =IF(places!$A162="","",places!$B162) -> New Frijoles | C163: =IF(places!$A162="","",places!$Y162) -> Town | D163: 9.1756 | E163: -79.80133 | F163: ICC1911 (A-0495, repointed) | G163: surveyed from ICC1911 georef, +-250m (repointed from CZ-023)
A164: =IF(places!$A163="","",places!$A163) -> CZ-174 | B164: =IF(places!$A163="","",places!$B163) -> Jamaica Town (Gorgona) | C164: =IF(places!$A163="","",places!$Y163) -> Neighborhood
A165: =IF(places!$A164="","",places!$A164) -> CZ-175 | B165: =IF(places!$A164="","",places!$B164) -> Camacho (Empire) | C165: =IF(places!$A164="","",places!$Y164) -> Neighborhood
A166: =IF(places!$A165="","",places!$A165) -> CZ-176 | B166: =IF(places!$A165="","",places!$B165) -> Bishop's Hollow (Ancon) | C166: =IF(places!$A165="","",places!$Y165) -> Neighborhood
A167: =IF(places!$A166="","",places!$A166) -> CZ-177 | B167: =IF(places!$A166="","",places!$B166) -> Banana Walk (Matachin) | C167: =IF(places!$A166="","",places!$Y166) -> Neighborhood
A168: =IF(places!$A167="","",places!$A167) -> CZ-178 | B168: =IF(places!$A167="","",places!$B167) -> Rio Grande works (Culebra) | C168: =IF(places!$A167="","",places!$Y167) -> Site/Institution
A169: =IF(places!$A168="","",places!$A168) -> CZ-179 | B169: =IF(places!$A168="","",places!$B168) -> Culebra Police Station (145) | C169: =IF(places!$A168="","",places!$Y168) -> Building | D169: 9.037 | E169: -79.6463 | F169: Map of Culebra 1910 (S-023) | G169: surveyed from CULEBRA1910 georef (audit read), +-150m
A170: =IF(places!$A169="","",places!$A169) -> CZ-180 | B170: =IF(places!$A169="","",places!$B169) -> Culebra Penitentiary (173) | C170: =IF(places!$A169="","",places!$Y169) -> Building | D170: 9.0367 | E170: -79.6466 | F170: Map of Culebra 1910 (S-023) | G170: surveyed from CULEBRA1910 georef (audit read), +-150m
A171: =IF(places!$A170="","",places!$A170) -> CZ-181 | B171: =IF(places!$A170="","",places!$B170) -> Culebra Pumping Station (146) | C171: =IF(places!$A170="","",places!$Y170) -> Building | D171: 9.0361 | E171: -79.6471 | F171: Map of Culebra 1910 (S-023) | G171: surveyed from CULEBRA1910 georef (audit read), +-150m
A172: =IF(places!$A171="","",places!$A171) -> CZ-182 | B172: =IF(places!$A171="","",places!$B171) -> Diablo Heights | C172: =IF(places!$A171="","",places!$Y171) -> Town | D172: 8.9744 | E172: -79.5738 | F172: PACIFIC1947 (harvest 2026-09-14) | G172: surveyed from PACIFIC1947 georef (graticule-true sheet; letters+club-house spread), +-200m
A173: =IF(places!$A172="","",places!$A172) -> CZ-183 | B173: =IF(places!$A172="","",places!$B172) -> Barro Colorado (village) | C173: =IF(places!$A172="","",places!$Y172) -> Town | D173: 9.1988 | E173: -79.8036 | F173: PRR1857 (harvest 2026-09-14) | G173: surveyed from PRR1857 georef (Totten isthmus map; interior region), +-800m
A174: =IF(places!$A173="","",places!$A173) -> CZ-184 | B174: =IF(places!$A173="","",places!$B173) -> Rio Indio Settlement | C174: =IF(places!$A173="","",places!$Y173) -> Town | D174: 9.2568 | E174: -79.9282 | F174: PRR1857 (harvest 2026-09-14) | G174: surveyed from PRR1857 georef (Totten isthmus map), +-500m per region
A175: =IF(places!$A174="","",places!$A174) -> CZ-185 | B175: =IF(places!$A174="","",places!$B174) -> Palo Matias Nuevo | C175: =IF(places!$A174="","",places!$Y174) -> Town | D175: 9.2119 | E175: -79.9066 | F175: PRR1857 (harvest 2026-09-14) | G175: surveyed from PRR1857 georef (Totten isthmus map), +-500m per region
A176: =IF(places!$A175="","",places!$A175) -> CZ-186 | B176: =IF(places!$A175="","",places!$B175) -> Palo Horqueta | C176: =IF(places!$A175="","",places!$Y175) -> Town | D176: 9.2093 | E176: -79.8992 | F176: PRR1857 (harvest 2026-09-14) | G176: surveyed from PRR1857 georef (Totten isthmus map), +-500m per region
A177: =IF(places!$A176="","",places!$A176) -> CZ-187 | B177: =IF(places!$A176="","",places!$B176) -> Palenquillo | C177: =IF(places!$A176="","",places!$Y176) -> Town | D177: 9.2295 | E177: -79.877 | F177: PRR1857 (harvest 2026-09-14) | G177: surveyed from PRR1857 georef (Totten isthmus map), +-500m per region
A178: =IF(places!$A177="","",places!$A177) -> CZ-188 | B178: =IF(places!$A177="","",places!$B177) -> Pedro Bernal's Settlement | C178: =IF(places!$A177="","",places!$Y177) -> Town | D178: 9.113 | E178: -79.8 | F178: PRR1857 (harvest 2026-09-14) | G178: surveyed from PRR1857 georef (Totten isthmus map), +-800m per region
A179: =IF(places!$A178="","",places!$A178) -> CZ-189 | B179: =IF(places!$A178="","",places!$B178) -> Mari Posa | C179: =IF(places!$A178="","",places!$Y178) -> Town | D179: 9.093 | E179: -79.71 | F179: PRR1857 (harvest 2026-09-14) | G179: surveyed from PRR1857 georef (Totten isthmus map), +-800m per region
A180: =IF(places!$A179="","",places!$A179) -> CZ-190 | B180: =IF(places!$A179="","",places!$B179) -> Noreza | C180: =IF(places!$A179="","",places!$Y179) -> Town | D180: 9.08 | E180: -79.7 | F180: PRR1857 (harvest 2026-09-14) | G180: surveyed from PRR1857 georef (Totten isthmus map), +-800m per region
... A202: =IF(places!$A201="","",places!$A201) -> CZ-214 | B202: =IF(places!$A201="","",places!$B201) -> Fort de Lesseps | C202: =IF(places!$A201="","",places!$Y201) -> Site/Institution | D202: 9.364954 | E202: -79.91031 | F202: FDL1000 (naId 5838610, dwg 6056-5, 1:1,000) | G202: fort built-cluster center from the dedicated 1:1,000 Section of Surveys reservation plan (compass + graphical-scale fit anchored on the Washington Hotel; pool cross-check 19 m, battery arc vs CENSUS1940_COLON 17 m; +-20-40 m). Supersedes the 2026-09-16 label-midpoint fix.
A203: =IF(places!$A202="","",places!$A202) -> CZ-215 | B203: =IF(places!$A202="","",places!$B202) -> Jamaica Town (Gatún) | C203: =IF(places!$A202="","",places!$Y202) -> Neighborhood
A204: =IF(places!$A203="","",places!$A203) -> CZ-216 | B204: =IF(places!$A203="","",places!$B203) -> Dos Hermanas | C204: =IF(places!$A203="","",places!$Y203) -> Town | D204: 9.2194 | E204: -79.8909 | F204: PK interpolation, 1886 Plan General (S-051) | G204: interpolated along canal kilometrage at PK ~16 between Tiger Hill and Bohio, +-2000m; approximate (canal meanders; perpendicular offset unknown) [2026-09-14]
...

Sheet places
A1: place_id (PK) | B1: preferred_name | C1: variant_names | D1: place_type | E1: erasure_type | F1: erasure_mechanism | G1: historical_theme | H1: population_type | I1: start_date | J1: end_date | K1: date_certainty | L1: spatial_certainty | M1: render_as (auto) | N1: uncertainty_radius_m | O1: archival_traces (auto) | P1: n_map (auto) | Q1: n_image (auto) | R1: n_textual (auto) | S1: n_geom (auto) | T1: archival_visibility (auto) | U1: has_surveyed_coord (auto) | V1: shortlist_status | W1: priority | X1: notes | Y1: scale | Z1: parent_id (FK) | AA1: card_note
A2: CZ-001 | B2: Matachin | C2: Matachin; Bas Matachin | D2: Station | E2: Submerged | F2: Gatun Lake flooding | G2: Displacement | H2: Panamanian village | I2: pre-1850? | J2: 1911-1914 | K2: Approximate | L2: Low | M2: =IF($A2="","",IF($L2="High","Solid point",IF($L2="Medium","Point + buffer",IF($L2="Low","Translucent area",IF($L2="Disputed","Candidate points",IF($L2="Unknown","Unplotted (unlocated panel)","-")))))) -> Translucent area | N2: 300 | O2: =IF($A2="","",COUNTIF(attestations!$B$2:$B$2000,$A2)) -> 30 | P2: =IF($A2="","",COUNTIFS(attestations!$B$2:$B$2000,$A2,attestations!$R$2:$R$2000,"Map")) -> 3 | Q2: =IF($A2="","",COUNTIFS(attestations!$B$2:$B$2000,$A2,attestations!$R$2:$R$2000,"Image")) -> 1 | R2: =IF($A2="","",COUNTIFS(attestations!$B$2:$B$2000,$A2,attestations!$R$2:$R$2000,"Textual")) -> 7 | S2: =IF($A2="","",COUNTIFS(attestations!$B$2:$B$2000,$A2,attestations!$D$2:$D$2000,"Geometry (Setting)")) -> 7 | T2: =IF($A2="","",IF($O2>=6,"High",IF($O2>=3,"Medium",IF($O2>=1,"Low","None")))) -> High | U2: =IF($A2="","",IF(COUNTIFS(attestations!$B$2:$B$2000,$A2,attestations!$I$2:$I$2000,"Georeferenced map GCP")>0,"Y","N")) -> Y | V2: Candidate | X2: Railroad-era Chagres town. | Y2: Town
A3: CZ-002 | B3: Barbacoas | D3: Village | E3: Submerged | F3: Gatun Lake flooding | G3: Displacement | H3: Panamanian village | I3: pre-1844 | J3: 1911-1914 | K3: Approximate | L3: Low | M3: =IF($A3="","",IF($L3="High","Solid point",IF($L3="Medium","Point + buffer",IF($L3="Low","Translucent area",IF($L3="Disputed","Candidate points",IF($L3="Unknown","Unplotted (unlocated panel)","-")))))) -> Translucent area | N3: 400 | O3: =IF($A3="","",COUNTIF(attestations!$B$2:$B$2000,$A3)) -> 19 | P3: =IF($A3="","",COUNTIFS(attestations!$B$2:$B$2000,$A3,attestations!$R$2:$R$2000,"Map")) -> 1 | Q3: =IF($A3="","",COUNTIFS(attestations!$B$2:$B$2000,$A3,attestations!$R$2:$R$2000,"Image")) -> 1 | R3: =IF($A3="","",COUNTIFS(attestations!$B$2:$B$2000,$A3,attestations!$R$2:$R$2000,"Textual")) -> 6 | S3: =IF($A3="","",COUNTIFS(attestations!$B$2:$B$2000,$A3,attestations!$D$2:$D$2000,"Geometry (Setting)")) -> 5 | T3: =IF($A3="","",IF($O3>=6,"High",IF($O3>=3,"Medium",IF($O3>=1,"Low","None")))) -> High | U3: =IF($A3="","",IF(COUNTIFS(attestations!$B$2:$B$2000,$A3,attestations!$I$2:$I$2000,"Georeferenced map GCP")>0,"Y","N")) -> Y | V3: Candidate | X3: Bridge-site history. | Y3: Town
A4: CZ-003 | B4: Cruces | C4: Cruces; Las Cruces; Venta Cruz | D4: Village | E4: Submerged | F4: Gatun Lake flooding | G4: Displacement | H4: Panamanian village | I4: c.1530 | J4: 1911-1914 | K4: Approximate | L4: Low | M4: =IF($A4="","",IF($L4="High","Solid point",IF($L4="Medium","Point + buffer",IF($L4="Low","Translucent area",IF($L4="Disputed","Candidate points",IF($L4="Unknown","Unplotted (unlocated panel)","-")))))) -> Translucent area | N4: 400 | O4: =IF($A4="","",COUNTIF(attestations!$B$2:$B$2000,$A4)) -> 27 | P4: =IF($A4="","",COUNTIFS(attestations!$B$2:$B$2000,$A4,attestations!$R$2:$R$2000,"Map")) -> 3 | Q4: =IF($A4="","",COUNTIFS(attestations!$B$2:$B$2000,$A4,attestations!$R$2:$R$2000,"Image")) -> 1 | R4: =IF($A4="","",COUNTIFS(attestations!$B$2:$B$2000,$A4,attestations!$R$2:$R$2000,"Textual")) -> 8 | S4: =IF($A4="","",COUNTIFS(attestations!$B$2:$B$2000,$A4,attestations!$D$2:$D$2000,"Geometry (Setting)")) -> 6 | T4: =IF($A4="","",IF($O4>=6,"High",IF($O4>=3,"Medium",IF($O4>=1,"Low","None")))) -> High | U4: =IF($A4="","",IF(COUNTIFS(attestations!$B$2:$B$2000,$A4,attestations!$I$2:$I$2000,"Georeferenced map GCP")>0,"Y","N")) -> Y | V4: Candidate | W4: High | X4: Colonial trail terminus. | Y4: Town
A5: CZ-004 | B5: Ahorca Lagarto | D5: Hamlet | E5: Submerged | F5: Gatun Lake flooding | G5: Displacement | H5: Panamanian village | J5: 1911-1914 | K5: Unknown | L5: Medium | M5: =IF($A5="","",IF($L5="High","Solid point",IF($L5="Medium","Point + buffer",IF($L5="Low","Translucent area",IF($L5="Disputed","Candidate points",IF($L5="Unknown","Unplotted (unlocated panel)","-")))))) -> Point + buffer | N5: 250 | O5: =IF($A5="","",COUNTIF(attestations!$B$2:$B$2000,$A5)) -> 17 | P5: =IF($A5="","",COUNTIFS(attestations!$B$2:$B$2000,$A5,attestations!$R$2:$R$2000,"Map")) -> 1 | Q5: =IF($A5="","",COUNTIFS(attestations!$B$2:$B$2000,$A5,attestations!$R$2:$R$2000,"Image")) -> 0 | R5: =IF($A5="","",COUNTIFS(attestations!$B$2:$B$2000,$A5,attestations!$R$2:$R$2000,"Textual")) -> 6 | S5: =IF($A5="","",COUNTIFS(attestations!$B$2:$B$2000,$A5,attestations!$D$2:$D$2000,"Geometry (Setting)")) -> 5 | T5: =IF($A5="","",IF($O5>=6,"High",IF($O5>=3,"Medium",IF($O5>=1,"Low","None")))) -> High | U5: =IF($A5="","",IF(COUNTIFS(attestations!$B$2:$B$2000,$A5,attestations!$I$2:$I$2000,"Georeferenced map GCP")>0,"Y","N")) -> Y | V5: Candidate | X5: Name-only test case -> unlocated panel. | Y5: Town
A6: CZ-005 | B6: Caimito | D6: Hamlet | E6: Submerged | F6: Gatun Lake flooding | G6: Displacement | H6: Panamanian village | J6: 1911-1914 | K6: Unknown | L6: Low | M6: =IF($A6="","",IF($L6="High","Solid point",IF($L6="Medium","Point + buffer",IF($L6="Low","Translucent area",IF($L6="Disputed","Candidate points",IF($L6="Unknown","Unplotted (unlocated panel)","-")))))) -> Translucent area | N6: 500 | O6: =IF($A6="","",COUNTIF(attestations!$B$2:$B$2000,$A6)) -> 16 | P6: =IF($A6="","",COUNTIFS(attestations!$B$2:$B$2000,$A6,attestations!$R$2:$R$2000,"Map")) -> 1 | Q6: =IF($A6="","",COUNTIFS(attestations!$B$2:$B$2000,$A6,attestations!$R$2:$R$2000,"Image")) -> 1 | R6: =IF($A6="","",COUNTIFS(attestations!$B$2:$B$2000,$A6,attestations!$R$2:$R$2000,"Textual")) -> 6 | S6: =IF($A6="","",COUNTIFS(attestations!$B$2:$B$2000,$A6,attestations!$D$2:$D$2000,"Geometry (Setting)")) -> 1 | T6: =IF($A6="","",IF($O6>=6,"High",IF($O6>=3,"Medium",IF($O6>=1,"Low","None")))) -> High | U6: =IF($A6="","",IF(COUNTIFS(attestations!$B$2:$B$2000,$A6,attestations!$I$2:$I$2000,"Georeferenced map GCP")>0,"Y","N")) -> Y | V6: Candidate | Y6: Town
A7: CZ-006 | B7: Santa Cruz | D7: Hamlet | E7: Submerged | F7: Gatun Lake flooding | G7: Displacement | H7: Panamanian village | J7: 1911-1914 | K7: Unknown | L7: Low | M7: =IF($A7="","",IF($L7="High","Solid point",IF($L7="Medium","Point + buffer",IF($L7="Low","Translucent area",IF($L7="Disputed","Candidate points",IF($L7="Unknown","Unplotted (unlocated panel)","-")))))) -> Translucent area | N7: 400 | O7: =IF($A7="","",COUNTIF(attestations!$B$2:$B$2000,$A7)) -> 18 | P7: =IF($A7="","",COUNTIFS(attestations!$B$2:$B$2000,$A7,attestations!$R$2:$R$2000,"Map")) -> 2 | Q7: =IF($A7="","",COUNTIFS(attestations!$B$2:$B$2000,$A7,attestations!$R$2:$R$2000,"Image")) -> 1 | R7: =IF($A7="","",COUNTIFS(attestations!$B$2:$B$2000,$A7,attestations!$R$2:$R$2000,"Textual")) -> 6 | S7: =IF($A7="","",COUNTIFS(attestations!$B$2:$B$2000,$A7,attestations!$D$2:$D$2000,"Geometry (Setting)")) -> 3 | T7: =IF($A7="","",IF($O7>=6,"High",IF($O7>=3,"Medium",IF($O7>=1,"Low","None")))) -> High | U7: =IF($A7="","",IF(COUNTIFS(attestations!$B$2:$B$2000,$A7,attestations!$I$2:$I$2000,"Georeferenced map GCP")>0,"Y","N")) -> Y | V7: Candidate | Y7: Town
A8: CZ-007 | B8: Bailamonos | D8: Hamlet | E8: Submerged | F8: Gatun Lake flooding | G8: Displacement | H8: Panamanian village | J8: 1911-1914 | K8: Unknown | L8: Low | M8: =IF($A8="","",IF($L8="High","Solid point",IF($L8="Medium","Point + buffer",IF($L8="Low","Translucent area",IF($L8="Disputed","Candidate points",IF($L8="Unknown","Unplotted (unlocated panel)","-")))))) -> Translucent area | N8: 800 | O8: =IF($A8="","",COUNTIF(attestations!$B$2:$B$2000,$A8)) -> 20 | P8: =IF($A8="","",COUNTIFS(attestations!$B$2:$B$2000,$A8,attestations!$R$2:$R$2000,"Map")) -> 1 | Q8: =IF($A8="","",COUNTIFS(attestations!$B$2:$B$2000,$A8,attestations!$R$2:$R$2000,"Image")) -> 0 | R8: =IF($A8="","",COUNTIFS(attestations!$B$2:$B$2000,$A8,attestations!$R$2:$R$2000,"Textual")) -> 6 | S8: =IF($A8="","",COUNTIFS(attestations!$B$2:$B$2000,$A8,attestations!$D$2:$D$2000,"Geometry (Setting)")) -> 4 | T8: =IF($A8="","",IF($O8>=6,"High",IF($O8>=3,"Medium",IF($O8>=1,"Low","None")))) -> High | U8: =IF($A8="","",IF(COUNTIFS(attestations!$B$2:$B$2000,$A8,attestations!$I$2:$I$2000,"Georeferenced map GCP")>0,"Y","N")) -> Y | V8: Candidate | Y8: Town
A9: CZ-008 | B9: Cruz de Juan Gallego | D9: Hamlet | E9: Submerged | F9: Gatun Lake flooding | G9: Displacement | H9: Panamanian village | J9: 1911-1914 | K9: Unknown | L9: Low | M9: =IF($A9="","",IF($L9="High","Solid point",IF($L9="Medium","Point + buffer",IF($L9="Low","Translucent area",IF($L9="Disputed","Candidate points",IF($L9="Unknown","Unplotted (unlocated panel)","-")))))) -> Translucent area | N9: 1000 | O9: =IF($A9="","",COUNTIF(attestations!$B$2:$B$2000,$A9)) -> 15 | P9: =IF($A9="","",COUNTIFS(attestations!$B$2:$B$2000,$A9,attestations!$R$2:$R$2000,"Map")) -> 0 | Q9: =IF($A9="","",COUNTIFS(attestations!$B$2:$B$2000,$A9,attestations!$R$2:$R$2000,"Image")) -> 1 | R9: =IF($A9="","",COUNTIFS(attestations!$B$2:$B$2000,$A9,attestations!$R$2:$R$2000,"Textual")) -> 3 | S9: =IF($A9="","",COUNTIFS(attestations!$B$2:$B$2000,$A9,attestations!$D$2:$D$2000,"Geometry (Setting)")) -> 1 | T9: =IF($A9="","",IF($O9>=6,"High",IF($O9>=3,"Medium",IF($O9>=1,"Low","None")))) -> High | U9: =IF($A9="","",IF(COUNTIFS(attestations!$B$2:$B$2000,$A9,attestations!$I$2:$I$2000,"Georeferenced map GCP")>0,"Y","N")) -> Y | V9: Candidate | Y9: Town
A10: CZ-009 | B10: Old Gatun | C10: Gatun (old village); De Lesseps City | D10: Village | E10: Submerged | F10: Gatun Dam construction | G10: Displacement | H10: Mixed | I10: pre-1844 | J10: 1911-1912 | K10: Approximate | L10: Low | M10: =IF($A10="","",IF($L10="High","Solid point",IF($L10="Medium","Point + buffer",IF($L10="Low","Translucent area",IF($L10="Disputed","Candidate points",IF($L10="Unknown","Unplotted (unlocated panel)","-")))))) -> Translucent area | N10: 500 | O10: =IF($A10="","",COUNTIF(attestations!$B$2:$B$2000,$A10)) -> 28 | P10: =IF($A10="","",COUNTIFS(attestations!$B$2:$B$2000,$A10,attestations!$R$2:$R$2000,"Map")) -> 3 | Q10: =IF($A10="","",COUNTIFS(attestations!$B$2:$B$2000,$A10,attestations!$R$2:$R$2000,"Image")) -> 3 | R10: =IF($A10="","",COUNTIFS(attestations!$B$2:$B$2000,$A10,attestations!$R$2:$R$2000,"Textual")) -> 9 | S10: =IF($A10="","",COUNTIFS(attestations!$B$2:$B$2000,$A10,attestations!$D$2:$D$2000,"Geometry (Setting)")) -> 6 | T10: =IF($A10="","",IF($O10>=6,"High",IF($O10>=3,"Medium",IF($O10>=1,"Low","None")))) -> High | U10: =IF($A10="","",IF(COUNTIFS(attestations!$B$2:$B$2000,$A10,attestations!$I$2:$I$2000,"Georeferenced map GCP")>0,"Y","N")) -> Y | V10: Candidate | W10: High | X10: Under ~80 ft dam fill. Abandoned 1908; site submerged 1911-1912 (A-0079). | Y10: Town
A11: CZ-010 | B11: New Gatun | C11: New Gatun; Nuevo Gatun | D11: Town | E11: Relocated | F11: Railroad relocation | G11: Displacement | H11: Mixed | I11: 1908 | K11: Approximate | L11: Medium | M11: =IF($A11="","",IF($L11="High","Solid point",IF($L11="Medium","Point + buffer",IF($L11="Low","Translucent area",IF($L11="Disputed","Candidate points",IF($L11="Unknown","Unplotted (unlocated panel)","-")))))) -> Point + buffer | N11: 250 | O11: =IF($A11="","",COUNTIF(attestations!$B$2:$B$2000,$A11)) -> 17 | P11: =IF($A11="","",COUNTIFS(attestations!$B$2:$B$2000,$A11,attestations!$R$2:$R$2000,"Map")) -> 1 | Q11: =IF($A11="","",COUNTIFS(attestations!$B$2:$B$2000,$A11,attestations!$R$2:$R$2000,"Image")) -> 1 | R11: =IF($A11="","",COUNTIFS(attestations!$B$2:$B$2000,$A11,attestations!$R$2:$R$2000,"Textual")) -> 5 | S11: =IF($A11="","",COUNTIFS(attestations!$B$2:$B$2000,$A11,attestations!$D$2:$D$2000,"Geometry (Setting)")) -> 4 | T11: =IF($A11="","",IF($O11>=6,"High",IF($O11>=3,"Medium",IF($O11>=1,"Low","None")))) -> High | U11: =IF($A11="","",IF(COUNTIFS(attestations!$B$2:$B$2000,$A11,attestations!$I$2:$I$2000,"Georeferenced map GCP")>0,"Y","N")) -> Y | V11: Candidate | W11: Medium | X11: Receiving town. | Y11: Town
A12: CZ-011 | B12: Empire | C12: Empire; Emperador; Alto Emperador | D12: Town | E12: Depopulated-not flooded | F12: 1912 depopulation order | G12: Labor | H12: Mixed | I12: c.1880s | J12: 1912-1916 | K12: Approximate | L12: Medium | M12: =IF($A12="","",IF($L12="High","Solid point",IF($L12="Medium","Point + buffer",IF($L12="Low","Translucent area",IF($L12="Disputed","Candidate points",IF($L12="Unknown","Unplotted (unlocated panel)","-")))))) -> Point + buffer | N12: 300 | O12: =IF($A12="","",COUNTIF(attestations!$B$2:$B$2000,$A12)) -> 35 | P12: =IF($A12="","",COUNTIFS(attestations!$B$2:$B$2000,$A12,attestations!$R$2:$R$2000,"Map")) -> 3 | Q12: =IF($A12="","",COUNTIFS(attestations!$B$2:$B$2000,$A12,attestations!$R$2:$R$2000,"Image")) -> 4 | R12: =IF($A12="","",COUNTIFS(attestations!$B$2:$B$2000,$A12,attestations!$R$2:$R$2000,"Textual")) -> 9 | S12: =IF($A12="","",COUNTIFS(attestations!$B$2:$B$2000,$A12,attestations!$D$2:$D$2000,"Geometry (Setting)")) -> 9 | T12: =IF($A12="","",IF($O12>=6,"High",IF($O12>=3,"Medium",IF($O12>=1,"Low","None")))) -> High | U12: =IF($A12="","",IF(COUNTIFS(attestations!$B$2:$B$2000,$A12,attestations!$I$2:$I$2000,"Georeferenced map GCP")>0,"Y","N")) -> Y | V12: Candidate | W12: High | X12: Keystone intentional-silence case. | Y12: Town
A13: CZ-012 | B13: Gorgona | C13: Gorgona; New Gorgona | D13: Town | E13: Depopulated-not flooded | F13: 1912 depopulation order | G13: Labor | H13: Mixed | I13: pre-1844 | J13: 1912-1915 | K13: Approximate | L13: Medium | M13: =IF($A13="","",IF($L13="High","Solid point",IF($L13="Medium","Point + buffer",IF($L13="Low","Translucent area",IF($L13="Disputed","Candidate points",IF($L13="Unknown","Unplotted (unlocated panel)","-")))))) -> Point + buffer | N13: 300 | O13: =IF($A13="","",COUNTIF(attestations!$B$2:$B$2000,$A13)) -> 34 | P13: =IF($A13="","",COUNTIFS(attestations!$B$2:$B$2000,$A13,attestations!$R$2:$R$2000,"Map")) -> 4 | Q13: =IF($A13="","",COUNTIFS(attestations!$B$2:$B$2000,$A13,attestations!$R$2:$R$2000,"Image")) -> 2 | R13: =IF($A13="","",COUNTIFS(attestations!$B$2:$B$2000,$A13,attestations!$R$2:$R$2000,"Textual")) -> 8 | S13: =IF($A13="","",COUNTIFS(attestations!$B$2:$B$2000,$A13,attestations!$D$2:$D$2000,"Geometry (Setting)")) -> 8 | T13: =IF($A13="","",IF($O13>=6,"High",IF($O13>=3,"Medium",IF($O13>=1,"Low","None")))) -> High | U13: =IF($A13="","",IF(COUNTIFS(attestations!$B$2:$B$2000,$A13,attestations!$I$2:$I$2000,"Georeferenced map GCP")>0,"Y","N")) -> Y | V13: Candidate | W13: High | X13: Well-documented depopulation. | Y13: Town
A14: CZ-013 | B14: Culebra | D14: Town | E14: Depopulated-not flooded | F14: 1912 depopulation order | G14: U.S. administration | H14: Gold Roll town | I14: c.1879 | J14: 1912-1915 | K14: Approximate | L14: Medium | M14: =IF($A14="","",IF($L14="High","Solid point",IF($L14="Medium","Point + buffer",IF($L14="Low","Translucent area",IF($L14="Disputed","Candidate points",IF($L14="Unknown","Unplotted (unlocated panel)","-")))))) -> Point + buffer | N14: 300 | O14: =IF($A14="","",COUNTIF(attestations!$B$2:$B$2000,$A14)) -> 29 | P14: =IF($A14="","",COUNTIFS(attestations!$B$2:$B$2000,$A14,attestations!$R$2:$R$2000,"Map")) -> 3 | Q14: =IF($A14="","",COUNTIFS(attestations!$B$2:$B$2000,$A14,attestations!$R$2:$R$2000,"Image")) -> 1 | R14: =IF($A14="","",COUNTIFS(attestations!$B$2:$B$2000,$A14,attestations!$R$2:$R$2000,"Textual")) -> 6 | S14: =IF($A14="","",COUNTIFS(attestations!$B$2:$B$2000,$A14,attestations!$D$2:$D$2000,"Geometry (Setting)")) -> 11 | T14: =IF($A14="","",IF($O14>=6,"High",IF($O14>=3,"Medium",IF($O14>=1,"Low","None")))) -> High | U14: =IF($A14="","",IF(COUNTIFS(attestations!$B$2:$B$2000,$A14,attestations!$I$2:$I$2000,"Georeferenced map GCP")>0,"Y","N")) -> Y | V14: Candidate | W14: Medium | X14: Town vs engineering-site edge case. Start widened to c.1879: Verbrugghe 1879 (Gallica S-040) names the Cerro de la Culebra as a Wyse-Reclus survey point. [2026-09-14] | Y14: Town
A15: CZ-014 | B15: Bas Obispo | C15: Bas Obispo; Haut Obispo | D15: Construction camp | E15: Unknown | F15: Unknown | G15: Labor | H15: Mixed | I15: pre-1857 | J15: 1911-1915 | K15: Inferred | L15: Low | M15: =IF($A15="","",IF($L15="High","Solid point",IF($L15="Medium","Point + buffer",IF($L15="Low","Translucent area",IF($L15="Disputed","Candidate points",IF($L15="Unknown","Unplotted (unlocated panel)","-")))))) -> Translucent area | N15: 500 | O15: =IF($A15="","",COUNTIF(attestations!$B$2:$B$2000,$A15)) -> 29 | P15: =IF($A15="","",COUNTIFS(attestations!$B$2:$B$2000,$A15,attestations!$R$2:$R$2000,"Map")) -> 2 | Q15: =IF($A15="","",COUNTIFS(attestations!$B$2:$B$2000,$A15,attestations!$R$2:$R$2000,"Image")) -> 2 | R15: =IF($A15="","",COUNTIFS(attestations!$B$2:$B$2000,$A15,attestations!$R$2:$R$2000,"Textual")) -> 7 | S15: =IF($A15="","",COUNTIFS(attestations!$B$2:$B$2000,$A15,attestations!$D$2:$D$2000,"Geometry (Setting)")) -> 8 | T15: =IF($A15="","",IF($O15>=6,"High",IF($O15>=3,"Medium",IF($O15>=1,"Low","None")))) -> High | U15: =IF($A15="","",IF(COUNTIFS(attestations!$B$2:$B$2000,$A15,attestations!$I$2:$I$2000,"Georeferenced map GCP")>0,"Y","N")) -> Y | V15: Candidate | X15: Classify at archive. 'Haut Obispo' equated as French-era name variant (decision 2026-09-05); its 7 CA hits from 1883-10-28 belong here. Start widened to c.1895: the 1895 GORPAN survey (A-0589) already traces a built-up footprint at Bas Obispo (French-canal-era work site / old P.R.R. line). [2026-09-13 lifespan fix] Start widened c.1895 -> c.1862? 2026-09-13: the 1862 plano names 'Estacion de Obispo' at the sheet edge (A-0895) - earliest name-at-site attestation, station name only; drawn village fabric begins with the 1895 survey. | lifespan extended to dated evidence 2026-09-14 (A-1482: 'Lower Obispo' settlement drawn on the 1857 Totten map) [was: c.1862?] | end date filled 2026-09-16 (user-approved gap fix): ceased in the construction-clearance era; erasure mechanism left Unknown - the site sat higher near Gamboa and 'drowned' is not established, so no flooding is asserted | Y15: Town
A16: CZ-015 | B16: Las Cascadas | D16: Construction camp | E16: Unknown | F16: Unknown | G16: Labor | H16: Mixed | I16: c.1895 | K16: Inferred | L16: Low | M16: =IF($A16="","",IF($L16="High","Solid point",IF($L16="Medium","Point + buffer",IF($L16="Low","Translucent area",IF($L16="Disputed","Candidate points",IF($L16="Unknown","Unplotted (unlocated panel)","-")))))) -> Translucent area | N16: 500 | O16: =IF($A16="","",COUNTIF(attestations!$B$2:$B$2000,$A16)) -> 21 | P16: =IF($A16="","",COUNTIFS(attestations!$B$2:$B$2000,$A16,attestations!$R$2:$R$2000,"Map")) -> 2 | Q16: =IF($A16="","",COUNTIFS(attestations!$B$2:$B$2000,$A16,attestations!$R$2:$R$2000,"Image")) -> 1 | R16: =IF($A16="","",COUNTIFS(attestations!$B$2:$B$2000,$A16,attestations!$R$2:$R$2000,"Textual")) -> 5 | S16: =IF($A16="","",COUNTIFS(attestations!$B$2:$B$2000,$A16,attestations!$D$2:$D$2000,"Geometry (Setting)")) -> 6 | T16: =IF($A16="","",IF($O16>=6,"High",IF($O16>=3,"Medium",IF($O16>=1,"Low","None")))) -> High | U16: =IF($A16="","",IF(COUNTIFS(attestations!$B$2:$B$2000,$A16,attestations!$I$2:$I$2000,"Georeferenced map GCP")>0,"Y","N")) -> Y | V16: Candidate | X16: Start widened to c.1895: the 1895 GORPAN survey (A-0590) shows the Las Cascadas village row on the P.R.R. [2026-09-13 lifespan fix] | Y16: Town
A17: CZ-016 | B17: Bohio | C17: Bohio; Bohio Soldado | D17: Village | E17: Unknown | F17: Unknown | G17: Displacement | H17: Panamanian village | I17: pre-1850? | J17: 1911-1914 | K17: Inferred | L17: Low | M17: =IF($A17="","",IF($L17="High","Solid point",IF($L17="Medium","Point + buffer",IF($L17="Low","Translucent area",IF($L17="Disputed","Candidate points",IF($L17="Unknown","Unplotted (unlocated panel)","-")))))) -> Translucent area | N17: 500 | O17: =IF($A17="","",COUNTIF(attestations!$B$2:$B$2000,$A17)) -> 27 | P17: =IF($A17="","",COUNTIFS(attestations!$B$2:$B$2000,$A17,attestations!$R$2:$R$2000,"Map")) -> 2 | Q17: =IF($A17="","",COUNTIFS(attestations!$B$2:$B$2000,$A17,attestations!$R$2:$R$2000,"Image")) -> 1 | R17: =IF($A17="","",COUNTIFS(attestations!$B$2:$B$2000,$A17,attestations!$R$2:$R$2000,"Textual")) -> 8 | S17: =IF($A17="","",COUNTIFS(attestations!$B$2:$B$2000,$A17,attestations!$D$2:$D$2000,"Geometry (Setting)")) -> 4 | T17: =IF($A17="","",IF($O17>=6,"High",IF($O17>=3,"Medium",IF($O17>=1,"Low","None")))) -> High | U17: =IF($A17="","",IF(COUNTIFS(attestations!$B$2:$B$2000,$A17,attestations!$I$2:$I$2000,"Georeferenced map GCP")>0,"Y","N")) -> Y | V17: Candidate | X17: Likely flood-affected; verify. | end date filled 2026-09-16 (user-approved gap fix): drowned by Gatun Lake when it filled 1913-14; end matched to the submerged cohort (Matachin/Old Gatun/Frijoles) | Y17: Town
A18: CZ-101 | B18: Empire Hospital | D18: Hospital | E18: Depopulated-not flooded | F18: 1912 depopulation order | G18: U.S. administration | H18: Mixed | I18: 1906 | J18: 1916 | K18: Approximate | L18: Medium | M18: =IF($A18="","",IF($L18="High","Solid point",IF($L18="Medium","Point + buffer",IF($L18="Low","Translucent area",IF($L18="Disputed","Candidate points",IF($L18="Unknown","Unplotted (unlocated panel)","-")))))) -> Point + buffer | N18: 400 | O18: =IF($A18="","",COUNTIF(attestations!$B$2:$B$2000,$A18)) -> 5 | P18: =IF($A18="","",COUNTIFS(attestations!$B$2:$B$2000,$A18,attestations!$R$2:$R$2000,"Map")) -> 1 | Q18: =IF($A18="","",COUNTIFS(attestations!$B$2:$B$2000,$A18,attestations!$R$2:$R$2000,"Image")) -> 0 | R18: =IF($A18="","",COUNTIFS(attestations!$B$2:$B$2000,$A18,attestations!$R$2:$R$2000,"Textual")) -> 1 | S18: =IF($A18="","",COUNTIFS(attestations!$B$2:$B$2000,$A18,attestations!$D$2:$D$2000,"Geometry (Setting)")) -> 1 | T18: =IF($A18="","",IF($O18>=6,"High",IF($O18>=3,"Medium",IF($O18>=1,"Low","None")))) -> Medium | U18: =IF($A18="","",IF(COUNTIFS(attestations!$B$2:$B$2000,$A18,attestations!$I$2:$I$2000,"Georeferenced map GCP")>0,"Y","N")) -> Y | V18: Candidate | X18: ICC hospital. | 2026-09-14: A-0041 retracted - the hospital has NO cartographic attestation on any sheet in hand; text-only place (Canal Record 1907). Placeholder coordinate and missing footprint are the honest record. | Y18: Site/Institution | Z18: CZ-011
A19: CZ-102 | B19: Empire Commissary | D19: Commissary/Supermarket | E19: Depopulated-not flooded | F19: 1912 depopulation order | G19: U.S. administration | H19: Mixed | I19: 1906 | J19: 1916 | K19: Approximate | L19: Medium | M19: =IF($A19="","",IF($L19="High","Solid point",IF($L19="Medium","Point + buffer",IF($L19="Low","Translucent area",IF($L19="Disputed","Candidate points",IF($L19="Unknown","Unplotted (unlocated panel)","-")))))) -> Point + buffer | N19: 400 | O19: =IF($A19="","",COUNTIF(attestations!$B$2:$B$2000,$A19)) -> 5 | P19: =IF($A19="","",COUNTIFS(attestations!$B$2:$B$2000,$A19,attestations!$R$2:$R$2000,"Map")) -> 0 | Q19: =IF($A19="","",COUNTIFS(attestations!$B$2:$B$2000,$A19,attestations!$R$2:$R$2000,"Image")) -> 0 | R19: =IF($A19="","",COUNTIFS(attestations!$B$2:$B$2000,$A19,attestations!$R$2:$R$2000,"Textual")) -> 1 | S19: =IF($A19="","",COUNTIFS(attestations!$B$2:$B$2000,$A19,attestations!$D$2:$D$2000,"Geometry (Setting)")) -> 1 | T19: =IF($A19="","",IF($O19>=6,"High",IF($O19>=3,"Medium",IF($O19>=1,"Low","None")))) -> Medium | U19: =IF($A19="","",IF(COUNTIFS(attestations!$B$2:$B$2000,$A19,attestations!$I$2:$I$2000,"Georeferenced map GCP")>0,"Y","N")) -> Y | V19: Candidate | X19: ICC commissary / store. Building outline traced 2026-09-13 from the source sheet into data/footprints.geojson (building-outline pass). | Y19: Site/Institution | Z19: CZ-011
A20: CZ-103 | B20: Empire Clubhouse & Cinema | D20: Cinema/Clubhouse | E20: Depopulated-not flooded | F20: 1912 depopulation order | G20: U.S. administration | H20: Gold Roll town | I20: 1907 | J20: 1916 | K20: Approximate | L20: Medium | M20: =IF($A20="","",IF($L20="High","Solid point",IF($L20="Medium","Point + buffer",IF($L20="Low","Translucent area",IF($L20="Disputed","Candidate points",IF($L20="Unknown","Unplotted (unlocated panel)","-")))))) -> Point + buffer | N20: 400 | O20: =IF($A20="","",COUNTIF(attestations!$B$2:$B$2000,$A20)) -> 1 | P20: =IF($A20="","",COUNTIFS(attestations!$B$2:$B$2000,$A20,attestations!$R$2:$R$2000,"Map")) -> 0 | Q20: =IF($A20="","",COUNTIFS(attestations!$B$2:$B$2000,$A20,attestations!$R$2:$R$2000,"Image")) -> 0 | R20: =IF($A20="","",COUNTIFS(attestations!$B$2:$B$2000,$A20,attestations!$R$2:$R$2000,"Textual")) -> 0 | S20: =IF($A20="","",COUNTIFS(attestations!$B$2:$B$2000,$A20,attestations!$D$2:$D$2000,"Geometry (Setting)")) -> 0 | T20: =IF($A20="","",IF($O20>=6,"High",IF($O20>=3,"Medium",IF($O20>=1,"Low","None")))) -> Low | U20: =IF($A20="","",IF(COUNTIFS(attestations!$B$2:$B$2000,$A20,attestations!$I$2:$I$2000,"Georeferenced map GCP")>0,"Y","N")) -> N | V20: Duplicate | X20: Gold-roll amenity. | MERGED into CZ-125 2026-09-14: the Canal Record 'Clubhouse' and the plan's Y.M.C.A. are the same institution (ICC clubhouses were YMCA-operated; full-sheet sweep found no separate Clubhouse label). Row kept for id stability - do not use. | Y20: Building | Z20: CZ-011
A21: CZ-104 | B21: Empire Silver Quarters | D21: Quarters/Housing | E21: Depopulated-not flooded | F21: 1912 depopulation order | G21: Labor | H21: West Indian / Silver Roll | I21: 1905 | J21: 1916 | K21: Approximate | L21: Low | M21: =IF($A21="","",IF($L21="High","Solid point",IF($L21="Medium","Point + buffer",IF($L21="Low","Translucent area",IF($L21="Disputed","Candidate points",IF($L21="Unknown","Unplotted (unlocated panel)","-")))))) -> Translucent area | N21: 400 | O21: =IF($A21="","",COUNTIF(attestations!$B$2:$B$2000,$A21)) -> 9 | P21: =IF($A21="","",COUNTIFS(attestations!$B$2:$B$2000,$A21,attestations!$R$2:$R$2000,"Map")) -> 1 | Q21: =IF($A21="","",COUNTIFS(attestations!$B$2:$B$2000,$A21,attestations!$R$2:$R$2000,"Image")) -> 0 | R21: =IF($A21="","",COUNTIFS(attestations!$B$2:$B$2000,$A21,attestations!$R$2:$R$2000,"Textual")) -> 1 | S21: =IF($A21="","",COUNTIFS(attestations!$B$2:$B$2000,$A21,attestations!$D$2:$D$2000,"Geometry (Setting)")) -> 0 | T21: =IF($A21="","",IF($O21>=6,"High",IF($O21>=3,"Medium",IF($O21>=1,"Low","None")))) -> High | U21: =IF($A21="","",IF(COUNTIFS(attestations!$B$2:$B$2000,$A21,attestations!$I$2:$I$2000,"Georeferenced map GCP")>0,"Y","N")) -> N | V21: Candidate | W21: High | X21: Silver-roll housing; thinly mapped. | Y21: Neighborhood | Z21: CZ-011
A22: CZ-105 | B22: Empire Gold Quarters | D22: Quarters/Housing | E22: Depopulated-not flooded | F22: 1912 depopulation order | G22: U.S. administration | H22: Gold Roll town | I22: 1905 | J22: 1916 | K22: Approximate | L22: Medium | M22: =IF($A22="","",IF($L22="High","Solid point",IF($L22="Medium","Point + buffer",IF($L22="Low","Translucent area",IF($L22="Disputed","Candidate points",IF($L22="Unknown","Unplotted (unlocated panel)","-")))))) -> Point + buffer | N22: 400 | O22: =IF($A22="","",COUNTIF(attestations!$B$2:$B$2000,$A22)) -> 8 | P22: =IF($A22="","",COUNTIFS(attestations!$B$2:$B$2000,$A22,attestations!$R$2:$R$2000,"Map")) -> 1 | Q22: =IF($A22="","",COUNTIFS(attestations!$B$2:$B$2000,$A22,attestations!$R$2:$R$2000,"Image")) -> 0 | R22: =IF($A22="","",COUNTIFS(attestations!$B$2:$B$2000,$A22,attestations!$R$2:$R$2000,"Textual")) -> 0 | S22: =IF($A22="","",COUNTIFS(attestations!$B$2:$B$2000,$A22,attestations!$D$2:$D$2000,"Geometry (Setting)")) -> 1 | T22: =IF($A22="","",IF($O22>=6,"High",IF($O22>=3,"Medium",IF($O22>=1,"Low","None")))) -> High | U22: =IF($A22="","",IF(COUNTIFS(attestations!$B$2:$B$2000,$A22,attestations!$I$2:$I$2000,"Georeferenced map GCP")>0,"Y","N")) -> Y | V22: Candidate | X22: Gold-roll housing. | Y22: Neighborhood | Z22: CZ-011
A23: CZ-106 | B23: Empire Plaza | D23: Park/Plaza | E23: Depopulated-not flooded | F23: 1912 depopulation order | G23: Other | H23: Mixed | I23: 1885 | J23: 1916 | K23: Approximate | L23: Medium | M23: =IF($A23="","",IF($L23="High","Solid point",IF($L23="Medium","Point + buffer",IF($L23="Low","Translucent area",IF($L23="Disputed","Candidate points",IF($L23="Unknown","Unplotted (unlocated panel)","-")))))) -> Point + buffer | N23: 400 | O23: =IF($A23="","",COUNTIF(attestations!$B$2:$B$2000,$A23)) -> 0 | P23: =IF($A23="","",COUNTIFS(attestations!$B$2:$B$2000,$A23,attestations!$R$2:$R$2000,"Map")) -> 0 | Q23: =IF($A23="","",COUNTIFS(attestations!$B$2:$B$2000,$A23,attestations!$R$2:$R$2000,"Image")) -> 0 | R23: =IF($A23="","",COUNTIFS(attestations!$B$2:$B$2000,$A23,attestations!$R$2:$R$2000,"Textual")) -> 0 | S23: =IF($A23="","",COUNTIFS(attestations!$B$2:$B$2000,$A23,attestations!$D$2:$D$2000,"Geometry (Setting)")) -> 0 | T23: =IF($A23="","",IF($O23>=6,"High",IF($O23>=3,"Medium",IF($O23>=1,"Low","None")))) -> None | U23: =IF($A23="","",IF(COUNTIFS(attestations!$B$2:$B$2000,$A23,attestations!$I$2:$I$2000,"Georeferenced map GCP")>0,"Y","N")) -> N | V23: Duplicate | X23: Central open space, inferred from a 'Band Stand' label read on the MIRRORED EMPIRE warp; the corrected warp reads 'Grand Stand' at the ballpark. MERGED into CZ-120 2026-09-13; the traced grandstand outline is attached to CZ-120. Row kept for id stability - do not use. | Y23: Site/Institution | Z23: CZ-011
A24: CZ-201 | B24: Nuevo Emperador (present-day) | C24: Emperador | D24: Modern town | E24: Persists | F24: Other | G24: Other | H24: Mixed | I24: pre-1994? | K24: Unknown | L24: Unknown | M24: =IF($A24="","",IF($L24="High","Solid point",IF($L24="Medium","Point + buffer",IF($L24="Low","Translucent area",IF($L24="Disputed","Candidate points",IF($L24="Unknown","Unplotted (unlocated panel)","-")))))) -> Unplotted (unlocated panel) | N24: 100 | O24: =IF($A24="","",COUNTIF(attestations!$B$2:$B$2000,$A24)) -> 1 | P24: =IF($A24="","",COUNTIFS(attestations!$B$2:$B$2000,$A24,attestations!$R$2:$R$2000,"Map")) -> 0 | Q24: =IF($A24="","",COUNTIFS(attestations!$B$2:$B$2000,$A24,attestations!$R$2:$R$2000,"Image")) -> 0 | R24: =IF($A24="","",COUNTIFS(attestations!$B$2:$B$2000,$A24,attestations!$R$2:$R$2000,"Textual")) -> 0 | S24: =IF($A24="","",COUNTIFS(attestations!$B$2:$B$2000,$A24,attestations!$D$2:$D$2000,"Geometry (Setting)")) -> 0 | T24: =IF($A24="","",IF($O24>=6,"High",IF($O24>=3,"Medium",IF($O24>=1,"Low","None")))) -> Low | U24: =IF($A24="","",IF(COUNTIFS(attestations!$B$2:$B$2000,$A24,attestations!$I$2:$I$2000,"Georeferenced map GCP")>0,"Y","N")) -> N | V24: Candidate | X24: Present-day settlement; illustrative. | ERASED 2026-09-14: unverified illustrative example removed from the model - not a duplicate; the export's Duplicate skip is reused for row-position stability. The palimpsest now rests on the verified extant places only. Do not use. | RESTORED 2026-09-14 as honest UNLOCATED extant: the town exists - existence attested by 1990s AP datelines 'NUEVO EMPERADOR, Panama' (dLOC) - but the old record's coordinate and founding were invented, so both are withdrawn [start was: 1955]. Coordinates enter only from a citable present-day source. | Y24: Town | Z24: CZ-011 | AA24: Present-day town. 1990s newspaper datelines confirm it exists, but no citable source yet gives its location or founding date.
A25: CZ-202 | B25: Modern roadway segment | D25: Modern infrastructure | E25: Persists | F25: Other | G25: Infrastructure | H25: Mixed | I25: 1950 | K25: Inferred | L25: Medium | M25: =IF($A25="","",IF($L25="High","Solid point",IF($L25="Medium","Point + buffer",IF($L25="Low","Translucent area",IF($L25="Disputed","Candidate points",IF($L25="Unknown","Unplotted (unlocated panel)","-")))))) -> Point + buffer | N25: 100 | O25: =IF($A25="","",COUNTIF(attestations!$B$2:$B$2000,$A25)) -> 0 | P25: =IF($A25="","",COUNTIFS(attestations!$B$2:$B$2000,$A25,attestations!$R$2:$R$2000,"Map")) -> 0 | Q25: =IF($A25="","",COUNTIFS(attestations!$B$2:$B$2000,$A25,attestations!$R$2:$R$2000,"Image")) -> 0 | R25: =IF($A25="","",COUNTIFS(attestations!$B$2:$B$2000,$A25,attestations!$R$2:$R$2000,"Textual")) -> 0 | S25: =IF($A25="","",COUNTIFS(attestations!$B$2:$B$2000,$A25,attestations!$D$2:$D$2000,"Geometry (Setting)")) -> 0 | T25: =IF($A25="","",IF($O25>=6,"High",IF($O25>=3,"Medium",IF($O25>=1,"Low","None")))) -> None | U25: =IF($A25="","",IF(COUNTIFS(attestations!$B$2:$B$2000,$A25,attestations!$I$2:$I$2000,"Georeferenced map GCP")>0,"Y","N")) -> N | V25: Duplicate | X25: Present-day road; illustrative. | ERASED 2026-09-14: unverified illustrative example removed from the model - not a duplicate; the export's Duplicate skip is reused for row-position stability. The palimpsest now rests on the verified extant places only. Do not use. | Y25: Infrastructure | Z25: CZ-011
A26: CZ-107 | B26: Empire Church / Chapel | D26: Church | E26: Depopulated-not flooded | F26: 1912 depopulation order | G26: Afro-Caribbean life | H26: West Indian / Silver Roll | I26: 1906 | J26: 1916 | K26: Approximate | L26: Medium | M26: =IF($A26="","",IF($L26="High","Solid point",IF($L26="Medium","Point + buffer",IF($L26="Low","Translucent area",IF($L26="Disputed","Candidate points",IF($L26="Unknown","Unplotted (unlocated panel)","-")))))) -> Point + buffer | N26: 400 | O26: =IF($A26="","",COUNTIF(attestations!$B$2:$B$2000,$A26)) -> 9 | P26: =IF($A26="","",COUNTIFS(attestations!$B$2:$B$2000,$A26,attestations!$R$2:$R$2000,"Map")) -> 0 | Q26: =IF($A26="","",COUNTIFS(attestations!$B$2:$B$2000,$A26,attestations!$R$2:$R$2000,"Image")) -> 0 | R26: =IF($A26="","",COUNTIFS(attestations!$B$2:$B$2000,$A26,attestations!$R$2:$R$2000,"Textual")) -> 1 | S26: =IF($A26="","",COUNTIFS(attestations!$B$2:$B$2000,$A26,attestations!$D$2:$D$2000,"Geometry (Setting)")) -> 1 | T26: =IF($A26="","",IF($O26>=6,"High",IF($O26>=3,"Medium",IF($O26>=1,"Low","None")))) -> High | U26: =IF($A26="","",IF(COUNTIFS(attestations!$B$2:$B$2000,$A26,attestations!$I$2:$I$2000,"Georeferenced map GCP")>0,"Y","N")) -> Y | V26: Candidate | X26: West Indian chapel. | Y26: Site/Institution | Z26: CZ-011
A27: CZ-108 | B27: Empire Cemetery | D27: Cemetery | E27: Depopulated-not flooded | F27: 1912 depopulation order | G27: Afro-Caribbean life | H27: West Indian / Silver Roll | I27: 1905 | J27: 1916 | K27: Inferred | L27: Low | M27: =IF($A27="","",IF($L27="High","Solid point",IF($L27="Medium","Point + buffer",IF($L27="Low","Translucent area",IF($L27="Disputed","Candidate points",IF($L27="Unknown","Unplotted (unlocated panel)","-")))))) -> Translucent area | N27: 400 | O27: =IF($A27="","",COUNTIF(attestations!$B$2:$B$2000,$A27)) -> 7 | P27: =IF($A27="","",COUNTIFS(attestations!$B$2:$B$2000,$A27,attestations!$R$2:$R$2000,"Map")) -> 1 | Q27: =IF($A27="","",COUNTIFS(attestations!$B$2:$B$2000,$A27,attestations!$R$2:$R$2000,"Image")) -> 0 | R27: =IF($A27="","",COUNTIFS(attestations!$B$2:$B$2000,$A27,attestations!$R$2:$R$2000,"Textual")) -> 0 | S27: =IF($A27="","",COUNTIFS(attestations!$B$2:$B$2000,$A27,attestations!$D$2:$D$2000,"Geometry (Setting)")) -> 0 | T27: =IF($A27="","",IF($O27>=6,"High",IF($O27>=3,"Medium",IF($O27>=1,"Low","None")))) -> High | U27: =IF($A27="","",IF(COUNTIFS(attestations!$B$2:$B$2000,$A27,attestations!$I$2:$I$2000,"Georeferenced map GCP")>0,"Y","N")) -> N | V27: Candidate | W27: High | X27: Afro-Caribbean burial ground; rarely on official maps. | Y27: Site/Institution | Z27: CZ-011
A28: CZ-109 | B28: Empire School | D28: School | E28: Depopulated-not flooded | F28: 1912 depopulation order | G28: U.S. administration | H28: Mixed | I28: 1906 | J28: 1916 | K28: Approximate | L28: Medium | M28: =IF($A28="","",IF($L28="High","Solid point",IF($L28="Medium","Point + buffer",IF($L28="Low","Translucent area",IF($L28="Disputed","Candidate points",IF($L28="Unknown","Unplotted (unlocated panel)","-")))))) -> Point + buffer | N28: 400 | O28: =IF($A28="","",COUNTIF(attestations!$B$2:$B$2000,$A28)) -> 5 | P28: =IF($A28="","",COUNTIFS(attestations!$B$2:$B$2000,$A28,attestations!$R$2:$R$2000,"Map")) -> 0 | Q28: =IF($A28="","",COUNTIFS(attestations!$B$2:$B$2000,$A28,attestations!$R$2:$R$2000,"Image")) -> 0 | R28: =IF($A28="","",COUNTIFS(attestations!$B$2:$B$2000,$A28,attestations!$R$2:$R$2000,"Textual")) -> 1 | S28: =IF($A28="","",COUNTIFS(attestations!$B$2:$B$2000,$A28,attestations!$D$2:$D$2000,"Geometry (Setting)")) -> 1 | T28: =IF($A28="","",IF($O28>=6,"High",IF($O28>=3,"Medium",IF($O28>=1,"Low","None")))) -> Medium | U28: =IF($A28="","",IF(COUNTIFS(attestations!$B$2:$B$2000,$A28,attestations!$I$2:$I$2000,"Georeferenced map GCP")>0,"Y","N")) -> Y | V28: Candidate | X28: Canal Zone school. Building outline traced 2026-09-13 from the source sheet into data/footprints.geojson (building-outline pass). | Y28: Site/Institution | Z28: CZ-011
A29: CZ-017 | B29: Cristobal | D29: Town | E29: Persists | F29: Other | G29: U.S. administration | H29: Mixed | I29: c.1855 | K29: Approximate | L29: Medium | M29: =IF($A29="","",IF($L29="High","Solid point",IF($L29="Medium","Point + buffer",IF($L29="Low","Translucent area",IF($L29="Disputed","Candidate points",IF($L29="Unknown","Unplotted (unlocated panel)","-")))))) -> Point + buffer | N29: 300 | O29: =IF($A29="","",COUNTIF(attestations!$B$2:$B$2000,$A29)) -> 22 | P29: =IF($A29="","",COUNTIFS(attestations!$B$2:$B$2000,$A29,attestations!$R$2:$R$2000,"Map")) -> 1 | Q29: =IF($A29="","",COUNTIFS(attestations!$B$2:$B$2000,$A29,attestations!$R$2:$R$2000,"Image")) -> 3 | R29: =IF($A29="","",COUNTIFS(attestations!$B$2:$B$2000,$A29,attestations!$R$2:$R$2000,"Textual")) -> 5 | S29: =IF($A29="","",COUNTIFS(attestations!$B$2:$B$2000,$A29,attestations!$D$2:$D$2000,"Geometry (Setting)")) -> 6 | T29: =IF($A29="","",IF($O29>=6,"High",IF($O29>=3,"Medium",IF($O29>=1,"Low","None")))) -> High | U29: =IF($A29="","",IF(COUNTIFS(attestations!$B$2:$B$2000,$A29,attestations!$I$2:$I$2000,"Georeferenced map GCP")>0,"Y","N")) -> Y | V29: Candidate | W29: Medium | X29: Atlantic terminal town adjoining Colon. In official CZ post-office list (Evening Star 1906-02-16). 9,994 Chronicling America hits from 1880-01-27. | Y29: Town | AA29: The canal's Atlantic terminal town, next to the Panamanian city of Colón.
A30: CZ-018 | B30: Ancon | D30: Town | E30: Persists | F30: Other | G30: U.S. administration | H30: Mixed | I30: c.1880 | K30: Approximate | L30: Medium | M30: =IF($A30="","",IF($L30="High","Solid point",IF($L30="Medium","Point + buffer",IF($L30="Low","Translucent area",IF($L30="Disputed","Candidate points",IF($L30="Unknown","Unplotted (unlocated panel)","-")))))) -> Point + buffer | N30: 300 | O30: =IF($A30="","",COUNTIF(attestations!$B$2:$B$2000,$A30)) -> 19 | P30: =IF($A30="","",COUNTIFS(attestations!$B$2:$B$2000,$A30,attestations!$R$2:$R$2000,"Map")) -> 1 | Q30: =IF($A30="","",COUNTIFS(attestations!$B$2:$B$2000,$A30,attestations!$R$2:$R$2000,"Image")) -> 1 | R30: =IF($A30="","",COUNTIFS(attestations!$B$2:$B$2000,$A30,attestations!$R$2:$R$2000,"Textual")) -> 5 | S30: =IF($A30="","",COUNTIFS(attestations!$B$2:$B$2000,$A30,attestations!$D$2:$D$2000,"Geometry (Setting)")) -> 5 | T30: =IF($A30="","",IF($O30>=6,"High",IF($O30>=3,"Medium",IF($O30>=1,"Low","None")))) -> High | U30: =IF($A30="","",IF(COUNTIFS(attestations!$B$2:$B$2000,$A30,attestations!$I$2:$I$2000,"Georeferenced map GCP")>0,"Y","N")) -> Y | V30: Candidate | W30: Medium | X30: ICC headquarters / hospital town. 1906 post-office list. 7,063 CA hits from 1880-01-07. | Y30: Town | AA30: Headquarters and hospital town of the Isthmian Canal Commission, the US agency that built the canal.
A31: CZ-019 | B31: Rio Grande | D31: Village | E31: Depopulated-not flooded | F31: 1912 depopulation order | G31: Displacement | H31: Mixed | I31: pre-1857 | J31: 1912 | K31: Approximate | L31: Medium | M31: =IF($A31="","",IF($L31="High","Solid point",IF($L31="Medium","Point + buffer",IF($L31="Low","Translucent area",IF($L31="Disputed","Candidate points",IF($L31="Unknown","Unplotted (unlocated panel)","-")))))) -> Point + buffer | N31: 300 | O31: =IF($A31="","",COUNTIF(attestations!$B$2:$B$2000,$A31)) -> 16 | P31: =IF($A31="","",COUNTIFS(attestations!$B$2:$B$2000,$A31,attestations!$R$2:$R$2000,"Map")) -> 1 | Q31: =IF($A31="","",COUNTIFS(attestations!$B$2:$B$2000,$A31,attestations!$R$2:$R$2000,"Image")) -> 1 | R31: =IF($A31="","",COUNTIFS(attestations!$B$2:$B$2000,$A31,attestations!$R$2:$R$2000,"Textual")) -> 5 | S31: =IF($A31="","",COUNTIFS(attestations!$B$2:$B$2000,$A31,attestations!$D$2:$D$2000,"Geometry (Setting)")) -> 5 | T31: =IF($A31="","",IF($O31>=6,"High",IF($O31>=3,"Medium",IF($O31>=1,"Low","None")))) -> High | U31: =IF($A31="","",IF(COUNTIFS(attestations!$B$2:$B$2000,$A31,attestations!$I$2:$I$2000,"Georeferenced map GCP")>0,"Y","N")) -> Y | V31: Candidate | W31: High | X31: Commissary settlement abandoned 1912 as canal advanced (Der Seebote 1913-05-18). Absent from prior gazetteer; 2,727 CA hits. CAUTION: also a river name. | lifespan extended to dated evidence 2026-09-14 (A-1487: Rio Grande Station lettering on the 1857 Totten map) [was: c.1880?] | Y31: Town
A32: CZ-020 | B32: Pedro Miguel | D32: Town | E32: Persists | F32: Other | G32: Infrastructure | H32: Mixed | I32: c.1855 | K32: Approximate | L32: Medium | M32: =IF($A32="","",IF($L32="High","Solid point",IF($L32="Medium","Point + buffer",IF($L32="Low","Translucent area",IF($L32="Disputed","Candidate points",IF($L32="Unknown","Unplotted (unlocated panel)","-")))))) -> Point + buffer | N32: 300 | O32: =IF($A32="","",COUNTIF(attestations!$B$2:$B$2000,$A32)) -> 24 | P32: =IF($A32="","",COUNTIFS(attestations!$B$2:$B$2000,$A32,attestations!$R$2:$R$2000,"Map")) -> 2 | Q32: =IF($A32="","",COUNTIFS(attestations!$B$2:$B$2000,$A32,attestations!$R$2:$R$2000,"Image")) -> 1 | R32: =IF($A32="","",COUNTIFS(attestations!$B$2:$B$2000,$A32,attestations!$R$2:$R$2000,"Textual")) -> 6 | S32: =IF($A32="","",COUNTIFS(attestations!$B$2:$B$2000,$A32,attestations!$D$2:$D$2000,"Geometry (Setting)")) -> 9 | T32: =IF($A32="","",IF($O32>=6,"High",IF($O32>=3,"Medium",IF($O32>=1,"Low","None")))) -> High | U32: =IF($A32="","",IF(COUNTIFS(attestations!$B$2:$B$2000,$A32,attestations!$I$2:$I$2000,"Georeferenced map GCP")>0,"Y","N")) -> Y | V32: Candidate | W32: Medium | X32: Lock town. 1906 post-office list; 1897 lock-plan article. 2,311 CA hits. | RULING 2026-09-13: split old/new - CZ-172 'Pedro Miguel (as-built)' now carries the 1911 property-block town; this id keeps the old (PRR-era) village. | Y32: Town | AA32: Village on the Panama Railroad line, later a lock town. The town laid out on the 1911 property map is recorded as a separate place.
A33: CZ-021 | B33: La Boca | D33: Town | E33: Relocated | F33: Other | G33: Afro-Caribbean life | H33: West Indian / Silver Roll | I33: c.1880 | K33: Approximate | L33: Medium | M33: =IF($A33="","",IF($L33="High","Solid point",IF($L33="Medium","Point + buffer",IF($L33="Low","Translucent area",IF($L33="Disputed","Candidate points",IF($L33="Unknown","Unplotted (unlocated panel)","-")))))) -> Point + buffer | N33: 300 | O33: =IF($A33="","",COUNTIF(attestations!$B$2:$B$2000,$A33)) -> 22 | P33: =IF($A33="","",COUNTIFS(attestations!$B$2:$B$2000,$A33,attestations!$R$2:$R$2000,"Map")) -> 2 | Q33: =IF($A33="","",COUNTIFS(attestations!$B$2:$B$2000,$A33,attestations!$R$2:$R$2000,"Image")) -> 1 | R33: =IF($A33="","",COUNTIFS(attestations!$B$2:$B$2000,$A33,attestations!$R$2:$R$2000,"Textual")) -> 6 | S33: =IF($A33="","",COUNTIFS(attestations!$B$2:$B$2000,$A33,attestations!$D$2:$D$2000,"Geometry (Setting)")) -> 5 | T33: =IF($A33="","",IF($O33>=6,"High",IF($O33>=3,"Medium",IF($O33>=1,"Low","None")))) -> High | U33: =IF($A33="","",IF(COUNTIFS(attestations!$B$2:$B$2000,$A33,attestations!$I$2:$I$2000,"Georeferenced map GCP")>0,"Y","N")) -> Y | V33: Candidate | W33: High | X33: Pacific terminal / silver town; renamed and absorbed into Balboa c.1909. 1906 post-office list; 1887 French works table. 2,173 CA hits. [2026-09-12 RULING: 1947 'La Boca' = same place resumed; end date reopened - name suppressed on official maps c.1908-1940s while site labeled Balboa, community persisted.] | Y33: Town
A34: CZ-022 | B34: Corozal | D34: Town | E34: Persists | F34: Other | G34: U.S. administration | H34: Mixed | I34: c.1880 | K34: Approximate | L34: Medium | M34: =IF($A34="","",IF($L34="High","Solid point",IF($L34="Medium","Point + buffer",IF($L34="Low","Translucent area",IF($L34="Disputed","Candidate points",IF($L34="Unknown","Unplotted (unlocated panel)","-")))))) -> Point + buffer | N34: 300 | O34: =IF($A34="","",COUNTIF(attestations!$B$2:$B$2000,$A34)) -> 20 | P34: =IF($A34="","",COUNTIFS(attestations!$B$2:$B$2000,$A34,attestations!$R$2:$R$2000,"Map")) -> 2 | Q34: =IF($A34="","",COUNTIFS(attestations!$B$2:$B$2000,$A34,attestations!$R$2:$R$2000,"Image")) -> 1 | R34: =IF($A34="","",COUNTIFS(attestations!$B$2:$B$2000,$A34,attestations!$R$2:$R$2000,"Textual")) -> 6 | S34: =IF($A34="","",COUNTIFS(attestations!$B$2:$B$2000,$A34,attestations!$D$2:$D$2000,"Geometry (Setting)")) -> 6 | T34: =IF($A34="","",IF($O34>=6,"High",IF($O34>=3,"Medium",IF($O34>=1,"Low","None")))) -> High | U34: =IF($A34="","",IF(COUNTIFS(attestations!$B$2:$B$2000,$A34,attestations!$I$2:$I$2000,"Georeferenced map GCP")>0,"Y","N")) -> Y | V34: Candidate | W34: Medium | X34: 1906 post-office list; 1887 French works table (OCR 'Corvzal'). 768 CA hits. | Y34: Town
A35: CZ-023 | B35: Frijoles | D35: Station | E35: Submerged | F35: Gatun Lake flooding | G35: Displacement | H35: Panamanian village | I35: c.1855 | J35: 1911-1914 | K35: Approximate | L35: Medium | M35: =IF($A35="","",IF($L35="High","Solid point",IF($L35="Medium","Point + buffer",IF($L35="Low","Translucent area",IF($L35="Disputed","Candidate points",IF($L35="Unknown","Unplotted (unlocated panel)","-")))))) -> Point + buffer | N35: 250 | O35: =IF($A35="","",COUNTIF(attestations!$B$2:$B$2000,$A35)) -> 17 | P35: =IF($A35="","",COUNTIFS(attestations!$B$2:$B$2000,$A35,attestations!$R$2:$R$2000,"Map")) -> 2 | Q35: =IF($A35="","",COUNTIFS(attestations!$B$2:$B$2000,$A35,attestations!$R$2:$R$2000,"Image")) -> 1 | R35: =IF($A35="","",COUNTIFS(attestations!$B$2:$B$2000,$A35,attestations!$R$2:$R$2000,"Textual")) -> 4 | S35: =IF($A35="","",COUNTIFS(attestations!$B$2:$B$2000,$A35,attestations!$D$2:$D$2000,"Geometry (Setting)")) -> 6 | T35: =IF($A35="","",IF($O35>=6,"High",IF($O35>=3,"Medium",IF($O35>=1,"Low","None")))) -> High | U35: =IF($A35="","",IF(COUNTIFS(attestations!$B$2:$B$2000,$A35,attestations!$I$2:$I$2000,"Georeferenced map GCP")>0,"Y","N")) -> Y | V35: Candidate | W35: High | X35: PRR station; old site flooded by Gatun Lake, station relocated. 1882 French brigade list; 1906 post offices. CAUTION: also a river name. 370 CA hits. | RULING 2026-09-13: split old/new - CZ-173 'New Frijoles' now carries the relocated-line station (c.1909-, persists); this id keeps the drowned PRR village, lifespan c.1855-1911/14 stands. The 1940 census read moved with the split - the lifespan DATA HEALTH flag is thereby resolved. | Y35: Town
A36: CZ-024 | B36: Paraiso | D36: Town | E36: Persists | F36: Other | G36: Labor | H36: Mixed | I36: pre-1857 | K36: Approximate | L36: Medium | M36: =IF($A36="","",IF($L36="High","Solid point",IF($L36="Medium","Point + buffer",IF($L36="Low","Translucent area",IF($L36="Disputed","Candidate points",IF($L36="Unknown","Unplotted (unlocated panel)","-")))))) -> Point + buffer | N36: 300 | O36: =IF($A36="","",COUNTIF(attestations!$B$2:$B$2000,$A36)) -> 27 | P36: =IF($A36="","",COUNTIFS(attestations!$B$2:$B$2000,$A36,attestations!$R$2:$R$2000,"Map")) -> 2 | Q36: =IF($A36="","",COUNTIFS(attestations!$B$2:$B$2000,$A36,attestations!$R$2:$R$2000,"Image")) -> 1 | R36: =IF($A36="","",COUNTIFS(attestations!$B$2:$B$2000,$A36,attestations!$R$2:$R$2000,"Textual")) -> 6 | S36: =IF($A36="","",COUNTIFS(attestations!$B$2:$B$2000,$A36,attestations!$D$2:$D$2000,"Geometry (Setting)")) -> 8 | T36: =IF($A36="","",IF($O36>=6,"High",IF($O36>=3,"Medium",IF($O36>=1,"Low","None")))) -> High | U36: =IF($A36="","",IF(COUNTIFS(attestations!$B$2:$B$2000,$A36,attestations!$I$2:$I$2000,"Georeferenced map GCP")>0,"Y","N")) -> Y | V36: Candidate | W36: Medium | X36: 1906 post-office list; 1887 French excavation table. 213 CA hits (more under French-era coverage). Start widened to c.1879: Verbrugghe 1879 (Gallica S-040) observes basaltic hills "a Paraiso". [2026-09-14] | lifespan extended to dated evidence 2026-09-14 (A-1485: 'Paraison' Station drawn on the 1857 Totten map) [was: c.1879] | Y36: Town
A37: CZ-025 | B37: San Pablo | D37: Station | E37: Submerged | F37: Gatun Lake flooding | G37: Displacement | H37: Panamanian village | I37: c.1855 | J37: 1911-1914 | K37: Approximate | L37: Low | M37: =IF($A37="","",IF($L37="High","Solid point",IF($L37="Medium","Point + buffer",IF($L37="Low","Translucent area",IF($L37="Disputed","Candidate points",IF($L37="Unknown","Unplotted (unlocated panel)","-")))))) -> Translucent area | N37: 400 | O37: =IF($A37="","",COUNTIF(attestations!$B$2:$B$2000,$A37)) -> 22 | P37: =IF($A37="","",COUNTIFS(attestations!$B$2:$B$2000,$A37,attestations!$R$2:$R$2000,"Map")) -> 2 | Q37: =IF($A37="","",COUNTIFS(attestations!$B$2:$B$2000,$A37,attestations!$R$2:$R$2000,"Image")) -> 1 | R37: =IF($A37="","",COUNTIFS(attestations!$B$2:$B$2000,$A37,attestations!$R$2:$R$2000,"Textual")) -> 7 | S37: =IF($A37="","",COUNTIFS(attestations!$B$2:$B$2000,$A37,attestations!$D$2:$D$2000,"Geometry (Setting)")) -> 6 | T37: =IF($A37="","",IF($O37>=6,"High",IF($O37>=3,"Medium",IF($O37>=1,"Low","None")))) -> High | U37: =IF($A37="","",IF(COUNTIFS(attestations!$B$2:$B$2000,$A37,attestations!$I$2:$I$2000,"Georeferenced map GCP")>0,"Y","N")) -> Y | V37: Candidate | W37: High | X37: PRR station on the Chagres. 1882 brigade list; 1887 works table; 1906 post offices; flooded by Gatun Lake. 145 CA hits. | Y37: Town
A38: CZ-026 | B38: Tabernilla | C38: Tabernilla; Tavernilla | D38: Station | E38: Submerged | F38: Gatun Lake flooding | G38: Displacement | H38: Panamanian village | I38: pre-1844 | J38: c.1913 | K38: Approximate | L38: Disputed | M38: =IF($A38="","",IF($L38="High","Solid point",IF($L38="Medium","Point + buffer",IF($L38="Low","Translucent area",IF($L38="Disputed","Candidate points",IF($L38="Unknown","Unplotted (unlocated panel)","-")))))) -> Candidate points | N38: 600 | O38: =IF($A38="","",COUNTIF(attestations!$B$2:$B$2000,$A38)) -> 24 | P38: =IF($A38="","",COUNTIFS(attestations!$B$2:$B$2000,$A38,attestations!$R$2:$R$2000,"Map")) -> 2 | Q38: =IF($A38="","",COUNTIFS(attestations!$B$2:$B$2000,$A38,attestations!$R$2:$R$2000,"Image")) -> 1 | R38: =IF($A38="","",COUNTIFS(attestations!$B$2:$B$2000,$A38,attestations!$R$2:$R$2000,"Textual")) -> 7 | S38: =IF($A38="","",COUNTIFS(attestations!$B$2:$B$2000,$A38,attestations!$D$2:$D$2000,"Geometry (Setting)")) -> 5 | T38: =IF($A38="","",IF($O38>=6,"High",IF($O38>=3,"Medium",IF($O38>=1,"Low","None")))) -> High | U38: =IF($A38="","",IF(COUNTIFS(attestations!$B$2:$B$2000,$A38,attestations!$I$2:$I$2000,"Georeferenced map GCP")>0,"Y","N")) -> Y | V38: Candidate | W38: High | X38: PRR station; commissary closed 1911 when Gatun Lake began filling (Der Seebote 1913-05-18). 1906 post offices; 'Tavernilla' from 1884. 106+61 CA hits. | lifespan extended 2026-09-14 La Estrella prints Tabernilla to 1913 [end was: 1911] | Y38: Town
A39: CZ-027 | B39: Gamboa | D39: Town | E39: Persists | F39: Other | G39: Infrastructure | H39: Mixed | I39: c.1882 | K39: Approximate | L39: Medium | M39: =IF($A39="","",IF($L39="High","Solid point",IF($L39="Medium","Point + buffer",IF($L39="Low","Translucent area",IF($L39="Disputed","Candidate points",IF($L39="Unknown","Unplotted (unlocated panel)","-")))))) -> Point + buffer | N39: 300 | O39: =IF($A39="","",COUNTIF(attestations!$B$2:$B$2000,$A39)) -> 16 | P39: =IF($A39="","",COUNTIFS(attestations!$B$2:$B$2000,$A39,attestations!$R$2:$R$2000,"Map")) -> 1 | Q39: =IF($A39="","",COUNTIFS(attestations!$B$2:$B$2000,$A39,attestations!$R$2:$R$2000,"Image")) -> 1 | R39: =IF($A39="","",COUNTIFS(attestations!$B$2:$B$2000,$A39,attestations!$R$2:$R$2000,"Textual")) -> 6 | S39: =IF($A39="","",COUNTIFS(attestations!$B$2:$B$2000,$A39,attestations!$D$2:$D$2000,"Geometry (Setting)")) -> 5 | T39: =IF($A39="","",IF($O39>=6,"High",IF($O39>=3,"Medium",IF($O39>=1,"Low","None")))) -> High | U39: =IF($A39="","",IF(COUNTIFS(attestations!$B$2:$B$2000,$A39,attestations!$I$2:$I$2000,"Georeferenced map GCP")>0,"Y","N")) -> Y | V39: Candidate | W39: Medium | X39: Chagres-crossing town, later dredging division HQ. 1882 French brigade list. 2,413 CA hits. | Y39: Town | AA39: Town where the railroad crossed the Chagres River; later headquarters of the canal's dredging division.
A40: CZ-028 | B40: Miraflores | D40: Village | E40: Depopulated-not flooded | F40: Other | G40: Displacement | H40: Panamanian village | I40: c.1906-1909? | J40: c.1913 | K40: Approximate | L40: Medium | M40: =IF($A40="","",IF($L40="High","Solid point",IF($L40="Medium","Point + buffer",IF($L40="Low","Translucent area",IF($L40="Disputed","Candidate points",IF($L40="Unknown","Unplotted (unlocated panel)","-")))))) -> Point + buffer | N40: 300 | O40: =IF($A40="","",COUNTIF(attestations!$B$2:$B$2000,$A40)) -> 16 | P40: =IF($A40="","",COUNTIFS(attestations!$B$2:$B$2000,$A40,attestations!$R$2:$R$2000,"Map")) -> 2 | Q40: =IF($A40="","",COUNTIFS(attestations!$B$2:$B$2000,$A40,attestations!$R$2:$R$2000,"Image")) -> 1 | R40: =IF($A40="","",COUNTIFS(attestations!$B$2:$B$2000,$A40,attestations!$R$2:$R$2000,"Textual")) -> 6 | S40: =IF($A40="","",COUNTIFS(attestations!$B$2:$B$2000,$A40,attestations!$D$2:$D$2000,"Geometry (Setting)")) -> 3 | T40: =IF($A40="","",IF($O40>=6,"High",IF($O40>=3,"Medium",IF($O40>=1,"Low","None")))) -> High | U40: =IF($A40="","",IF(COUNTIFS(attestations!$B$2:$B$2000,$A40,attestations!$I$2:$I$2000,"Georeferenced map GCP")>0,"Y","N")) -> Y | V40: Candidate | W40: High | X40: Old village displaced by Miraflores Locks works. 1897 lock-plan article; 1907 ICC dump list. 1,470 CA hits. | RESOLVED 2026-09-13: founding date stands. KWIC showed the 1897 press line ('one lock at Miraflores...') and the 1895 French drawing attest the LOCK SITE/toponym, not a settlement; toponym in press from Jan 1881 (French launch). No settlement evidenced before the US era: 1905-06 survey searched-absent, then 1907 spoil dumps, 1909 town dot, 1911 camp blocks. start was 'c.1855?' (PRR-era village claim - no support found, withdrawn). | RULING 2026-09-14 (conflict half, delegated): the A-0879 1905-06 searched-absence vs 1909 town dot is RESOLVED as corroboration of the US-era founding - absence-then-presence brackets the start; 'c.1906-1909?' stands (1907 mentions are works, not clearly settlement - no sharpening). Both questions on this place now closed. | Y40: Town
A41: CZ-029 | B41: Cucaracha | D41: Village | E41: Depopulated-not flooded | F41: Other | G41: Labor | H41: Mixed | I41: c.1883? | J41: c.1914 | K41: Unknown | L41: Medium | M41: =IF($A41="","",IF($L41="High","Solid point",IF($L41="Medium","Point + buffer",IF($L41="Low","Translucent area",IF($L41="Disputed","Candidate points",IF($L41="Unknown","Unplotted (unlocated panel)","-")))))) -> Point + buffer | N41: 300 | O41: =IF($A41="","",COUNTIF(attestations!$B$2:$B$2000,$A41)) -> 18 | P41: =IF($A41="","",COUNTIFS(attestations!$B$2:$B$2000,$A41,attestations!$R$2:$R$2000,"Map")) -> 1 | Q41: =IF($A41="","",COUNTIFS(attestations!$B$2:$B$2000,$A41,attestations!$R$2:$R$2000,"Image")) -> 1 | R41: =IF($A41="","",COUNTIFS(attestations!$B$2:$B$2000,$A41,attestations!$R$2:$R$2000,"Textual")) -> 5 | S41: =IF($A41="","",COUNTIFS(attestations!$B$2:$B$2000,$A41,attestations!$D$2:$D$2000,"Geometry (Setting)")) -> 6 | T41: =IF($A41="","",IF($O41>=6,"High",IF($O41>=3,"Medium",IF($O41>=1,"Low","None")))) -> High | U41: =IF($A41="","",IF(COUNTIFS(attestations!$B$2:$B$2000,$A41,attestations!$I$2:$I$2000,"Georeferenced map GCP")>0,"Y","N")) -> Y | V41: Candidate | W41: Medium | X41: Settlement at Culebra Cut, namesake of the Cucaracha slide. 974 CA hits from 1883-05-11; individual pages not yet verified. | lifespan extended 2026-09-14 La Estrella prints Cucaracha to 1914 - the slide year kept the name alive in the Panamanian press [end was: c.1913?] | Y41: Town
A42: CZ-030 | B42: Mindi | D42: Station | E42: Unknown | F42: Unknown | G42: Infrastructure | H42: Panamanian village | I42: c.1855 | K42: Approximate | L42: Low | M42: =IF($A42="","",IF($L42="High","Solid point",IF($L42="Medium","Point + buffer",IF($L42="Low","Translucent area",IF($L42="Disputed","Candidate points",IF($L42="Unknown","Unplotted (unlocated panel)","-")))))) -> Translucent area | N42: 400 | O42: =IF($A42="","",COUNTIF(attestations!$B$2:$B$2000,$A42)) -> 20 | P42: =IF($A42="","",COUNTIFS(attestations!$B$2:$B$2000,$A42,attestations!$R$2:$R$2000,"Map")) -> 2 | Q42: =IF($A42="","",COUNTIFS(attestations!$B$2:$B$2000,$A42,attestations!$R$2:$R$2000,"Image")) -> 1 | R42: =IF($A42="","",COUNTIFS(attestations!$B$2:$B$2000,$A42,attestations!$R$2:$R$2000,"Textual")) -> 5 | S42: =IF($A42="","",COUNTIFS(attestations!$B$2:$B$2000,$A42,attestations!$D$2:$D$2000,"Geometry (Setting)")) -> 3 | T42: =IF($A42="","",IF($O42>=6,"High",IF($O42>=3,"Medium",IF($O42>=1,"Low","None")))) -> High | U42: =IF($A42="","",IF(COUNTIFS(attestations!$B$2:$B$2000,$A42,attestations!$I$2:$I$2000,"Georeferenced map GCP")>0,"Y","N")) -> Y | V42: Candidate | W42: Medium | X42: PRR station near Atlantic end. 557 CA hits from 1880-02-03. CAUTION: also a diverted-stream name (1906 table). | INVESTIGATED 2026-09-13: 1911 property map and 1905-06 survey agree within ~200 m; the 1909 label (~2.2 km SSE) is the dissenting claim and stands as a plotted candidate. No coordinate change. | Y42: Town
A43: CZ-031 | B43: Buena Vista | D43: Station | E43: Submerged | F43: Gatun Lake flooding | G43: Displacement | H43: Panamanian village | I43: c.1855 | J43: 1911-1914 | K43: Approximate | L43: Medium | M43: =IF($A43="","",IF($L43="High","Solid point",IF($L43="Medium","Point + buffer",IF($L43="Low","Translucent area",IF($L43="Disputed","Candidate points",IF($L43="Unknown","Unplotted (unlocated panel)","-")))))) -> Point + buffer | N43: 300 | O43: =IF($A43="","",COUNTIF(attestations!$B$2:$B$2000,$A43)) -> 21 | P43: =IF($A43="","",COUNTIFS(attestations!$B$2:$B$2000,$A43,attestations!$R$2:$R$2000,"Map")) -> 1 | Q43: =IF($A43="","",COUNTIFS(attestations!$B$2:$B$2000,$A43,attestations!$R$2:$R$2000,"Image")) -> 0 | R43: =IF($A43="","",COUNTIFS(attestations!$B$2:$B$2000,$A43,attestations!$R$2:$R$2000,"Textual")) -> 4 | S43: =IF($A43="","",COUNTIFS(attestations!$B$2:$B$2000,$A43,attestations!$D$2:$D$2000,"Geometry (Setting)")) -> 5 | T43: =IF($A43="","",IF($O43>=6,"High",IF($O43>=3,"Medium",IF($O43>=1,"Low","None")))) -> High | U43: =IF($A43="","",IF(COUNTIFS(attestations!$B$2:$B$2000,$A43,attestations!$I$2:$I$2000,"Georeferenced map GCP")>0,"Y","N")) -> Y | V43: Candidate | W43: Medium | X43: PRR station near Gatun, in the flooded reach. 359 CA hits from 1903-03-16; generic name, verify hits individually. SPLIT 2026-09-13: the Pacific-side camp claims (A-0503/A-0540/A-0609 + the CULEBRACAMPS footprint) moved to CZ-155 - this row is the Atlantic old-line station/village only. Text mentions (Canal Record, newspapers, Smithsonian) are generic-name hits kept here; verify individually if either place's paper trail matters. | 2026-09-13: CZ-074 Isla Vista merged in as a probable 1862 label artifact (its single read already sat here; Canal Record: 0 pages). | Y43: Town
A44: CZ-032 | B44: Lion Hill | D44: Station | E44: Submerged | F44: Gatun Lake flooding | G44: Displacement | H44: Panamanian village | I44: c.1855 | J44: 1911-1914 | K44: Approximate | L44: Medium | M44: =IF($A44="","",IF($L44="High","Solid point",IF($L44="Medium","Point + buffer",IF($L44="Low","Translucent area",IF($L44="Disputed","Candidate points",IF($L44="Unknown","Unplotted (unlocated panel)","-")))))) -> Point + buffer | N44: 250 | O44: =IF($A44="","",COUNTIF(attestations!$B$2:$B$2000,$A44)) -> 16 | P44: =IF($A44="","",COUNTIFS(attestations!$B$2:$B$2000,$A44,attestations!$R$2:$R$2000,"Map")) -> 2 | Q44: =IF($A44="","",COUNTIFS(attestations!$B$2:$B$2000,$A44,attestations!$R$2:$R$2000,"Image")) -> 0 | R44: =IF($A44="","",COUNTIFS(attestations!$B$2:$B$2000,$A44,attestations!$R$2:$R$2000,"Textual")) -> 5 | S44: =IF($A44="","",COUNTIFS(attestations!$B$2:$B$2000,$A44,attestations!$D$2:$D$2000,"Geometry (Setting)")) -> 5 | T44: =IF($A44="","",IF($O44>=6,"High",IF($O44>=3,"Medium",IF($O44>=1,"Low","None")))) -> High | U44: =IF($A44="","",IF(COUNTIFS(attestations!$B$2:$B$2000,$A44,attestations!$I$2:$I$2000,"Georeferenced map GCP")>0,"Y","N")) -> Y | V44: Candidate | W44: Medium | X44: PRR station flooded by Gatun Lake. 256 CA hits from 1880-02-07. | Y44: Town
A45: CZ-033 | B45: Tiger Hill | D45: Station | E45: Submerged | F45: Gatun Lake flooding | G45: Displacement | H45: Panamanian village | I45: c.1855 | J45: 1911-1914 | K45: Approximate | L45: Unknown | M45: =IF($A45="","",IF($L45="High","Solid point",IF($L45="Medium","Point + buffer",IF($L45="Low","Translucent area",IF($L45="Disputed","Candidate points",IF($L45="Unknown","Unplotted (unlocated panel)","-")))))) -> Unplotted (unlocated panel) | O45: =IF($A45="","",COUNTIF(attestations!$B$2:$B$2000,$A45)) -> 15 | P45: =IF($A45="","",COUNTIFS(attestations!$B$2:$B$2000,$A45,attestations!$R$2:$R$2000,"Map")) -> 1 | Q45: =IF($A45="","",COUNTIFS(attestations!$B$2:$B$2000,$A45,attestations!$R$2:$R$2000,"Image")) -> 0 | R45: =IF($A45="","",COUNTIFS(attestations!$B$2:$B$2000,$A45,attestations!$R$2:$R$2000,"Textual")) -> 5 | S45: =IF($A45="","",COUNTIFS(attestations!$B$2:$B$2000,$A45,attestations!$D$2:$D$2000,"Geometry (Setting)")) -> 1 | T45: =IF($A45="","",IF($O45>=6,"High",IF($O45>=3,"Medium",IF($O45>=1,"Low","None")))) -> High | U45: =IF($A45="","",IF(COUNTIFS(attestations!$B$2:$B$2000,$A45,attestations!$I$2:$I$2000,"Georeferenced map GCP")>0,"Y","N")) -> N | V45: Candidate | W45: Medium | X45: PRR station flooded by Gatun Lake. 175 CA hits from 1882-01-06. | Y45: Town
A46: CZ-034 | B46: Mamei | D46: Station | E46: Submerged | F46: Gatun Lake flooding | G46: Displacement | H46: Panamanian village | I46: c.1855 | J46: 1911-1914 | K46: Approximate | L46: Low | M46: =IF($A46="","",IF($L46="High","Solid point",IF($L46="Medium","Point + buffer",IF($L46="Low","Translucent area",IF($L46="Disputed","Candidate points",IF($L46="Unknown","Unplotted (unlocated panel)","-")))))) -> Translucent area | N46: 600 | O46: =IF($A46="","",COUNTIF(attestations!$B$2:$B$2000,$A46)) -> 18 | P46: =IF($A46="","",COUNTIFS(attestations!$B$2:$B$2000,$A46,attestations!$R$2:$R$2000,"Map")) -> 2 | Q46: =IF($A46="","",COUNTIFS(attestations!$B$2:$B$2000,$A46,attestations!$R$2:$R$2000,"Image")) -> 1 | R46: =IF($A46="","",COUNTIFS(attestations!$B$2:$B$2000,$A46,attestations!$R$2:$R$2000,"Textual")) -> 5 | S46: =IF($A46="","",COUNTIFS(attestations!$B$2:$B$2000,$A46,attestations!$D$2:$D$2000,"Geometry (Setting)")) -> 4 | T46: =IF($A46="","",IF($O46>=6,"High",IF($O46>=3,"Medium",IF($O46>=1,"Low","None")))) -> High | U46: =IF($A46="","",IF(COUNTIFS(attestations!$B$2:$B$2000,$A46,attestations!$I$2:$I$2000,"Georeferenced map GCP")>0,"Y","N")) -> Y | V46: Candidate | W46: Medium | X46: PRR station / ICC dump site (1907 list, verified). 141 CA hits from 1880-02-15. | Y46: Town
A47: CZ-035 | B47: Camp Elliott | D47: Military base | E47: Depopulated-not flooded | F47: Other | G47: U.S. administration | H47: Mixed | I47: c.1904 | J47: c.1914 | K47: Approximate | L47: Medium | M47: =IF($A47="","",IF($L47="High","Solid point",IF($L47="Medium","Point + buffer",IF($L47="Low","Translucent area",IF($L47="Disputed","Candidate points",IF($L47="Unknown","Unplotted (unlocated panel)","-")))))) -> Point + buffer | N47: 300 | O47: =IF($A47="","",COUNTIF(attestations!$B$2:$B$2000,$A47)) -> 14 | P47: =IF($A47="","",COUNTIFS(attestations!$B$2:$B$2000,$A47,attestations!$R$2:$R$2000,"Map")) -> 0 | Q47: =IF($A47="","",COUNTIFS(attestations!$B$2:$B$2000,$A47,attestations!$R$2:$R$2000,"Image")) -> 0 | R47: =IF($A47="","",COUNTIFS(attestations!$B$2:$B$2000,$A47,attestations!$R$2:$R$2000,"Textual")) -> 5 | S47: =IF($A47="","",COUNTIFS(attestations!$B$2:$B$2000,$A47,attestations!$D$2:$D$2000,"Geometry (Setting)")) -> 4 | T47: =IF($A47="","",IF($O47>=6,"High",IF($O47>=3,"Medium",IF($O47>=1,"Low","None")))) -> High | U47: =IF($A47="","",IF(COUNTIFS(attestations!$B$2:$B$2000,$A47,attestations!$I$2:$I$2000,"Georeferenced map GCP")>0,"Y","N")) -> Y | V47: Candidate | W47: Medium | X47: U.S. Marine camp near Bas Obispo (cf. 1913 Seebote: Bas Obispo commissary closed for being too near the Marine camp). 209 CA hits from 1903-12-26. | Y47: Town
A48: CZ-036 | B48: Monte Lirio | D48: Village | E48: Unknown | F48: Unknown | G48: Infrastructure | H48: Mixed | I48: c.1909 | K48: Approximate | L48: Low | M48: =IF($A48="","",IF($L48="High","Solid point",IF($L48="Medium","Point + buffer",IF($L48="Low","Translucent area",IF($L48="Disputed","Candidate points",IF($L48="Unknown","Unplotted (unlocated panel)","-")))))) -> Translucent area | N48: 500 | O48: =IF($A48="","",COUNTIF(attestations!$B$2:$B$2000,$A48)) -> 15 | P48: =IF($A48="","",COUNTIFS(attestations!$B$2:$B$2000,$A48,attestations!$R$2:$R$2000,"Map")) -> 0 | Q48: =IF($A48="","",COUNTIFS(attestations!$B$2:$B$2000,$A48,attestations!$R$2:$R$2000,"Image")) -> 1 | R48: =IF($A48="","",COUNTIFS(attestations!$B$2:$B$2000,$A48,attestations!$R$2:$R$2000,"Textual")) -> 5 | S48: =IF($A48="","",COUNTIFS(attestations!$B$2:$B$2000,$A48,attestations!$D$2:$D$2000,"Geometry (Setting)")) -> 3 | T48: =IF($A48="","",IF($O48>=6,"High",IF($O48>=3,"Medium",IF($O48>=1,"Low","None")))) -> High | U48: =IF($A48="","",IF(COUNTIFS(attestations!$B$2:$B$2000,$A48,attestations!$I$2:$I$2000,"Georeferenced map GCP")>0,"Y","N")) -> Y | V48: Candidate | W48: Medium | X48: Town on the relocated PRR line. 23 CA hits from 1910-11-29. | Y48: Town
A49: CZ-037 | B49: Toro Point | D49: Construction camp | E49: Depopulated-not flooded | F49: Other | G49: Infrastructure | H49: Mixed | I49: c.1907 | K49: Unknown | L49: Medium | M49: =IF($A49="","",IF($L49="High","Solid point",IF($L49="Medium","Point + buffer",IF($L49="Low","Translucent area",IF($L49="Disputed","Candidate points",IF($L49="Unknown","Unplotted (unlocated panel)","-")))))) -> Point + buffer | N49: 300 | O49: =IF($A49="","",COUNTIF(attestations!$B$2:$B$2000,$A49)) -> 14 | P49: =IF($A49="","",COUNTIFS(attestations!$B$2:$B$2000,$A49,attestations!$R$2:$R$2000,"Map")) -> 1 | Q49: =IF($A49="","",COUNTIFS(attestations!$B$2:$B$2000,$A49,attestations!$R$2:$R$2000,"Image")) -> 1 | R49: =IF($A49="","",COUNTIFS(attestations!$B$2:$B$2000,$A49,attestations!$R$2:$R$2000,"Textual")) -> 6 | S49: =IF($A49="","",COUNTIFS(attestations!$B$2:$B$2000,$A49,attestations!$D$2:$D$2000,"Geometry (Setting)")) -> 2 | T49: =IF($A49="","",IF($O49>=6,"High",IF($O49>=3,"Medium",IF($O49>=1,"Low","None")))) -> High | U49: =IF($A49="","",IF(COUNTIFS(attestations!$B$2:$B$2000,$A49,attestations!$I$2:$I$2000,"Georeferenced map GCP")>0,"Y","N")) -> Y | V49: Candidate | W49: Medium | X49: Breakwater works / later Fort Sherman site, Atlantic entrance. 289 CA hits; records not yet harvested. | Y49: Town
A50: CZ-039 | B50: Balboa | D50: Town | E50: Persists | F50: Other | G50: U.S. administration | H50: Mixed | I50: c.1909 | K50: Approximate | L50: Unknown | M50: =IF($A50="","",IF($L50="High","Solid point",IF($L50="Medium","Point + buffer",IF($L50="Low","Translucent area",IF($L50="Disputed","Candidate points",IF($L50="Unknown","Unplotted (unlocated panel)","-")))))) -> Unplotted (unlocated panel) | O50: =IF($A50="","",COUNTIF(attestations!$B$2:$B$2000,$A50)) -> 13 | P50: =IF($A50="","",COUNTIFS(attestations!$B$2:$B$2000,$A50,attestations!$R$2:$R$2000,"Map")) -> 0 | Q50: =IF($A50="","",COUNTIFS(attestations!$B$2:$B$2000,$A50,attestations!$R$2:$R$2000,"Image")) -> 1 | R50: =IF($A50="","",COUNTIFS(attestations!$B$2:$B$2000,$A50,attestations!$R$2:$R$2000,"Textual")) -> 4 | S50: =IF($A50="","",COUNTIFS(attestations!$B$2:$B$2000,$A50,attestations!$D$2:$D$2000,"Geometry (Setting)")) -> 4 | T50: =IF($A50="","",IF($O50>=6,"High",IF($O50>=3,"Medium",IF($O50>=1,"Low","None")))) -> High | U50: =IF($A50="","",IF(COUNTIFS(attestations!$B$2:$B$2000,$A50,attestations!$I$2:$I$2000,"Georeferenced map GCP")>0,"Y","N")) -> Y | V50: Candidate | X50: Pacific terminal town, successor of La Boca (renamed c.1909); still exists. 1,881 CA hits from 1904-01-15. | Y50: Town | AA50: The canal's Pacific terminal town. It succeeded La Boca, renamed Balboa around 1909.
A51: CZ-040 | B51: Mount Hope | C51: Mount Hope; Monkey Hill | D51: Town | E51: Persists | F51: Other | G51: U.S. administration | H51: West Indian / Silver Roll | I51: c.1880 | K51: Approximate | L51: Low | M51: =IF($A51="","",IF($L51="High","Solid point",IF($L51="Medium","Point + buffer",IF($L51="Low","Translucent area",IF($L51="Disputed","Candidate points",IF($L51="Unknown","Unplotted (unlocated panel)","-")))))) -> Translucent area | N51: 400 | O51: =IF($A51="","",COUNTIF(attestations!$B$2:$B$2000,$A51)) -> 23 | P51: =IF($A51="","",COUNTIFS(attestations!$B$2:$B$2000,$A51,attestations!$R$2:$R$2000,"Map")) -> 2 | Q51: =IF($A51="","",COUNTIFS(attestations!$B$2:$B$2000,$A51,attestations!$R$2:$R$2000,"Image")) -> 1 | R51: =IF($A51="","",COUNTIFS(attestations!$B$2:$B$2000,$A51,attestations!$R$2:$R$2000,"Textual")) -> 5 | S51: =IF($A51="","",COUNTIFS(attestations!$B$2:$B$2000,$A51,attestations!$D$2:$D$2000,"Geometry (Setting)")) -> 5 | T51: =IF($A51="","",IF($O51>=6,"High",IF($O51>=3,"Medium",IF($O51>=1,"Low","None")))) -> High | U51: =IF($A51="","",IF(COUNTIFS(attestations!$B$2:$B$2000,$A51,attestations!$I$2:$I$2000,"Georeferenced map GCP")>0,"Y","N")) -> Y | V51: Candidate | X51: Atlantic-side storage/cemetery town near Cristobal (Monkey Hill until 1905). 1,867 CA hits from 1880-01-15. | Y51: Town | AA51: Storage and cemetery town near Cristóbal on the Atlantic side, called Monkey Hill until 1905.
A52: CZ-041 | B52: Taboga | D52: Village | E52: Persists | F52: Other | G52: Other | H52: Panamanian village | I52: pre-1844 | K52: Approximate | L52: Medium | M52: =IF($A52="","",IF($L52="High","Solid point",IF($L52="Medium","Point + buffer",IF($L52="Low","Translucent area",IF($L52="Disputed","Candidate points",IF($L52="Unknown","Unplotted (unlocated panel)","-")))))) -> Point + buffer | N52: 300 | O52: =IF($A52="","",COUNTIF(attestations!$B$2:$B$2000,$A52)) -> 13 | P52: =IF($A52="","",COUNTIFS(attestations!$B$2:$B$2000,$A52,attestations!$R$2:$R$2000,"Map")) -> 1 | Q52: =IF($A52="","",COUNTIFS(attestations!$B$2:$B$2000,$A52,attestations!$R$2:$R$2000,"Image")) -> 2 | R52: =IF($A52="","",COUNTIFS(attestations!$B$2:$B$2000,$A52,attestations!$R$2:$R$2000,"Textual")) -> 5 | S52: =IF($A52="","",COUNTIFS(attestations!$B$2:$B$2000,$A52,attestations!$D$2:$D$2000,"Geometry (Setting)")) -> 1 | T52: =IF($A52="","",IF($O52>=6,"High",IF($O52>=3,"Medium",IF($O52>=1,"Low","None")))) -> High | U52: =IF($A52="","",IF(COUNTIFS(attestations!$B$2:$B$2000,$A52,attestations!$I$2:$I$2000,"Georeferenced map GCP")>0,"Y","N")) -> Y | V52: Candidate | X52: Island town in Panama Bay; French-era sanatorium. Outside the Zone. 972 CA hits from 1882-09-11. | 2026-09-14: start pre-1850? -> pre-1844 (2026-09-14): I. Taboga drawn with village marks on the 1844 Garella carte. | Y52: Town | AA52: Island town in the Bay of Panama, outside the Canal Zone; a sanatorium during the French canal period.
A53: CZ-042 | B53: Porto Bello | C53: Porto Bello; Portobelo | D53: Town | E53: Persists | F53: Other | G53: Labor | H53: Panamanian village | I53: pre-1850? | K53: Approximate | L53: Medium | M53: =IF($A53="","",IF($L53="High","Solid point",IF($L53="Medium","Point + buffer",IF($L53="Low","Translucent area",IF($L53="Disputed","Candidate points",IF($L53="Unknown","Unplotted (unlocated panel)","-")))))) -> Point + buffer | N53: 300 | O53: =IF($A53="","",COUNTIF(attestations!$B$2:$B$2000,$A53)) -> 12 | P53: =IF($A53="","",COUNTIFS(attestations!$B$2:$B$2000,$A53,attestations!$R$2:$R$2000,"Map")) -> 0 | Q53: =IF($A53="","",COUNTIFS(attestations!$B$2:$B$2000,$A53,attestations!$R$2:$R$2000,"Image")) -> 1 | R53: =IF($A53="","",COUNTIFS(attestations!$B$2:$B$2000,$A53,attestations!$R$2:$R$2000,"Textual")) -> 5 | S53: =IF($A53="","",COUNTIFS(attestations!$B$2:$B$2000,$A53,attestations!$D$2:$D$2000,"Geometry (Setting)")) -> 1 | T53: =IF($A53="","",IF($O53>=6,"High",IF($O53>=3,"Medium",IF($O53>=1,"Low","None")))) -> High | U53: =IF($A53="","",IF(COUNTIFS(attestations!$B$2:$B$2000,$A53,attestations!$I$2:$I$2000,"Georeferenced map GCP")>0,"Y","N")) -> Y | V53: Candidate | X53: Colonial port outside the Zone; ICC quarry town during construction. 828 CA hits from 1880-04-15. Verified 1912 mention (rainfall record). | Y53: Town | AA53: Spanish colonial port outside the Canal Zone; a quarry town during canal construction.
A54: CZ-043 | B54: Alhajuela | D54: Hamlet | E54: Unknown | F54: Unknown | G54: Infrastructure | H54: Panamanian village | I54: c.1897? | K54: Unknown | L54: Unknown | M54: =IF($A54="","",IF($L54="High","Solid point",IF($L54="Medium","Point + buffer",IF($L54="Low","Translucent area",IF($L54="Disputed","Candidate points",IF($L54="Unknown","Unplotted (unlocated panel)","-")))))) -> Unplotted (unlocated panel) | O54: =IF($A54="","",COUNTIF(attestations!$B$2:$B$2000,$A54)) -> 13 | P54: =IF($A54="","",COUNTIFS(attestations!$B$2:$B$2000,$A54,attestations!$R$2:$R$2000,"Map")) -> 1 | Q54: =IF($A54="","",COUNTIFS(attestations!$B$2:$B$2000,$A54,attestations!$R$2:$R$2000,"Image")) -> 1 | R54: =IF($A54="","",COUNTIFS(attestations!$B$2:$B$2000,$A54,attestations!$R$2:$R$2000,"Textual")) -> 5 | S54: =IF($A54="","",COUNTIFS(attestations!$B$2:$B$2000,$A54,attestations!$D$2:$D$2000,"Geometry (Setting)")) -> 1 | T54: =IF($A54="","",IF($O54>=6,"High",IF($O54>=3,"Medium",IF($O54>=1,"Low","None")))) -> High | U54: =IF($A54="","",IF(COUNTIFS(attestations!$B$2:$B$2000,$A54,attestations!$I$2:$I$2000,"Georeferenced map GCP")>0,"Y","N")) -> Y | V54: Candidate | X54: Proposed Chagres dam site upstream of the Zone (1897 plan, verified); flooded by Lake Alajuela 1935 (outside 1880-1920 window). 121 CA hits. | Y54: Town
A55: CZ-044 | B55: Juan Grande | D55: Hamlet | E55: Unknown | F55: Unknown | G55: Other | H55: Panamanian village | K55: Unknown | L55: Medium | M55: =IF($A55="","",IF($L55="High","Solid point",IF($L55="Medium","Point + buffer",IF($L55="Low","Translucent area",IF($L55="Disputed","Candidate points",IF($L55="Unknown","Unplotted (unlocated panel)","-")))))) -> Point + buffer | N55: 250 | O55: =IF($A55="","",COUNTIF(attestations!$B$2:$B$2000,$A55)) -> 20 | P55: =IF($A55="","",COUNTIFS(attestations!$B$2:$B$2000,$A55,attestations!$R$2:$R$2000,"Map")) -> 1 | Q55: =IF($A55="","",COUNTIFS(attestations!$B$2:$B$2000,$A55,attestations!$R$2:$R$2000,"Image")) -> 1 | R55: =IF($A55="","",COUNTIFS(attestations!$B$2:$B$2000,$A55,attestations!$R$2:$R$2000,"Textual")) -> 5 | S55: =IF($A55="","",COUNTIFS(attestations!$B$2:$B$2000,$A55,attestations!$D$2:$D$2000,"Geometry (Setting)")) -> 5 | T55: =IF($A55="","",IF($O55>=6,"High",IF($O55>=3,"Medium",IF($O55>=1,"Low","None")))) -> High | U55: =IF($A55="","",IF(COUNTIFS(attestations!$B$2:$B$2000,$A55,attestations!$I$2:$I$2000,"Georeferenced map GCP")>0,"Y","N")) -> Y | V55: Candidate | X55: Name-only candidate: primarily a Chagres tributary (1906 diversion table, verified). Settlement existence unconfirmed. 48 CA hits. | Y55: Town
A56: CZ-045 | B56: Gatuncillo | D56: Hamlet | E56: Unknown | F56: Unknown | G56: Other | H56: Panamanian village | K56: Unknown | L56: Unknown | M56: =IF($A56="","",IF($L56="High","Solid point",IF($L56="Medium","Point + buffer",IF($L56="Low","Translucent area",IF($L56="Disputed","Candidate points",IF($L56="Unknown","Unplotted (unlocated panel)","-")))))) -> Unplotted (unlocated panel) | O56: =IF($A56="","",COUNTIF(attestations!$B$2:$B$2000,$A56)) -> 14 | P56: =IF($A56="","",COUNTIFS(attestations!$B$2:$B$2000,$A56,attestations!$R$2:$R$2000,"Map")) -> 1 | Q56: =IF($A56="","",COUNTIFS(attestations!$B$2:$B$2000,$A56,attestations!$R$2:$R$2000,"Image")) -> 0 | R56: =IF($A56="","",COUNTIFS(attestations!$B$2:$B$2000,$A56,attestations!$R$2:$R$2000,"Textual")) -> 5 | S56: =IF($A56="","",COUNTIFS(attestations!$B$2:$B$2000,$A56,attestations!$D$2:$D$2000,"Geometry (Setting)")) -> 0 | T56: =IF($A56="","",IF($O56>=6,"High",IF($O56>=3,"Medium",IF($O56>=1,"Low","None")))) -> High | U56: =IF($A56="","",IF(COUNTIFS(attestations!$B$2:$B$2000,$A56,attestations!$I$2:$I$2000,"Georeferenced map GCP")>0,"Y","N")) -> N | V56: Candidate | X56: Name-only candidate: primarily a river (1884 German report, verified). Settlement existence unconfirmed. 25 CA hits. | EXEMPLARY UNLOCATED 2026-09-14: survives in text, appears on no map across 17 archives + 5 text corpora. Kept in the unlocated panel as the dissertation's showcase of honest not-knowing - not to be chased further; NARA RG 185 paper (PI-91) is the only remaining route and is deliberately declined. | Y56: Town
A57: CZ-046 | B57: Balboa Heights | D57: Town | E57: Persists | F57: Other | G57: U.S. administration | H57: Gold Roll town | I57: c.1914 | K57: Approximate | L57: Unknown | M57: =IF($A57="","",IF($L57="High","Solid point",IF($L57="Medium","Point + buffer",IF($L57="Low","Translucent area",IF($L57="Disputed","Candidate points",IF($L57="Unknown","Unplotted (unlocated panel)","-")))))) -> Unplotted (unlocated panel) | O57: =IF($A57="","",COUNTIF(attestations!$B$2:$B$2000,$A57)) -> 8 | P57: =IF($A57="","",COUNTIFS(attestations!$B$2:$B$2000,$A57,attestations!$R$2:$R$2000,"Map")) -> 0 | Q57: =IF($A57="","",COUNTIFS(attestations!$B$2:$B$2000,$A57,attestations!$R$2:$R$2000,"Image")) -> 1 | R57: =IF($A57="","",COUNTIFS(attestations!$B$2:$B$2000,$A57,attestations!$R$2:$R$2000,"Textual")) -> 3 | S57: =IF($A57="","",COUNTIFS(attestations!$B$2:$B$2000,$A57,attestations!$D$2:$D$2000,"Geometry (Setting)")) -> 1 | T57: =IF($A57="","",IF($O57>=6,"High",IF($O57>=3,"Medium",IF($O57>=1,"Low","None")))) -> High | U57: =IF($A57="","",IF(COUNTIFS(attestations!$B$2:$B$2000,$A57,attestations!$I$2:$I$2000,"Georeferenced map GCP")>0,"Y","N")) -> N | V57: Candidate | W57: Medium | X57: Canal administration headquarters from 1914. 2,725 Canal Record pages. | Y57: Town | AA57: Headquarters of the canal administration from 1914.
A58: CZ-047 | B58: Chagres | D58: Village | E58: Depopulated-not flooded | F58: Other | G58: Displacement | H58: Panamanian village | I58: pre-1844 | J58: c.1916 | K58: Approximate | L58: Medium | M58: =IF($A58="","",IF($L58="High","Solid point",IF($L58="Medium","Point + buffer",IF($L58="Low","Translucent area",IF($L58="Disputed","Candidate points",IF($L58="Unknown","Unplotted (unlocated panel)","-")))))) -> Point + buffer | N58: 300 | O58: =IF($A58="","",COUNTIF(attestations!$B$2:$B$2000,$A58)) -> 14 | P58: =IF($A58="","",COUNTIFS(attestations!$B$2:$B$2000,$A58,attestations!$R$2:$R$2000,"Map")) -> 2 | Q58: =IF($A58="","",COUNTIFS(attestations!$B$2:$B$2000,$A58,attestations!$R$2:$R$2000,"Image")) -> 1 | R58: =IF($A58="","",COUNTIFS(attestations!$B$2:$B$2000,$A58,attestations!$R$2:$R$2000,"Textual")) -> 3 | S58: =IF($A58="","",COUNTIFS(attestations!$B$2:$B$2000,$A58,attestations!$D$2:$D$2000,"Geometry (Setting)")) -> 2 | T58: =IF($A58="","",IF($O58>=6,"High",IF($O58>=3,"Medium",IF($O58>=1,"Low","None")))) -> High | U58: =IF($A58="","",IF(COUNTIFS(attestations!$B$2:$B$2000,$A58,attestations!$I$2:$I$2000,"Georeferenced map GCP")>0,"Y","N")) -> Y | V58: Candidate | W58: High | X58: Historic village at the Chagres mouth (San Lorenzo). Canal Record Vol. IX (1915-16): 'To Remove the Village of Chagres... arrangements for the removal of the town.' 1,102 CR pages (river-name ambiguity). | 2026-09-14: start pre-1850? -> pre-1844 (2026-09-14): CHAGRES village on the 1844 Garella carte. | Y58: Town
A59: CZ-048 | B59: Palo Seco | C59: Palo Seco Leper Colony | D59: Hospital | E59: Persists | F59: Other | G59: U.S. administration | H59: Mixed | I59: c.1907 | K59: Approximate | L59: Medium | M59: =IF($A59="","",IF($L59="High","Solid point",IF($L59="Medium","Point + buffer",IF($L59="Low","Translucent area",IF($L59="Disputed","Candidate points",IF($L59="Unknown","Unplotted (unlocated panel)","-")))))) -> Point + buffer | N59: 300 | O59: =IF($A59="","",COUNTIF(attestations!$B$2:$B$2000,$A59)) -> 13 | P59: =IF($A59="","",COUNTIFS(attestations!$B$2:$B$2000,$A59,attestations!$R$2:$R$2000,"Map")) -> 0 | Q59: =IF($A59="","",COUNTIFS(attestations!$B$2:$B$2000,$A59,attestations!$R$2:$R$2000,"Image")) -> 1 | R59: =IF($A59="","",COUNTIFS(attestations!$B$2:$B$2000,$A59,attestations!$R$2:$R$2000,"Textual")) -> 3 | S59: =IF($A59="","",COUNTIFS(attestations!$B$2:$B$2000,$A59,attestations!$D$2:$D$2000,"Geometry (Setting)")) -> 1 | T59: =IF($A59="","",IF($O59>=6,"High",IF($O59>=3,"Medium",IF($O59>=1,"Low","None")))) -> High | U59: =IF($A59="","",IF(COUNTIFS(attestations!$B$2:$B$2000,$A59,attestations!$I$2:$I$2000,"Georeferenced map GCP")>0,"Y","N")) -> Y | V59: Candidate | W59: Medium | X59: Leper-colony settlement on the Pacific shore; community life documented ('Fireworks for Palo Seco', Vol. I). 103 CR pages. | 2026-09-13: 1940 census ED map attests it as 'Palo Seco Leper Colony', its own enumeration district (ED 1-6) - see A-1188. | Y59: Site/Institution | AA59: Leprosy colony on the Pacific shore, with its own community life; counted as a separate census district in 1940.
A60: CZ-049 | B60: Darien | D60: Station | E60: Unknown | F60: Unknown | G60: Infrastructure | H60: Mixed | I60: c.1912 | K60: Approximate | L60: Medium | M60: =IF($A60="","",IF($L60="High","Solid point",IF($L60="Medium","Point + buffer",IF($L60="Low","Translucent area",IF($L60="Disputed","Candidate points",IF($L60="Unknown","Unplotted (unlocated panel)","-")))))) -> Point + buffer | N60: 150 | O60: =IF($A60="","",COUNTIF(attestations!$B$2:$B$2000,$A60)) -> 7 | P60: =IF($A60="","",COUNTIFS(attestations!$B$2:$B$2000,$A60,attestations!$R$2:$R$2000,"Map")) -> 0 | Q60: =IF($A60="","",COUNTIFS(attestations!$B$2:$B$2000,$A60,attestations!$R$2:$R$2000,"Image")) -> 1 | R60: =IF($A60="","",COUNTIFS(attestations!$B$2:$B$2000,$A60,attestations!$R$2:$R$2000,"Textual")) -> 2 | S60: =IF($A60="","",COUNTIFS(attestations!$B$2:$B$2000,$A60,attestations!$D$2:$D$2000,"Geometry (Setting)")) -> 1 | T60: =IF($A60="","",IF($O60>=6,"High",IF($O60>=3,"Medium",IF($O60>=1,"Low","None")))) -> High | U60: =IF($A60="","",IF(COUNTIFS(attestations!$B$2:$B$2000,$A60,attestations!$I$2:$I$2000,"Georeferenced map GCP")>0,"Y","N")) -> Y | V60: Candidate | W60: Medium | X60: Station on the relocated PRR line. 369 CR pages (Darien region ambiguity). | Y60: Town
A61: CZ-050 | B61: Summit | C61: Summit; New Culebra | D61: Station | E61: Persists | F61: Other | G61: Infrastructure | H61: Mixed | I61: c.1904 | K61: Approximate | L61: Medium | M61: =IF($A61="","",IF($L61="High","Solid point",IF($L61="Medium","Point + buffer",IF($L61="Low","Translucent area",IF($L61="Disputed","Candidate points",IF($L61="Unknown","Unplotted (unlocated panel)","-")))))) -> Point + buffer | N61: 150 | O61: =IF($A61="","",COUNTIF(attestations!$B$2:$B$2000,$A61)) -> 11 | P61: =IF($A61="","",COUNTIFS(attestations!$B$2:$B$2000,$A61,attestations!$R$2:$R$2000,"Map")) -> 0 | Q61: =IF($A61="","",COUNTIFS(attestations!$B$2:$B$2000,$A61,attestations!$R$2:$R$2000,"Image")) -> 1 | R61: =IF($A61="","",COUNTIFS(attestations!$B$2:$B$2000,$A61,attestations!$R$2:$R$2000,"Textual")) -> 2 | S61: =IF($A61="","",COUNTIFS(attestations!$B$2:$B$2000,$A61,attestations!$D$2:$D$2000,"Geometry (Setting)")) -> 1 | T61: =IF($A61="","",IF($O61>=6,"High",IF($O61>=3,"Medium",IF($O61>=1,"Low","None")))) -> High | U61: =IF($A61="","",IF(COUNTIFS(attestations!$B$2:$B$2000,$A61,attestations!$I$2:$I$2000,"Georeferenced map GCP")>0,"Y","N")) -> Y | V61: Candidate | W61: Medium | X61: Relocated-line station; Canal Record: "New Culebra Named 'Summit'" - the renaming itself is documented. 128+49 CR pages. | lifespan extended 2026-09-14 Moses v00084: Cut spoil 'dumped in Summit' in 1904 [start was: c.1912] | Y61: Town | AA61: Station on the relocated railroad line. The Canal Record reported the renaming of New Culebra as Summit.
A62: CZ-051 | B62: Red Tank | D62: Village | E62: Depopulated-not flooded | F62: Other | G62: Afro-Caribbean life | H62: West Indian / Silver Roll | I62: c.1915 | K62: Approximate | L62: Medium | M62: =IF($A62="","",IF($L62="High","Solid point",IF($L62="Medium","Point + buffer",IF($L62="Low","Translucent area",IF($L62="Disputed","Candidate points",IF($L62="Unknown","Unplotted (unlocated panel)","-")))))) -> Point + buffer | N62: 250 | O62: =IF($A62="","",COUNTIF(attestations!$B$2:$B$2000,$A62)) -> 8 | P62: =IF($A62="","",COUNTIFS(attestations!$B$2:$B$2000,$A62,attestations!$R$2:$R$2000,"Map")) -> 0 | Q62: =IF($A62="","",COUNTIFS(attestations!$B$2:$B$2000,$A62,attestations!$R$2:$R$2000,"Image")) -> 1 | R62: =IF($A62="","",COUNTIFS(attestations!$B$2:$B$2000,$A62,attestations!$R$2:$R$2000,"Textual")) -> 3 | S62: =IF($A62="","",COUNTIFS(attestations!$B$2:$B$2000,$A62,attestations!$D$2:$D$2000,"Geometry (Setting)")) -> 1 | T62: =IF($A62="","",IF($O62>=6,"High",IF($O62>=3,"Medium",IF($O62>=1,"Low","None")))) -> High | U62: =IF($A62="","",IF(COUNTIFS(attestations!$B$2:$B$2000,$A62,attestations!$I$2:$I$2000,"Georeferenced map GCP")>0,"Y","N")) -> Y | V62: Candidate | W62: High | X62: Silver (West Indian) town near Pedro Miguel; commissary opened as branch of Pedro Miguel store (Vol. IX). 43 CR pages. | Y62: Town
A63: CZ-052 | B63: Camacho | D63: Village | E63: Depopulated-not flooded | F63: Other | G63: Labor | H63: Mixed | I63: c.1907 | K63: Unknown | L63: Low | M63: =IF($A63="","",IF($L63="High","Solid point",IF($L63="Medium","Point + buffer",IF($L63="Low","Translucent area",IF($L63="Disputed","Candidate points",IF($L63="Unknown","Unplotted (unlocated panel)","-")))))) -> Translucent area | N63: 400 | O63: =IF($A63="","",COUNTIF(attestations!$B$2:$B$2000,$A63)) -> 12 | P63: =IF($A63="","",COUNTIFS(attestations!$B$2:$B$2000,$A63,attestations!$R$2:$R$2000,"Map")) -> 1 | Q63: =IF($A63="","",COUNTIFS(attestations!$B$2:$B$2000,$A63,attestations!$R$2:$R$2000,"Image")) -> 1 | R63: =IF($A63="","",COUNTIFS(attestations!$B$2:$B$2000,$A63,attestations!$R$2:$R$2000,"Textual")) -> 3 | S63: =IF($A63="","",COUNTIFS(attestations!$B$2:$B$2000,$A63,attestations!$D$2:$D$2000,"Geometry (Setting)")) -> 2 | T63: =IF($A63="","",IF($O63>=6,"High",IF($O63>=3,"Medium",IF($O63>=1,"Low","None")))) -> High | U63: =IF($A63="","",IF(COUNTIFS(attestations!$B$2:$B$2000,$A63,attestations!$I$2:$I$2000,"Georeferenced map GCP")>0,"Y","N")) -> Y | V63: Candidate | W63: Medium | X63: Central-division settlement/district listed between Culebra and Empire in district tables. 229 CR pages. | Y63: Town
A64: CZ-053 | B64: Naos Island | D64: Construction camp | E64: Depopulated-not flooded | F64: Other | G64: Labor | H64: West Indian / Silver Roll | I64: by 1905-06 | K64: Approximate | L64: Low | M64: =IF($A64="","",IF($L64="High","Solid point",IF($L64="Medium","Point + buffer",IF($L64="Low","Translucent area",IF($L64="Disputed","Candidate points",IF($L64="Unknown","Unplotted (unlocated panel)","-")))))) -> Translucent area | N64: 400 | O64: =IF($A64="","",COUNTIF(attestations!$B$2:$B$2000,$A64)) -> 12 | P64: =IF($A64="","",COUNTIFS(attestations!$B$2:$B$2000,$A64,attestations!$R$2:$R$2000,"Map")) -> 2 | Q64: =IF($A64="","",COUNTIFS(attestations!$B$2:$B$2000,$A64,attestations!$R$2:$R$2000,"Image")) -> 1 | R64: =IF($A64="","",COUNTIFS(attestations!$B$2:$B$2000,$A64,attestations!$R$2:$R$2000,"Textual")) -> 3 | S64: =IF($A64="","",COUNTIFS(attestations!$B$2:$B$2000,$A64,attestations!$D$2:$D$2000,"Geometry (Setting)")) -> 3 | T64: =IF($A64="","",IF($O64>=6,"High",IF($O64>=3,"Medium",IF($O64>=1,"Low","None")))) -> High | U64: =IF($A64="","",IF(COUNTIFS(attestations!$B$2:$B$2000,$A64,attestations!$I$2:$I$2000,"Georeferenced map GCP")>0,"Y","N")) -> Y | V64: Candidate | W64: Medium | X64: Breakwater labor settlement served by La Boca labor trains; quarantine station. 127 CR pages. | 2026-09-14: start c.1907 -> by 1905-06 (2026-09-14): NAOS I. with buildings on the 1905-06 Map No.3. | Y64: Town
A65: CZ-054 | B65: El Vigia | D65: Station | E65: Unknown | F65: Unknown | G65: Infrastructure | H65: Panamanian village | K65: Unknown | L65: Unknown | M65: =IF($A65="","",IF($L65="High","Solid point",IF($L65="Medium","Point + buffer",IF($L65="Low","Translucent area",IF($L65="Disputed","Candidate points",IF($L65="Unknown","Unplotted (unlocated panel)","-")))))) -> Unplotted (unlocated panel) | O65: =IF($A65="","",COUNTIF(attestations!$B$2:$B$2000,$A65)) -> 13 | P65: =IF($A65="","",COUNTIFS(attestations!$B$2:$B$2000,$A65,attestations!$R$2:$R$2000,"Map")) -> 0 | Q65: =IF($A65="","",COUNTIFS(attestations!$B$2:$B$2000,$A65,attestations!$R$2:$R$2000,"Image")) -> 0 | R65: =IF($A65="","",COUNTIFS(attestations!$B$2:$B$2000,$A65,attestations!$R$2:$R$2000,"Textual")) -> 3 | S65: =IF($A65="","",COUNTIFS(attestations!$B$2:$B$2000,$A65,attestations!$D$2:$D$2000,"Geometry (Setting)")) -> 1 | T65: =IF($A65="","",IF($O65>=6,"High",IF($O65>=3,"Medium",IF($O65>=1,"Low","None")))) -> High | U65: =IF($A65="","",IF(COUNTIFS(attestations!$B$2:$B$2000,$A65,attestations!$I$2:$I$2000,"Georeferenced map GCP")>0,"Y","N")) -> Y | V65: Candidate | X65: Hydrographic/rain-gauge station on the Chagres; settlement status unconfirmed. 70 CR pages. | Y65: Town
A66: CZ-055 | B66: Diablo | C66: Diablo; Diablo Heights | D66: Village | E66: Depopulated-not flooded | F66: Other | G66: Displacement | H66: Mixed | I66: by 1905-06 | J66: 1913-1914 | K66: Approximate | L66: Medium | M66: =IF($A66="","",IF($L66="High","Solid point",IF($L66="Medium","Point + buffer",IF($L66="Low","Translucent area",IF($L66="Disputed","Candidate points",IF($L66="Unknown","Unplotted (unlocated panel)","-")))))) -> Point + buffer | N66: 250 | O66: =IF($A66="","",COUNTIF(attestations!$B$2:$B$2000,$A66)) -> 7 | P66: =IF($A66="","",COUNTIFS(attestations!$B$2:$B$2000,$A66,attestations!$R$2:$R$2000,"Map")) -> 0 | Q66: =IF($A66="","",COUNTIFS(attestations!$B$2:$B$2000,$A66,attestations!$R$2:$R$2000,"Image")) -> 0 | R66: =IF($A66="","",COUNTIFS(attestations!$B$2:$B$2000,$A66,attestations!$R$2:$R$2000,"Textual")) -> 2 | S66: =IF($A66="","",COUNTIFS(attestations!$B$2:$B$2000,$A66,attestations!$D$2:$D$2000,"Geometry (Setting)")) -> 2 | T66: =IF($A66="","",IF($O66>=6,"High",IF($O66>=3,"Medium",IF($O66>=1,"Low","None")))) -> High | U66: =IF($A66="","",IF(COUNTIFS(attestations!$B$2:$B$2000,$A66,attestations!$I$2:$I$2000,"Georeferenced map GCP")>0,"Y","N")) -> Y | V66: Candidate | W66: High | X66: Canal Record Vol. VII: 'Diablo Demolished. All of the buildings at Diablo...' Later rebuilt as Diablo Heights. 97 CR pages. 'Diablo Heights' (1940s American townsite on the site) equated as name variant 2026-09-07; post-1914 Diablo Heights mentions are toponym afterlife of the demolished village. Start widened c.1907 -> by 1905-06 2026-09-13: Camp Diablo is drawn on the 1905-06 survey at the identified position (A-0860). | 2026-09-14: split old/new - CZ-182 'Diablo Heights' carries the 1940s successor townsite (1939-40 Canal Record + both 1947 sheets, repointed); this id keeps the old village/camp, lifespan by 1905-06 - 1913/14 stands. | Y66: Town
A67: CZ-056 | B67: Agua Clara | D67: Village | E67: Submerged | F67: Gatun Lake flooding | G67: Displacement | H67: Panamanian village | J67: 1910-1913 | K67: Approximate | L67: Unknown | M67: =IF($A67="","",IF($L67="High","Solid point",IF($L67="Medium","Point + buffer",IF($L67="Low","Translucent area",IF($L67="Disputed","Candidate points",IF($L67="Unknown","Unplotted (unlocated panel)","-")))))) -> Unplotted (unlocated panel) | O67: =IF($A67="","",COUNTIF(attestations!$B$2:$B$2000,$A67)) -> 13 | P67: =IF($A67="","",COUNTIFS(attestations!$B$2:$B$2000,$A67,attestations!$R$2:$R$2000,"Map")) -> 1 | Q67: =IF($A67="","",COUNTIFS(attestations!$B$2:$B$2000,$A67,attestations!$R$2:$R$2000,"Image")) -> 1 | R67: =IF($A67="","",COUNTIFS(attestations!$B$2:$B$2000,$A67,attestations!$R$2:$R$2000,"Textual")) -> 2 | S67: =IF($A67="","",COUNTIFS(attestations!$B$2:$B$2000,$A67,attestations!$D$2:$D$2000,"Geometry (Setting)")) -> 0 | T67: =IF($A67="","",IF($O67>=6,"High",IF($O67>=3,"Medium",IF($O67>=1,"Low","None")))) -> High | U67: =IF($A67="","",IF(COUNTIFS(attestations!$B$2:$B$2000,$A67,attestations!$I$2:$I$2000,"Georeferenced map GCP")>0,"Y","N")) -> N | V67: Candidate | W67: High | X67: Canal Record Vol. III-IV flood reports: 'in Agua Clara, the whole village excepting two houses, are exposed.' Not previously in gazetteer. 36 CR pages. | EXEMPLARY UNLOCATED 2026-09-14: survives in text, appears on no map across 17 archives + 5 text corpora. Kept in the unlocated panel as the dissertation's showcase of honest not-knowing - not to be chased further; NARA RG 185 paper (PI-91) is the only remaining route and is deliberately declined. | Y67: Town
A68: CZ-057 | B68: Juan Mina | D68: Village | E68: Depopulated-not flooded | F68: Other | G68: Displacement | H68: Panamanian village | K68: Unknown | L68: Unknown | M68: =IF($A68="","",IF($L68="High","Solid point",IF($L68="Medium","Point + buffer",IF($L68="Low","Translucent area",IF($L68="Disputed","Candidate points",IF($L68="Unknown","Unplotted (unlocated panel)","-")))))) -> Unplotted (unlocated panel) | O68: =IF($A68="","",COUNTIF(attestations!$B$2:$B$2000,$A68)) -> 15 | P68: =IF($A68="","",COUNTIFS(attestations!$B$2:$B$2000,$A68,attestations!$R$2:$R$2000,"Map")) -> 1 | Q68: =IF($A68="","",COUNTIFS(attestations!$B$2:$B$2000,$A68,attestations!$R$2:$R$2000,"Image")) -> 0 | R68: =IF($A68="","",COUNTIFS(attestations!$B$2:$B$2000,$A68,attestations!$R$2:$R$2000,"Textual")) -> 2 | S68: =IF($A68="","",COUNTIFS(attestations!$B$2:$B$2000,$A68,attestations!$D$2:$D$2000,"Geometry (Setting)")) -> 1 | T68: =IF($A68="","",IF($O68>=6,"High",IF($O68>=3,"Medium",IF($O68>=1,"Low","None")))) -> High | U68: =IF($A68="","",IF(COUNTIFS(attestations!$B$2:$B$2000,$A68,attestations!$I$2:$I$2000,"Georeferenced map GCP")>0,"Y","N")) -> Y | V68: Candidate | W68: High | X68: Chagres village above Gamboa: 'the territory along the Chagres... including the village of Juan Mina' (Vol. VII property-map/depopulation context). Also a hydrographic station. 152 CR pages. | Y68: Town
A69: CZ-058 | B69: Enterprise | D69: Hamlet | E69: Unknown | F69: Unknown | G69: Labor | H69: Mixed | I69: c.1880s | K69: Unknown | L69: Low | M69: =IF($A69="","",IF($L69="High","Solid point",IF($L69="Medium","Point + buffer",IF($L69="Low","Translucent area",IF($L69="Disputed","Candidate points",IF($L69="Unknown","Unplotted (unlocated panel)","-")))))) -> Translucent area | N69: 400 | O69: =IF($A69="","",COUNTIF(attestations!$B$2:$B$2000,$A69)) -> 11 | P69: =IF($A69="","",COUNTIFS(attestations!$B$2:$B$2000,$A69,attestations!$R$2:$R$2000,"Map")) -> 0 | Q69: =IF($A69="","",COUNTIFS(attestations!$B$2:$B$2000,$A69,attestations!$R$2:$R$2000,"Image")) -> 0 | R69: =IF($A69="","",COUNTIFS(attestations!$B$2:$B$2000,$A69,attestations!$R$2:$R$2000,"Textual")) -> 2 | S69: =IF($A69="","",COUNTIFS(attestations!$B$2:$B$2000,$A69,attestations!$D$2:$D$2000,"Geometry (Setting)")) -> 3 | T69: =IF($A69="","",IF($O69>=6,"High",IF($O69>=3,"Medium",IF($O69>=1,"Low","None")))) -> High | U69: =IF($A69="","",IF(COUNTIFS(attestations!$B$2:$B$2000,$A69,attestations!$I$2:$I$2000,"Georeferenced map GCP")>0,"Y","N")) -> Y | V69: Candidate | W69: Medium | X69: Appears in French/early settlement lists beside San Pablo and Caimito Mulato (Vol. I). 60 CR pages. | Y69: Town
A70: CZ-059 | B70: Whitehouse | C70: White House; Casa Blanca | D70: Hamlet | E70: Unknown | F70: Unknown | G70: Labor | H70: Mixed | I70: c.1888 | K70: Unknown | L70: Medium | M70: =IF($A70="","",IF($L70="High","Solid point",IF($L70="Medium","Point + buffer",IF($L70="Low","Translucent area",IF($L70="Disputed","Candidate points",IF($L70="Unknown","Unplotted (unlocated panel)","-")))))) -> Point + buffer | N70: 300 | O70: =IF($A70="","",COUNTIF(attestations!$B$2:$B$2000,$A70)) -> 19 | P70: =IF($A70="","",COUNTIFS(attestations!$B$2:$B$2000,$A70,attestations!$R$2:$R$2000,"Map")) -> 1 | Q70: =IF($A70="","",COUNTIFS(attestations!$B$2:$B$2000,$A70,attestations!$R$2:$R$2000,"Image")) -> 0 | R70: =IF($A70="","",COUNTIFS(attestations!$B$2:$B$2000,$A70,attestations!$R$2:$R$2000,"Textual")) -> 2 | S70: =IF($A70="","",COUNTIFS(attestations!$B$2:$B$2000,$A70,attestations!$D$2:$D$2000,"Geometry (Setting)")) -> 5 | T70: =IF($A70="","",IF($O70>=6,"High",IF($O70>=3,"Medium",IF($O70>=1,"Low","None")))) -> High | U70: =IF($A70="","",IF(COUNTIFS(attestations!$B$2:$B$2000,$A70,attestations!$I$2:$I$2000,"Georeferenced map GCP")>0,"Y","N")) -> Y | V70: Candidate | W70: Medium | X70: French-era settlement near the Rio Camacho diversion (PI-91 Casa Blanca = Whitehouse; 15 Canal Record pages). MERGED 2026-09-09: 1907 encampment-plan camp at axis Sta 1600 (map 6, two quarters clusters) = same place; blueprint coordinate adopted, ICC1909 claim kept as attestation. | Y70: Town
A71: CZ-060 | B71: Vamos Vamos | D71: Hamlet | E71: Submerged | F71: Gatun Lake flooding | G71: Displacement | H71: Panamanian village | I71: pre-1844 | J71: 1911-1914 | K71: Approximate | L71: Unknown | M71: =IF($A71="","",IF($L71="High","Solid point",IF($L71="Medium","Point + buffer",IF($L71="Low","Translucent area",IF($L71="Disputed","Candidate points",IF($L71="Unknown","Unplotted (unlocated panel)","-")))))) -> Unplotted (unlocated panel) | O71: =IF($A71="","",COUNTIF(attestations!$B$2:$B$2000,$A71)) -> 18 | P71: =IF($A71="","",COUNTIFS(attestations!$B$2:$B$2000,$A71,attestations!$R$2:$R$2000,"Map")) -> 1 | Q71: =IF($A71="","",COUNTIFS(attestations!$B$2:$B$2000,$A71,attestations!$R$2:$R$2000,"Image")) -> 0 | R71: =IF($A71="","",COUNTIFS(attestations!$B$2:$B$2000,$A71,attestations!$R$2:$R$2000,"Textual")) -> 2 | S71: =IF($A71="","",COUNTIFS(attestations!$B$2:$B$2000,$A71,attestations!$D$2:$D$2000,"Geometry (Setting)")) -> 2 | T71: =IF($A71="","",IF($O71>=6,"High",IF($O71>=3,"Medium",IF($O71>=1,"Low","None")))) -> High | U71: =IF($A71="","",IF(COUNTIFS(attestations!$B$2:$B$2000,$A71,attestations!$I$2:$I$2000,"Georeferenced map GCP")>0,"Y","N")) -> Y | V71: Candidate | W71: High | X71: Chagres-side hamlet, K.21.6 area; on French sectional maps (PI-91 1:J1(c)) and diversion plans. 2 Canal Record pages. In the flooded reach. Start widened pre-1899 -> c.1862 2026-09-13: the 1862 plano draws the village itself (A-0891 first fix, village marks on the Chagres). | Y71: Town
A72: CZ-061 | B72: Pena Blanca | C72: Pena Blanca; Peña Blanca | D72: Hamlet | E72: Submerged | F72: Gatun Lake flooding | G72: Displacement | H72: Panamanian village | I72: c.1862 | J72: 1911-1914 | K72: Approximate | L72: Medium | M72: =IF($A72="","",IF($L72="High","Solid point",IF($L72="Medium","Point + buffer",IF($L72="Low","Translucent area",IF($L72="Disputed","Candidate points",IF($L72="Unknown","Unplotted (unlocated panel)","-")))))) -> Point + buffer | N72: 300 | O72: =IF($A72="","",COUNTIF(attestations!$B$2:$B$2000,$A72)) -> 16 | P72: =IF($A72="","",COUNTIFS(attestations!$B$2:$B$2000,$A72,attestations!$R$2:$R$2000,"Map")) -> 1 | Q72: =IF($A72="","",COUNTIFS(attestations!$B$2:$B$2000,$A72,attestations!$R$2:$R$2000,"Image")) -> 0 | R72: =IF($A72="","",COUNTIFS(attestations!$B$2:$B$2000,$A72,attestations!$R$2:$R$2000,"Textual")) -> 2 | S72: =IF($A72="","",COUNTIFS(attestations!$B$2:$B$2000,$A72,attestations!$D$2:$D$2000,"Geometry (Setting)")) -> 4 | T72: =IF($A72="","",IF($O72>=6,"High",IF($O72>=3,"Medium",IF($O72>=1,"Low","None")))) -> High | U72: =IF($A72="","",IF(COUNTIFS(attestations!$B$2:$B$2000,$A72,attestations!$I$2:$I$2000,"Georeferenced map GCP")>0,"Y","N")) -> Y | V72: Candidate | W72: High | X72: French lock No. 1 site (1888) and Chagres diversion point, K.22.9; in the flooded reach. PI-91 refs across entries 2 and 16. 2 Canal Record pages. Start concretized from 'pre-1884' to c.1862: the 1862 Chagres cadastral tract label (A-0584, S-028) is the earliest documented use of the name at this site. [2026-09-13 lifespan fix] | Y72: Town
A73: CZ-062 | B73: Cartagenita | C73: Cartagena | D73: Hamlet | E73: Unknown | F73: Unknown | G73: Labor | H73: Mixed | K73: Unknown | L73: Medium | M73: =IF($A73="","",IF($L73="High","Solid point",IF($L73="Medium","Point + buffer",IF($L73="Low","Translucent area",IF($L73="Disputed","Candidate points",IF($L73="Unknown","Unplotted (unlocated panel)","-")))))) -> Point + buffer | N73: 300 | O73: =IF($A73="","",COUNTIF(attestations!$B$2:$B$2000,$A73)) -> 18 | P73: =IF($A73="","",COUNTIFS(attestations!$B$2:$B$2000,$A73,attestations!$R$2:$R$2000,"Map")) -> 1 | Q73: =IF($A73="","",COUNTIFS(attestations!$B$2:$B$2000,$A73,attestations!$R$2:$R$2000,"Image")) -> 0 | R73: =IF($A73="","",COUNTIFS(attestations!$B$2:$B$2000,$A73,attestations!$R$2:$R$2000,"Textual")) -> 2 | S73: =IF($A73="","",COUNTIFS(attestations!$B$2:$B$2000,$A73,attestations!$D$2:$D$2000,"Geometry (Setting)")) -> 4 | T73: =IF($A73="","",IF($O73>=6,"High",IF($O73>=3,"Medium",IF($O73>=1,"Low","None")))) -> High | U73: =IF($A73="","",IF(COUNTIFS(attestations!$B$2:$B$2000,$A73,attestations!$I$2:$I$2000,"Georeferenced map GCP")>0,"Y","N")) -> Y | V73: Candidate | W73: Medium | X73: Pacific-side hamlet on French detailed plans (PI-91 2:F/231, F/338; 7 Canal Record pages). MERGED 2026-09-09: 1907 encampment-plan CARTAGENA hamlet at axis Sta 1890 (map 18, Rio Cartagenita valley) = same place; blueprint coordinate adopted, ICC1909 claim kept as attestation. | Y73: Town
A74: CZ-063 | B74: Palo Grande | D74: Hamlet | E74: Unknown | F74: Unknown | G74: Other | H74: Panamanian village | K74: Unknown | L74: Unknown | M74: =IF($A74="","",IF($L74="High","Solid point",IF($L74="Medium","Point + buffer",IF($L74="Low","Translucent area",IF($L74="Disputed","Candidate points",IF($L74="Unknown","Unplotted (unlocated panel)","-")))))) -> Unplotted (unlocated panel) | O74: =IF($A74="","",COUNTIF(attestations!$B$2:$B$2000,$A74)) -> 15 | P74: =IF($A74="","",COUNTIFS(attestations!$B$2:$B$2000,$A74,attestations!$R$2:$R$2000,"Map")) -> 1 | Q74: =IF($A74="","",COUNTIFS(attestations!$B$2:$B$2000,$A74,attestations!$R$2:$R$2000,"Image")) -> 0 | R74: =IF($A74="","",COUNTIFS(attestations!$B$2:$B$2000,$A74,attestations!$R$2:$R$2000,"Textual")) -> 2 | S74: =IF($A74="","",COUNTIFS(attestations!$B$2:$B$2000,$A74,attestations!$D$2:$D$2000,"Geometry (Setting)")) -> 2 | T74: =IF($A74="","",IF($O74>=6,"High",IF($O74>=3,"Medium",IF($O74>=1,"Low","None")))) -> High | U74: =IF($A74="","",IF(COUNTIFS(attestations!$B$2:$B$2000,$A74,attestations!$I$2:$I$2000,"Georeferenced map GCP")>0,"Y","N")) -> Y | V74: Candidate | W74: Medium | X74: Upper-Chagres river settlement on French sectional maps (PI-91 1:J1(m,n)). 2 Canal Record pages. | Y74: Town
A75: CZ-064 | B75: Cocoli | D75: Village | E75: Persists | F75: Other | G75: Infrastructure | H75: Mixed | I75: c.1881 | K75: Approximate | L75: Low | M75: =IF($A75="","",IF($L75="High","Solid point",IF($L75="Medium","Point + buffer",IF($L75="Low","Translucent area",IF($L75="Disputed","Candidate points",IF($L75="Unknown","Unplotted (unlocated panel)","-")))))) -> Translucent area | N75: 400 | O75: =IF($A75="","",COUNTIF(attestations!$B$2:$B$2000,$A75)) -> 16 | P75: =IF($A75="","",COUNTIFS(attestations!$B$2:$B$2000,$A75,attestations!$R$2:$R$2000,"Map")) -> 1 | Q75: =IF($A75="","",COUNTIFS(attestations!$B$2:$B$2000,$A75,attestations!$R$2:$R$2000,"Image")) -> 0 | R75: =IF($A75="","",COUNTIFS(attestations!$B$2:$B$2000,$A75,attestations!$R$2:$R$2000,"Textual")) -> 2 | S75: =IF($A75="","",COUNTIFS(attestations!$B$2:$B$2000,$A75,attestations!$D$2:$D$2000,"Geometry (Setting)")) -> 1 | T75: =IF($A75="","",IF($O75>=6,"High",IF($O75>=3,"Medium",IF($O75>=1,"Low","None")))) -> High | U75: =IF($A75="","",IF(COUNTIFS(attestations!$B$2:$B$2000,$A75,attestations!$I$2:$I$2000,"Georeferenced map GCP")>0,"Y","N")) -> Y | V75: Candidate | W75: Medium | X75: Pacific-side settlement on the Rio Cocoli (PI-91 2:F/306, 3:10); later a townsite. 107 Canal Record pages. | RULING 2026-09-13: split - this id keeps the OLD Cocoli village (incl. the 1911 property-map claim); the 1947 townsite read moved to CZ-171. | Y75: Town | AA75: Old village on the Cocolí River. The later US townsite of the same name is recorded as a separate place.
A76: CZ-065 | B76: Margarita | D76: Town | E76: Persists | F76: Other | G76: Infrastructure | H76: Mixed | I76: c.1917 | K76: Approximate | L76: Medium | M76: =IF($A76="","",IF($L76="High","Solid point",IF($L76="Medium","Point + buffer",IF($L76="Low","Translucent area",IF($L76="Disputed","Candidate points",IF($L76="Unknown","Unplotted (unlocated panel)","-")))))) -> Point + buffer | N76: 250 | O76: =IF($A76="","",COUNTIF(attestations!$B$2:$B$2000,$A76)) -> 10 | P76: =IF($A76="","",COUNTIFS(attestations!$B$2:$B$2000,$A76,attestations!$R$2:$R$2000,"Map")) -> 0 | Q76: =IF($A76="","",COUNTIFS(attestations!$B$2:$B$2000,$A76,attestations!$R$2:$R$2000,"Image")) -> 0 | R76: =IF($A76="","",COUNTIFS(attestations!$B$2:$B$2000,$A76,attestations!$R$2:$R$2000,"Textual")) -> 2 | S76: =IF($A76="","",COUNTIFS(attestations!$B$2:$B$2000,$A76,attestations!$D$2:$D$2000,"Geometry (Setting)")) -> 2 | T76: =IF($A76="","",IF($O76>=6,"High",IF($O76>=3,"Medium",IF($O76>=1,"Low","None")))) -> High | U76: =IF($A76="","",IF(COUNTIFS(attestations!$B$2:$B$2000,$A76,attestations!$I$2:$I$2000,"Georeferenced map GCP")>0,"Y","N")) -> Y | V76: Candidate | W76: Medium | X76: Atlantic-side Third Locks town, twin of Cocoli: 'quarters and other facilities in the new locks towns of Margarita and Cocoli' (Gov. Ann. Rep. 1941, IA). 1951 report pairs it with Paraiso as existing townsites. Added 2026-09-07. | lifespan extended to dated evidence 2026-09-13 [was: c.1940] | Y76: Town | AA76: Atlantic-side town of the Third Locks project (an unfinished 1940s plan to add a third set of locks), twin of Cocolí on the Pacific side.
A77: CZ-066 | B77: Coco Solo | D77: Military base | E77: Persists | F77: Other | G77: U.S. administration | H77: Mixed | I77: c.1918 | K77: Approximate | L77: Medium | M77: =IF($A77="","",IF($L77="High","Solid point",IF($L77="Medium","Point + buffer",IF($L77="Low","Translucent area",IF($L77="Disputed","Candidate points",IF($L77="Unknown","Unplotted (unlocated panel)","-")))))) -> Point + buffer | N77: 250 | O77: =IF($A77="","",COUNTIF(attestations!$B$2:$B$2000,$A77)) -> 10 | P77: =IF($A77="","",COUNTIFS(attestations!$B$2:$B$2000,$A77,attestations!$R$2:$R$2000,"Map")) -> 0 | Q77: =IF($A77="","",COUNTIFS(attestations!$B$2:$B$2000,$A77,attestations!$R$2:$R$2000,"Image")) -> 0 | R77: =IF($A77="","",COUNTIFS(attestations!$B$2:$B$2000,$A77,attestations!$R$2:$R$2000,"Textual")) -> 3 | S77: =IF($A77="","",COUNTIFS(attestations!$B$2:$B$2000,$A77,attestations!$D$2:$D$2000,"Geometry (Setting)")) -> 1 | T77: =IF($A77="","",IF($O77>=6,"High",IF($O77>=3,"Medium",IF($O77>=1,"Low","None")))) -> High | U77: =IF($A77="","",IF(COUNTIFS(attestations!$B$2:$B$2000,$A77,attestations!$I$2:$I$2000,"Georeferenced map GCP")>0,"Y","N")) -> Y | V77: Candidate | W77: Medium | X77: Submarine base + town, Atlantic side (184 IA texts; ECU oral histories). N.A.S. Coco Solo; hospital; transferred to Panama 1999, now part of Colon port area. Added 2026-09-07. | Y77: Town | AA77: US Navy submarine base and town on the Atlantic side. Transferred to Panama in 1999; now part of the port of Colón.
A78: CZ-067 | B78: Fort Clayton | D78: Military base | E78: Persists | F78: Other | G78: U.S. administration | H78: Mixed | I78: c.1919 | K78: Approximate | L78: Medium | M78: =IF($A78="","",IF($L78="High","Solid point",IF($L78="Medium","Point + buffer",IF($L78="Low","Translucent area",IF($L78="Disputed","Candidate points",IF($L78="Unknown","Unplotted (unlocated panel)","-")))))) -> Point + buffer | N78: 250 | O78: =IF($A78="","",COUNTIF(attestations!$B$2:$B$2000,$A78)) -> 10 | P78: =IF($A78="","",COUNTIFS(attestations!$B$2:$B$2000,$A78,attestations!$R$2:$R$2000,"Map")) -> 0 | Q78: =IF($A78="","",COUNTIFS(attestations!$B$2:$B$2000,$A78,attestations!$R$2:$R$2000,"Image")) -> 0 | R78: =IF($A78="","",COUNTIFS(attestations!$B$2:$B$2000,$A78,attestations!$R$2:$R$2000,"Textual")) -> 2 | S78: =IF($A78="","",COUNTIFS(attestations!$B$2:$B$2000,$A78,attestations!$D$2:$D$2000,"Geometry (Setting)")) -> 1 | T78: =IF($A78="","",IF($O78>=6,"High",IF($O78>=3,"Medium",IF($O78>=1,"Low","None")))) -> High | U78: =IF($A78="","",IF(COUNTIFS(attestations!$B$2:$B$2000,$A78,attestations!$I$2:$I$2000,"Georeferenced map GCP")>0,"Y","N")) -> Y | V78: Candidate | W78: Low | X78: US Army post, Pacific side. Handed to Panama 1999; now Ciudad del Saber (City of Knowledge). Added 2026-09-07 (military-post class; Camp Elliott precedent). | Y78: Town | AA78: US Army post on the Pacific side. Transferred to Panama in 1999; now the City of Knowledge (Ciudad del Saber).
A79: CZ-068 | B79: Fort Davis | D79: Military base | E79: Persists | F79: Other | G79: U.S. administration | H79: Mixed | I79: c.1919 | K79: Approximate | L79: Medium | M79: =IF($A79="","",IF($L79="High","Solid point",IF($L79="Medium","Point + buffer",IF($L79="Low","Translucent area",IF($L79="Disputed","Candidate points",IF($L79="Unknown","Unplotted (unlocated panel)","-")))))) -> Point + buffer | N79: 250 | O79: =IF($A79="","",COUNTIF(attestations!$B$2:$B$2000,$A79)) -> 9 | P79: =IF($A79="","",COUNTIFS(attestations!$B$2:$B$2000,$A79,attestations!$R$2:$R$2000,"Map")) -> 0 | Q79: =IF($A79="","",COUNTIFS(attestations!$B$2:$B$2000,$A79,attestations!$R$2:$R$2000,"Image")) -> 0 | R79: =IF($A79="","",COUNTIFS(attestations!$B$2:$B$2000,$A79,attestations!$R$2:$R$2000,"Textual")) -> 2 | S79: =IF($A79="","",COUNTIFS(attestations!$B$2:$B$2000,$A79,attestations!$D$2:$D$2000,"Geometry (Setting)")) -> 1 | T79: =IF($A79="","",IF($O79>=6,"High",IF($O79>=3,"Medium",IF($O79>=1,"Low","None")))) -> High | U79: =IF($A79="","",IF(COUNTIFS(attestations!$B$2:$B$2000,$A79,attestations!$I$2:$I$2000,"Georeferenced map GCP")>0,"Y","N")) -> Y | V79: Candidate | W79: Low | X79: US Army post 'between Gatun and Cristobal' with its own PRR station (Gov. Ann. Rep. 1919, IA). Handed to Panama 1999. Added 2026-09-07. | Y79: Town | AA79: US Army post between Gatún and Cristóbal, with its own railroad station. Transferred to Panama in 1999.
A80: CZ-069 | B80: Fort Sherman | D80: Military base | E80: Persists | F80: Other | G80: U.S. administration | H80: Mixed | I80: c.1912 | K80: Approximate | L80: Medium | M80: =IF($A80="","",IF($L80="High","Solid point",IF($L80="Medium","Point + buffer",IF($L80="Low","Translucent area",IF($L80="Disputed","Candidate points",IF($L80="Unknown","Unplotted (unlocated panel)","-")))))) -> Point + buffer | N80: 300 | O80: =IF($A80="","",COUNTIF(attestations!$B$2:$B$2000,$A80)) -> 9 | P80: =IF($A80="","",COUNTIFS(attestations!$B$2:$B$2000,$A80,attestations!$R$2:$R$2000,"Map")) -> 0 | Q80: =IF($A80="","",COUNTIFS(attestations!$B$2:$B$2000,$A80,attestations!$R$2:$R$2000,"Image")) -> 0 | R80: =IF($A80="","",COUNTIFS(attestations!$B$2:$B$2000,$A80,attestations!$R$2:$R$2000,"Textual")) -> 1 | S80: =IF($A80="","",COUNTIFS(attestations!$B$2:$B$2000,$A80,attestations!$D$2:$D$2000,"Geometry (Setting)")) -> 1 | T80: =IF($A80="","",IF($O80>=6,"High",IF($O80>=3,"Medium",IF($O80>=1,"Low","None")))) -> High | U80: =IF($A80="","",IF(COUNTIFS(attestations!$B$2:$B$2000,$A80,attestations!$I$2:$I$2000,"Georeferenced map GCP")>0,"Y","N")) -> Y | V80: Candidate | W80: Low | X80: US Army coast-artillery post at Toro Point, Atlantic entrance. Jungle warfare school; handed to Panama 1999. Added 2026-09-07. | Y80: Town | AA80: US Army coastal artillery post at the canal's Atlantic entrance, later a jungle warfare school. Transferred to Panama in 1999.
A81: CZ-070 | B81: Fort Amador | D81: Military base | E81: Persists | F81: Other | G81: U.S. administration | H81: Mixed | I81: c.1913 | K81: Approximate | L81: Medium | M81: =IF($A81="","",IF($L81="High","Solid point",IF($L81="Medium","Point + buffer",IF($L81="Low","Translucent area",IF($L81="Disputed","Candidate points",IF($L81="Unknown","Unplotted (unlocated panel)","-")))))) -> Point + buffer | N81: 250 | O81: =IF($A81="","",COUNTIF(attestations!$B$2:$B$2000,$A81)) -> 12 | P81: =IF($A81="","",COUNTIFS(attestations!$B$2:$B$2000,$A81,attestations!$R$2:$R$2000,"Map")) -> 0 | Q81: =IF($A81="","",COUNTIFS(attestations!$B$2:$B$2000,$A81,attestations!$R$2:$R$2000,"Image")) -> 0 | R81: =IF($A81="","",COUNTIFS(attestations!$B$2:$B$2000,$A81,attestations!$R$2:$R$2000,"Textual")) -> 3 | S81: =IF($A81="","",COUNTIFS(attestations!$B$2:$B$2000,$A81,attestations!$D$2:$D$2000,"Geometry (Setting)")) -> 1 | T81: =IF($A81="","",IF($O81>=6,"High",IF($O81>=3,"Medium",IF($O81>=1,"Low","None")))) -> High | U81: =IF($A81="","",IF(COUNTIFS(attestations!$B$2:$B$2000,$A81,attestations!$I$2:$I$2000,"Georeferenced map GCP")>0,"Y","N")) -> Y | V81: Candidate | W81: Low | X81: US Army post at Pacific entrance causeway (earlier Fort Grant complex). Handed to Panama 1999; now Amador Causeway leisure area. Added 2026-09-07. | Y81: Town | AA81: US Army post at the canal's Pacific entrance. Transferred to Panama in 1999; now the Amador Causeway leisure area.
A82: CZ-071 | B82: Albrook Field | D82: Military base | E82: Persists | F82: Other | G82: U.S. administration | H82: Mixed | I82: c.1928 | K82: Approximate | L82: Medium | M82: =IF($A82="","",IF($L82="High","Solid point",IF($L82="Medium","Point + buffer",IF($L82="Low","Translucent area",IF($L82="Disputed","Candidate points",IF($L82="Unknown","Unplotted (unlocated panel)","-")))))) -> Point + buffer | N82: 250 | O82: =IF($A82="","",COUNTIF(attestations!$B$2:$B$2000,$A82)) -> 9 | P82: =IF($A82="","",COUNTIFS(attestations!$B$2:$B$2000,$A82,attestations!$R$2:$R$2000,"Map")) -> 0 | Q82: =IF($A82="","",COUNTIFS(attestations!$B$2:$B$2000,$A82,attestations!$R$2:$R$2000,"Image")) -> 0 | R82: =IF($A82="","",COUNTIFS(attestations!$B$2:$B$2000,$A82,attestations!$R$2:$R$2000,"Textual")) -> 2 | S82: =IF($A82="","",COUNTIFS(attestations!$B$2:$B$2000,$A82,attestations!$D$2:$D$2000,"Geometry (Setting)")) -> 2 | T82: =IF($A82="","",IF($O82>=6,"High",IF($O82>=3,"Medium",IF($O82>=1,"Low","None")))) -> High | U82: =IF($A82="","",IF(COUNTIFS(attestations!$B$2:$B$2000,$A82,attestations!$I$2:$I$2000,"Georeferenced map GCP")>0,"Y","N")) -> Y | V82: Candidate | W82: Low | X82: US Army Air Corps field beside Balboa (Gov. Ann. Rep. 1935, IA). Handed to Panama 1999; now Marcos A. Gelabert airport. Added 2026-09-07. | lifespan extended to dated evidence 2026-09-13 [was: c.1932] | Y82: Town | AA82: US Army Air Corps airfield beside Balboa. Transferred to Panama in 1999; now Marcos A. Gelabert Airport.
A83: CZ-072 | B83: Quarry Heights | D83: Military base | E83: Persists | F83: Other | G83: U.S. administration | H83: Mixed | I83: c.1909? | K83: Approximate | L83: Unknown | M83: =IF($A83="","",IF($L83="High","Solid point",IF($L83="Medium","Point + buffer",IF($L83="Low","Translucent area",IF($L83="Disputed","Candidate points",IF($L83="Unknown","Unplotted (unlocated panel)","-")))))) -> Unplotted (unlocated panel) | O83: =IF($A83="","",COUNTIF(attestations!$B$2:$B$2000,$A83)) -> 11 | P83: =IF($A83="","",COUNTIFS(attestations!$B$2:$B$2000,$A83,attestations!$R$2:$R$2000,"Map")) -> 0 | Q83: =IF($A83="","",COUNTIFS(attestations!$B$2:$B$2000,$A83,attestations!$R$2:$R$2000,"Image")) -> 0 | R83: =IF($A83="","",COUNTIFS(attestations!$B$2:$B$2000,$A83,attestations!$R$2:$R$2000,"Textual")) -> 1 | S83: =IF($A83="","",COUNTIFS(attestations!$B$2:$B$2000,$A83,attestations!$D$2:$D$2000,"Geometry (Setting)")) -> 1 | T83: =IF($A83="","",IF($O83>=6,"High",IF($O83>=3,"Medium",IF($O83>=1,"Low","None")))) -> High | U83: =IF($A83="","",IF(COUNTIFS(attestations!$B$2:$B$2000,$A83,attestations!$I$2:$I$2000,"Georeferenced map GCP")>0,"Y","N")) -> N | V83: Candidate | W83: Low | X83: US military HQ on Ancon Hill slopes (Department/SOUTHCOM command). Handed to Panama 1999. Added 2026-09-07. | lifespan extended 2026-09-14 Butcher v00025: the quarry shipping La Boca fill 1909-12; the c.1916 date is the Army post on the same heights [start was: c.1916] | Y83: Town | AA83: US military headquarters on the slopes of Ancón Hill, on the site of an earlier quarry. Transferred to Panama in 1999.
A84: CZ-073 | B84: Barro Colorado Island | C84: Barro Colorado | D84: Landscape feature | E84: Persists | F84: Flooding (Gatun Lake) | G84: Displacement | I84: c.1914 | K84: Approximate | L84: Medium | M84: =IF($A84="","",IF($L84="High","Solid point",IF($L84="Medium","Point + buffer",IF($L84="Low","Translucent area",IF($L84="Disputed","Candidate points",IF($L84="Unknown","Unplotted (unlocated panel)","-")))))) -> Point + buffer | N84: 150 | O84: =IF($A84="","",COUNTIF(attestations!$B$2:$B$2000,$A84)) -> 7 | P84: =IF($A84="","",COUNTIFS(attestations!$B$2:$B$2000,$A84,attestations!$R$2:$R$2000,"Map")) -> 0 | Q84: =IF($A84="","",COUNTIFS(attestations!$B$2:$B$2000,$A84,attestations!$R$2:$R$2000,"Image")) -> 0 | R84: =IF($A84="","",COUNTIFS(attestations!$B$2:$B$2000,$A84,attestations!$R$2:$R$2000,"Textual")) -> 2 | S84: =IF($A84="","",COUNTIFS(attestations!$B$2:$B$2000,$A84,attestations!$D$2:$D$2000,"Geometry (Setting)")) -> 1 | T84: =IF($A84="","",IF($O84>=6,"High",IF($O84>=3,"Medium",IF($O84>=1,"Low","None")))) -> High | U84: =IF($A84="","",IF(COUNTIFS(attestations!$B$2:$B$2000,$A84,attestations!$I$2:$I$2000,"Georeferenced map GCP")>0,"Y","N")) -> Y | V84: Candidate | W84: Low | X84: Hilltop turned island by the Gatun Lake flooding (1913-14); biological reserve 1923, STRI station. Flood-created feature, not an erased town; included 2026-09-07. pop_type blank: uninhabited research reserve. | 2026-09-14: the 1857 'Barro Colorado Abajo' village read moved to CZ-183; this id keeps the island (c.1914-). Name ancestry runs village -> hill -> island (R-18). | Y84: Site/Institution | AA84: A hilltop that became an island when Gatún Lake was flooded in 1913–14; a biological reserve since 1923. The 1857 village of Barro Colorado Abajo is recorded as a separate place.
A85: CZ-074 | B85: Isla Vista | C85: El Pueblo Isla Vista | D85: Village | E85: Submerged | F85: Gatun Lake flooding | G85: Displacement | H85: Panamanian village | I85: pre-1862 | J85: before 1905? | K85: Inferred | L85: Low | M85: =IF($A85="","",IF($L85="High","Solid point",IF($L85="Medium","Point + buffer",IF($L85="Low","Translucent area",IF($L85="Disputed","Candidate points",IF($L85="Unknown","Unplotted (unlocated panel)","-")))))) -> Translucent area | N85: 800 | O85: =IF($A85="","",COUNTIF(attestations!$B$2:$B$2000,$A85)) -> 0 | P85: =IF($A85="","",COUNTIFS(attestations!$B$2:$B$2000,$A85,attestations!$R$2:$R$2000,"Map")) -> 0 | Q85: =IF($A85="","",COUNTIFS(attestations!$B$2:$B$2000,$A85,attestations!$R$2:$R$2000,"Image")) -> 0 | R85: =IF($A85="","",COUNTIFS(attestations!$B$2:$B$2000,$A85,attestations!$R$2:$R$2000,"Textual")) -> 0 | S85: =IF($A85="","",COUNTIFS(attestations!$B$2:$B$2000,$A85,attestations!$D$2:$D$2000,"Geometry (Setting)")) -> 0 | T85: =IF($A85="","",IF($O85>=6,"High",IF($O85>=3,"Medium",IF($O85>=1,"Low","None")))) -> None | U85: =IF($A85="","",IF(COUNTIFS(attestations!$B$2:$B$2000,$A85,attestations!$I$2:$I$2000,"Georeferenced map GCP")>0,"Y","N")) -> N | V85: Duplicate | X85: Pueblo on the Chagres below Bohio, drawn on the 1862 PRR land-claims plano; absent from every later map consulted. | MERGED into CZ-031 2026-09-13: probable reading artifact - the 1862 'El Pueblo de [..]ista Vista' label; appears on no later map; 0 Canal Record pages. Row kept for id stability - do not use. | Y85: Town
A86: CZ-075 | B86: Haut Obispo | C86: Haut Obispo; Alto Obispo | D86: Hamlet | E86: Depopulated-not flooded | F86: 1912 depopulation order | G86: Displacement | H86: Panamanian village | I86: pre-1857 | J86: c.1912-1914 | K86: Inferred | L86: Medium | M86: =IF($A86="","",IF($L86="High","Solid point",IF($L86="Medium","Point + buffer",IF($L86="Low","Translucent area",IF($L86="Disputed","Candidate points",IF($L86="Unknown","Unplotted (unlocated panel)","-")))))) -> Point + buffer | N86: 250 | O86: =IF($A86="","",COUNTIF(attestations!$B$2:$B$2000,$A86)) -> 16 | P86: =IF($A86="","",COUNTIFS(attestations!$B$2:$B$2000,$A86,attestations!$R$2:$R$2000,"Map")) -> 0 | Q86: =IF($A86="","",COUNTIFS(attestations!$B$2:$B$2000,$A86,attestations!$R$2:$R$2000,"Image")) -> 0 | R86: =IF($A86="","",COUNTIFS(attestations!$B$2:$B$2000,$A86,attestations!$R$2:$R$2000,"Textual")) -> 0 | S86: =IF($A86="","",COUNTIFS(attestations!$B$2:$B$2000,$A86,attestations!$D$2:$D$2000,"Geometry (Setting)")) -> 4 | T86: =IF($A86="","",IF($O86>=6,"High",IF($O86>=3,"Medium",IF($O86>=1,"Low","None")))) -> High | U86: =IF($A86="","",IF(COUNTIFS(attestations!$B$2:$B$2000,$A86,attestations!$I$2:$I$2000,"Georeferenced map GCP")>0,"Y","N")) -> Y | V86: Candidate | X86: Hamlet NE of Bas Obispo; 1895 French sheet and 1907 Culebra Division encampment plans. | lifespan extended to dated evidence 2026-09-13 [was: pre-1895; 1883 ChronAm read] | Y86: Town
A87: CZ-076 | B87: Alto Emperador | D87: Hamlet | E87: Depopulated-not flooded | F87: Other | G87: Displacement | H87: Panamanian village | I87: pre-1895 | J87: c.1912? | K87: Inferred | L87: Low | M87: =IF($A87="","",IF($L87="High","Solid point",IF($L87="Medium","Point + buffer",IF($L87="Low","Translucent area",IF($L87="Disputed","Candidate points",IF($L87="Unknown","Unplotted (unlocated panel)","-")))))) -> Translucent area | N87: 400 | O87: =IF($A87="","",COUNTIF(attestations!$B$2:$B$2000,$A87)) -> 10 | P87: =IF($A87="","",COUNTIFS(attestations!$B$2:$B$2000,$A87,attestations!$R$2:$R$2000,"Map")) -> 0 | Q87: =IF($A87="","",COUNTIFS(attestations!$B$2:$B$2000,$A87,attestations!$R$2:$R$2000,"Image")) -> 0 | R87: =IF($A87="","",COUNTIFS(attestations!$B$2:$B$2000,$A87,attestations!$R$2:$R$2000,"Textual")) -> 0 | S87: =IF($A87="","",COUNTIFS(attestations!$B$2:$B$2000,$A87,attestations!$D$2:$D$2000,"Geometry (Setting)")) -> 1 | T87: =IF($A87="","",IF($O87>=6,"High",IF($O87>=3,"Medium",IF($O87>=1,"Low","None")))) -> High | U87: =IF($A87="","",IF(COUNTIFS(attestations!$B$2:$B$2000,$A87,attestations!$I$2:$I$2000,"Georeferenced map GCP")>0,"Y","N")) -> Y | V87: Candidate | X87: District SE of Emperador on the 1895 French sheet. | Y87: Neighborhood | Z87: CZ-011
A88: CZ-077 | B88: Corosita | C88: Camp Corosita | D88: Construction camp | E88: Depopulated-not flooded | F88: Other | G88: Labor | H88: Mixed | I88: c.1905 | J88: c.1913 | K88: Inferred | L88: Medium | M88: =IF($A88="","",IF($L88="High","Solid point",IF($L88="Medium","Point + buffer",IF($L88="Low","Translucent area",IF($L88="Disputed","Candidate points",IF($L88="Unknown","Unplotted (unlocated panel)","-")))))) -> Point + buffer | N88: 200 | O88: =IF($A88="","",COUNTIF(attestations!$B$2:$B$2000,$A88)) -> 11 | P88: =IF($A88="","",COUNTIFS(attestations!$B$2:$B$2000,$A88,attestations!$R$2:$R$2000,"Map")) -> 0 | Q88: =IF($A88="","",COUNTIFS(attestations!$B$2:$B$2000,$A88,attestations!$R$2:$R$2000,"Image")) -> 0 | R88: =IF($A88="","",COUNTIFS(attestations!$B$2:$B$2000,$A88,attestations!$R$2:$R$2000,"Textual")) -> 0 | S88: =IF($A88="","",COUNTIFS(attestations!$B$2:$B$2000,$A88,attestations!$D$2:$D$2000,"Geometry (Setting)")) -> 1 | T88: =IF($A88="","",IF($O88>=6,"High",IF($O88>=3,"Medium",IF($O88>=1,"Low","None")))) -> High | U88: =IF($A88="","",IF(COUNTIFS(attestations!$B$2:$B$2000,$A88,attestations!$I$2:$I$2000,"Georeferenced map GCP")>0,"Y","N")) -> Y | V88: Candidate | X88: ICC construction camp near the Obispo River; sheet 2 of the 1907 Culebra Division encampment plans. | Y88: Town
A89: CZ-078 | B89: Cunette | C89: Cunette camp | D89: Construction camp | E89: Depopulated-not flooded | F89: Other | G89: Labor | H89: Mixed | I89: c.1905 | J89: c.1913 | K89: Inferred | L89: Low | M89: =IF($A89="","",IF($L89="High","Solid point",IF($L89="Medium","Point + buffer",IF($L89="Low","Translucent area",IF($L89="Disputed","Candidate points",IF($L89="Unknown","Unplotted (unlocated panel)","-")))))) -> Translucent area | N89: 400 | O89: =IF($A89="","",COUNTIF(attestations!$B$2:$B$2000,$A89)) -> 15 | P89: =IF($A89="","",COUNTIFS(attestations!$B$2:$B$2000,$A89,attestations!$R$2:$R$2000,"Map")) -> 0 | Q89: =IF($A89="","",COUNTIFS(attestations!$B$2:$B$2000,$A89,attestations!$R$2:$R$2000,"Image")) -> 0 | R89: =IF($A89="","",COUNTIFS(attestations!$B$2:$B$2000,$A89,attestations!$R$2:$R$2000,"Textual")) -> 0 | S89: =IF($A89="","",COUNTIFS(attestations!$B$2:$B$2000,$A89,attestations!$D$2:$D$2000,"Geometry (Setting)")) -> 6 | T89: =IF($A89="","",IF($O89>=6,"High",IF($O89>=3,"Medium",IF($O89>=1,"Low","None")))) -> High | U89: =IF($A89="","",IF(COUNTIFS(attestations!$B$2:$B$2000,$A89,attestations!$I$2:$I$2000,"Georeferenced map GCP")>0,"Y","N")) -> Y | V89: Candidate | X89: ICC camp for cunette excavation crews; sheets 7-8 (N+S ends) of the 1907 encampment plans. Position VERIFIED 2026-09-08: south-end sheet (O-line, Sta 1580) is continuous with the north sheet's Sta 1550 - one camp band Sta 1544-1590 between Buena Vista and Las Cascadas. | RULING 2026-09-13: position conflict (blueprint camp band vs 1909+1911 site ~3 km N of Empire) stays UNRESOLVED by design - all claims plotted as candidates; the zone-map site may be a distinct 'Cunette' settlement (the term is also the Cut's drainage trench). | Y89: Town
A90: CZ-079 | B90: Cerro | C90: Cerro camp | D90: Construction camp | E90: Depopulated-not flooded | F90: Other | G90: Labor | H90: Mixed | I90: c.1905 | J90: c.1916 | K90: Inferred | L90: Medium | M90: =IF($A90="","",IF($L90="High","Solid point",IF($L90="Medium","Point + buffer",IF($L90="Low","Translucent area",IF($L90="Disputed","Candidate points",IF($L90="Unknown","Unplotted (unlocated panel)","-")))))) -> Point + buffer | N90: 200 | O90: =IF($A90="","",COUNTIF(attestations!$B$2:$B$2000,$A90)) -> 9 | P90: =IF($A90="","",COUNTIFS(attestations!$B$2:$B$2000,$A90,attestations!$R$2:$R$2000,"Map")) -> 0 | Q90: =IF($A90="","",COUNTIFS(attestations!$B$2:$B$2000,$A90,attestations!$R$2:$R$2000,"Image")) -> 0 | R90: =IF($A90="","",COUNTIFS(attestations!$B$2:$B$2000,$A90,attestations!$R$2:$R$2000,"Textual")) -> 0 | S90: =IF($A90="","",COUNTIFS(attestations!$B$2:$B$2000,$A90,attestations!$D$2:$D$2000,"Geometry (Setting)")) -> 2 | T90: =IF($A90="","",IF($O90>=6,"High",IF($O90>=3,"Medium",IF($O90>=1,"Low","None")))) -> High | U90: =IF($A90="","",IF(COUNTIFS(attestations!$B$2:$B$2000,$A90,attestations!$I$2:$I$2000,"Georeferenced map GCP")>0,"Y","N")) -> Y | V90: Candidate | X90: Camp on the hill E of Empire; sheet 9 of the 1907 encampment plans. | lifespan extended to dated evidence 2026-09-13 [was: c.1913] | Y90: Town
A91: CZ-080 | B91: Lirio | C91: Lirio camp | D91: Construction camp | E91: Depopulated-not flooded | F91: Other | G91: Labor | H91: Mixed | I91: c.1905 | J91: c.1916 | K91: Inferred | L91: Medium | M91: =IF($A91="","",IF($L91="High","Solid point",IF($L91="Medium","Point + buffer",IF($L91="Low","Translucent area",IF($L91="Disputed","Candidate points",IF($L91="Unknown","Unplotted (unlocated panel)","-")))))) -> Point + buffer | N91: 200 | O91: =IF($A91="","",COUNTIF(attestations!$B$2:$B$2000,$A91)) -> 8 | P91: =IF($A91="","",COUNTIFS(attestations!$B$2:$B$2000,$A91,attestations!$R$2:$R$2000,"Map")) -> 0 | Q91: =IF($A91="","",COUNTIFS(attestations!$B$2:$B$2000,$A91,attestations!$R$2:$R$2000,"Image")) -> 0 | R91: =IF($A91="","",COUNTIFS(attestations!$B$2:$B$2000,$A91,attestations!$R$2:$R$2000,"Textual")) -> 0 | S91: =IF($A91="","",COUNTIFS(attestations!$B$2:$B$2000,$A91,attestations!$D$2:$D$2000,"Geometry (Setting)")) -> 4 | T91: =IF($A91="","",IF($O91>=6,"High",IF($O91>=3,"Medium",IF($O91>=1,"Low","None")))) -> High | U91: =IF($A91="","",IF(COUNTIFS(attestations!$B$2:$B$2000,$A91,attestations!$I$2:$I$2000,"Georeferenced map GCP")>0,"Y","N")) -> Y | V91: Candidate | X91: Camp between Empire and Culebra; sheet 11 of the 1907 encampment plans; Lirio labels also on ICC1911. | RULING 2026-09-13: the three-way position scatter (1905-06 / 1909 / hill names) stays as candidate points - no winner chosen. | End extended c.1913 -> c.1916 2026-09-14: Canal Record census rows carry Lirio Camp (309 persons in 1913-14) through Vol IX 1915-16 (A-1388, variant-name probe). | Y91: Town
A92: CZ-081 | B92: Caballo Viejo | D92: Village | E92: Submerged | F92: Gatun Lake flooding | G92: Displacement | H92: Panamanian village | I92: pre-1895 | J92: 1911-1914 | K92: Inferred | L92: Medium | M92: =IF($A92="","",IF($L92="High","Solid point",IF($L92="Medium","Point + buffer",IF($L92="Low","Translucent area",IF($L92="Disputed","Candidate points",IF($L92="Unknown","Unplotted (unlocated panel)","-")))))) -> Point + buffer | N92: 250 | O92: =IF($A92="","",COUNTIF(attestations!$B$2:$B$2000,$A92)) -> 14 | P92: =IF($A92="","",COUNTIFS(attestations!$B$2:$B$2000,$A92,attestations!$R$2:$R$2000,"Map")) -> 0 | Q92: =IF($A92="","",COUNTIFS(attestations!$B$2:$B$2000,$A92,attestations!$R$2:$R$2000,"Image")) -> 0 | R92: =IF($A92="","",COUNTIFS(attestations!$B$2:$B$2000,$A92,attestations!$R$2:$R$2000,"Textual")) -> 0 | S92: =IF($A92="","",COUNTIFS(attestations!$B$2:$B$2000,$A92,attestations!$D$2:$D$2000,"Geometry (Setting)")) -> 4 | T92: =IF($A92="","",IF($O92>=6,"High",IF($O92>=3,"Medium",IF($O92>=1,"Low","None")))) -> High | U92: =IF($A92="","",IF(COUNTIFS(attestations!$B$2:$B$2000,$A92,attestations!$I$2:$I$2000,"Georeferenced map GCP")>0,"Y","N")) -> Y | V92: Candidate | X92: Old-line village by Juan Grande; 1905-06 ICC survey and ICC1911. | lifespan extended to dated evidence 2026-09-13 [was: pre-1905] | Y92: Town
A93: CZ-082 | B93: Chagresito | D93: Hamlet | E93: Submerged | F93: Gatun Lake flooding | G93: Displacement | H93: Panamanian village | I93: pre-1904 | J93: 1911-1914 | K93: Inferred | L93: Low | M93: =IF($A93="","",IF($L93="High","Solid point",IF($L93="Medium","Point + buffer",IF($L93="Low","Translucent area",IF($L93="Disputed","Candidate points",IF($L93="Unknown","Unplotted (unlocated panel)","-")))))) -> Translucent area | N93: 400 | O93: =IF($A93="","",COUNTIF(attestations!$B$2:$B$2000,$A93)) -> 8 | P93: =IF($A93="","",COUNTIFS(attestations!$B$2:$B$2000,$A93,attestations!$R$2:$R$2000,"Map")) -> 0 | Q93: =IF($A93="","",COUNTIFS(attestations!$B$2:$B$2000,$A93,attestations!$R$2:$R$2000,"Image")) -> 0 | R93: =IF($A93="","",COUNTIFS(attestations!$B$2:$B$2000,$A93,attestations!$R$2:$R$2000,"Textual")) -> 0 | S93: =IF($A93="","",COUNTIFS(attestations!$B$2:$B$2000,$A93,attestations!$D$2:$D$2000,"Geometry (Setting)")) -> 2 | T93: =IF($A93="","",IF($O93>=6,"High",IF($O93>=3,"Medium",IF($O93>=1,"Low","None")))) -> High | U93: =IF($A93="","",IF(COUNTIFS(attestations!$B$2:$B$2000,$A93,attestations!$I$2:$I$2000,"Georeferenced map GCP")>0,"Y","N")) -> Y | V93: Candidate | X93: Chagres hamlet below Frijoles; ICC1909 and ICC1911. | lifespan extended 2026-09-15 (retro audit National Archives leg): 'Chagrecito' lettered with house dots on the c.1904 occupation map (S-053) [was: pre-1908] | Y93: Town
A94: CZ-083 | B94: Mulato | D94: Hamlet | E94: Submerged | F94: Gatun Lake flooding | G94: Displacement | H94: Panamanian village | I94: pre-1857? | J94: 1911-1914 | K94: Inferred | L94: Low | M94: =IF($A94="","",IF($L94="High","Solid point",IF($L94="Medium","Point + buffer",IF($L94="Low","Translucent area",IF($L94="Disputed","Candidate points",IF($L94="Unknown","Unplotted (unlocated panel)","-")))))) -> Translucent area | N94: 400 | O94: =IF($A94="","",COUNTIF(attestations!$B$2:$B$2000,$A94)) -> 12 | P94: =IF($A94="","",COUNTIFS(attestations!$B$2:$B$2000,$A94,attestations!$R$2:$R$2000,"Map")) -> 0 | Q94: =IF($A94="","",COUNTIFS(attestations!$B$2:$B$2000,$A94,attestations!$R$2:$R$2000,"Image")) -> 0 | R94: =IF($A94="","",COUNTIFS(attestations!$B$2:$B$2000,$A94,attestations!$R$2:$R$2000,"Textual")) -> 0 | S94: =IF($A94="","",COUNTIFS(attestations!$B$2:$B$2000,$A94,attestations!$D$2:$D$2000,"Geometry (Setting)")) -> 2 | T94: =IF($A94="","",IF($O94>=6,"High",IF($O94>=3,"Medium",IF($O94>=1,"Low","None")))) -> High | U94: =IF($A94="","",IF(COUNTIFS(attestations!$B$2:$B$2000,$A94,attestations!$I$2:$I$2000,"Georeferenced map GCP")>0,"Y","N")) -> Y | V94: Candidate | X94: Chagres hamlet near Caimito; 1862 plano and ICC1911. | lifespan extended to dated evidence 2026-09-14 (A-1488: 1857 riverside lettering, reading confidence LOW - '?' kept) [was: pre-1862] | Y94: Town
A95: CZ-084 | B95: Las Penitas | C95: Las Penitas | D95: Hamlet | E95: Submerged | F95: Gatun Lake flooding | G95: Displacement | H95: Panamanian village | I95: pre-1886 | J95: 1911-1914 | K95: Inferred | L95: Low | M95: =IF($A95="","",IF($L95="High","Solid point",IF($L95="Medium","Point + buffer",IF($L95="Low","Translucent area",IF($L95="Disputed","Candidate points",IF($L95="Unknown","Unplotted (unlocated panel)","-")))))) -> Translucent area | N95: 400 | O95: =IF($A95="","",COUNTIF(attestations!$B$2:$B$2000,$A95)) -> 10 | P95: =IF($A95="","",COUNTIFS(attestations!$B$2:$B$2000,$A95,attestations!$R$2:$R$2000,"Map")) -> 0 | Q95: =IF($A95="","",COUNTIFS(attestations!$B$2:$B$2000,$A95,attestations!$R$2:$R$2000,"Image")) -> 0 | R95: =IF($A95="","",COUNTIFS(attestations!$B$2:$B$2000,$A95,attestations!$R$2:$R$2000,"Textual")) -> 0 | S95: =IF($A95="","",COUNTIFS(attestations!$B$2:$B$2000,$A95,attestations!$D$2:$D$2000,"Geometry (Setting)")) -> 2 | T95: =IF($A95="","",IF($O95>=6,"High",IF($O95>=3,"Medium",IF($O95>=1,"Low","None")))) -> High | U95: =IF($A95="","",IF(COUNTIFS(attestations!$B$2:$B$2000,$A95,attestations!$I$2:$I$2000,"Georeferenced map GCP")>0,"Y","N")) -> Y | V95: Candidate | X95: Chagres-bank hamlet between Ahorca Lagarto and Bohio; ICC1909. | 2026-09-14: start pre-1904 -> pre-1886 (2026-09-14): 'Las Penitas' with building marks on the 1886 Plan General. | Y95: Town
A96: CZ-085 | B96: Palo Matias Viejo | C96: Palo Matias | D96: Hamlet | E96: Submerged | F96: Gatun Lake flooding | G96: Displacement | H96: Panamanian village | I96: pre-1857 | J96: 1911-1914 | K96: Inferred | L96: Low | M96: =IF($A96="","",IF($L96="High","Solid point",IF($L96="Medium","Point + buffer",IF($L96="Low","Translucent area",IF($L96="Disputed","Candidate points",IF($L96="Unknown","Unplotted (unlocated panel)","-")))))) -> Translucent area | N96: 400 | O96: =IF($A96="","",COUNTIF(attestations!$B$2:$B$2000,$A96)) -> 12 | P96: =IF($A96="","",COUNTIFS(attestations!$B$2:$B$2000,$A96,attestations!$R$2:$R$2000,"Map")) -> 0 | Q96: =IF($A96="","",COUNTIFS(attestations!$B$2:$B$2000,$A96,attestations!$R$2:$R$2000,"Image")) -> 0 | R96: =IF($A96="","",COUNTIFS(attestations!$B$2:$B$2000,$A96,attestations!$R$2:$R$2000,"Textual")) -> 0 | S96: =IF($A96="","",COUNTIFS(attestations!$B$2:$B$2000,$A96,attestations!$D$2:$D$2000,"Geometry (Setting)")) -> 4 | T96: =IF($A96="","",IF($O96>=6,"High",IF($O96>=3,"Medium",IF($O96>=1,"Low","None")))) -> High | U96: =IF($A96="","",IF(COUNTIFS(attestations!$B$2:$B$2000,$A96,attestations!$I$2:$I$2000,"Georeferenced map GCP")>0,"Y","N")) -> Y | V96: Candidate | X96: Chagres-bank hamlet; ICC1909; Palo Matias tract on the 1862 plano. | Y96: Town
A97: CZ-086 | B97: Whitehouse | C97: White House | D97: Construction camp | E97: Depopulated-not flooded | F97: Other | G97: Labor | H97: Mixed | I97: c.1906 | J97: c.1913 | K97: Inferred | L97: Medium | M97: =IF($A97="","",IF($L97="High","Solid point",IF($L97="Medium","Point + buffer",IF($L97="Low","Translucent area",IF($L97="Disputed","Candidate points",IF($L97="Unknown","Unplotted (unlocated panel)","-")))))) -> Point + buffer | N97: 200 | O97: =IF($A97="","",COUNTIF(attestations!$B$2:$B$2000,$A97)) -> 2 | P97: =IF($A97="","",COUNTIFS(attestations!$B$2:$B$2000,$A97,attestations!$R$2:$R$2000,"Map")) -> 0 | Q97: =IF($A97="","",COUNTIFS(attestations!$B$2:$B$2000,$A97,attestations!$R$2:$R$2000,"Image")) -> 0 | R97: =IF($A97="","",COUNTIFS(attestations!$B$2:$B$2000,$A97,attestations!$R$2:$R$2000,"Textual")) -> 0 | S97: =IF($A97="","",COUNTIFS(attestations!$B$2:$B$2000,$A97,attestations!$D$2:$D$2000,"Geometry (Setting)")) -> 0 | T97: =IF($A97="","",IF($O97>=6,"High",IF($O97>=3,"Medium",IF($O97>=1,"Low","None")))) -> Low | U97: =IF($A97="","",IF(COUNTIFS(attestations!$B$2:$B$2000,$A97,attestations!$I$2:$I$2000,"Georeferenced map GCP")>0,"Y","N")) -> N | V97: Duplicate | X97: DUPLICATE of CZ-059 Whitehouse (merged 2026-09-09) - row kept only for position stability; do not use | Y97: Town
A98: CZ-087 | B98: Cartagena | C98: Cartagenita | D98: Hamlet | E98: Depopulated-not flooded | F98: Other | G98: Displacement | H98: Panamanian village | I98: pre-1907 | J98: c.1913? | K98: Unknown | L98: Medium | M98: =IF($A98="","",IF($L98="High","Solid point",IF($L98="Medium","Point + buffer",IF($L98="Low","Translucent area",IF($L98="Disputed","Candidate points",IF($L98="Unknown","Unplotted (unlocated panel)","-")))))) -> Point + buffer | N98: 250 | O98: =IF($A98="","",COUNTIF(attestations!$B$2:$B$2000,$A98)) -> 2 | P98: =IF($A98="","",COUNTIFS(attestations!$B$2:$B$2000,$A98,attestations!$R$2:$R$2000,"Map")) -> 0 | Q98: =IF($A98="","",COUNTIFS(attestations!$B$2:$B$2000,$A98,attestations!$R$2:$R$2000,"Image")) -> 0 | R98: =IF($A98="","",COUNTIFS(attestations!$B$2:$B$2000,$A98,attestations!$R$2:$R$2000,"Textual")) -> 0 | S98: =IF($A98="","",COUNTIFS(attestations!$B$2:$B$2000,$A98,attestations!$D$2:$D$2000,"Geometry (Setting)")) -> 0 | T98: =IF($A98="","",IF($O98>=6,"High",IF($O98>=3,"Medium",IF($O98>=1,"Low","None")))) -> Low | U98: =IF($A98="","",IF(COUNTIFS(attestations!$B$2:$B$2000,$A98,attestations!$I$2:$I$2000,"Georeferenced map GCP")>0,"Y","N")) -> N | V98: Duplicate | X98: DUPLICATE of CZ-062 Cartagenita (merged 2026-09-09) - row kept only for position stability; do not use | Y98: Town
A99: CZ-110 | B99: Spanish Town | D99: Labor camp | E99: Depopulated-not flooded | F99: Other | G99: Labor | H99: Mixed | I99: c.1906? | J99: c.1916? | K99: Unknown | L99: Medium | M99: =IF($A99="","",IF($L99="High","Solid point",IF($L99="Medium","Point + buffer",IF($L99="Low","Translucent area",IF($L99="Disputed","Candidate points",IF($L99="Unknown","Unplotted (unlocated panel)","-")))))) -> Point + buffer | N99: 350 | O99: =IF($A99="","",COUNTIF(attestations!$B$2:$B$2000,$A99)) -> 10 | P99: =IF($A99="","",COUNTIFS(attestations!$B$2:$B$2000,$A99,attestations!$R$2:$R$2000,"Map")) -> 0 | Q99: =IF($A99="","",COUNTIFS(attestations!$B$2:$B$2000,$A99,attestations!$R$2:$R$2000,"Image")) -> 0 | R99: =IF($A99="","",COUNTIFS(attestations!$B$2:$B$2000,$A99,attestations!$R$2:$R$2000,"Textual")) -> 0 | S99: =IF($A99="","",COUNTIFS(attestations!$B$2:$B$2000,$A99,attestations!$D$2:$D$2000,"Geometry (Setting)")) -> 1 | T99: =IF($A99="","",IF($O99>=6,"High",IF($O99>=3,"Medium",IF($O99>=1,"Low","None")))) -> High | U99: =IF($A99="","",IF(COUNTIFS(attestations!$B$2:$B$2000,$A99,attestations!$I$2:$I$2000,"Georeferenced map GCP")>0,"Y","N")) -> Y | V99: Candidate | W99: High | X99: Labour settlement NE of Paraiso, labeled with dot cluster on the 1911 property map (the only sheet that names it - absent from zone-scale cartography). Name suggests European/Spanish labourers, unverified. Registered 2026-09-13 from the ICC1911 absence audit; absent from the 1947 sheet. | lifespan extended to dated evidence 2026-09-13 [was: c.1913?] | Y99: Town
A100: CZ-111 | B100: Golden Green | D100: Construction camp | E100: Depopulated-not flooded | F100: Other | G100: Labor | H100: Mixed | I100: c.1907? | J100: after 1917? | K100: Unknown | L100: Medium | M100: =IF($A100="","",IF($L100="High","Solid point",IF($L100="Medium","Point + buffer",IF($L100="Low","Translucent area",IF($L100="Disputed","Candidate points",IF($L100="Unknown","Unplotted (unlocated panel)","-")))))) -> Point + buffer | N100: 350 | O100: =IF($A100="","",COUNTIF(attestations!$B$2:$B$2000,$A100)) -> 11 | P100: =IF($A100="","",COUNTIFS(attestations!$B$2:$B$2000,$A100,attestations!$R$2:$R$2000,"Map")) -> 0 | Q100: =IF($A100="","",COUNTIFS(attestations!$B$2:$B$2000,$A100,attestations!$R$2:$R$2000,"Image")) -> 0 | R100: =IF($A100="","",COUNTIFS(attestations!$B$2:$B$2000,$A100,attestations!$R$2:$R$2000,"Textual")) -> 0 | S100: =IF($A100="","",COUNTIFS(attestations!$B$2:$B$2000,$A100,attestations!$D$2:$D$2000,"Geometry (Setting)")) -> 1 | T100: =IF($A100="","",IF($O100>=6,"High",IF($O100>=3,"Medium",IF($O100>=1,"Low","None")))) -> High | U100: =IF($A100="","",IF(COUNTIFS(attestations!$B$2:$B$2000,$A100,attestations!$I$2:$I$2000,"Georeferenced map GCP")>0,"Y","N")) -> Y | V100: Candidate | W100: High | X100: Camp labeled with dots between Empire Sta. and Lirio on the 1911 property map; not on the 1909 zone map or any later sheet. Population unverified. Registered 2026-09-13 from the ICC1911 absence audit. | lifespan extended to dated evidence 2026-09-13 [was: c.1913?] | Y100: Town
...

Sheet sources
A1: source_id (PK) | B1: medium | C1: title | D1: creator / author | E1: source_date | F1: repository | G1: archive_ref | H1: url | I1: source_origin | J1: reliability | K1: georeferenced | L1: rms_error_m | M1: ext_uri (Wikidata/GeoNames) | N1: notes | O1: archive_id
A2: S-001 | B2: Web compilation | C2: czbrats "Villages Underwater" pages | D2: Canal Zone Brats | E2: n.d. | F2: czbrats.com | G2: - | H2: https://www.czbrats.com/Builders/earlytowns.htm | I2: Mixed | J2: Low | K2: NA | N2: Lead-generator; verify every name. | O2: ARC-06
A3: S-002 | B3: Secondary | C3: Erased: The Untold Story of the Panama Canal | D3: Marixa Lasso | E3: 2019 | F3: Harvard University Press | G3: ISBN 9780674984448 | H3: - | I3: Secondary | J3: High | K3: NA | N3: Depopulation as policy. Maps by T. Stallman. | O3: ARC-20
A4: S-003 | B4: Report | C4: The Canal Record (official weekly) | D4: Isthmian Canal Commission | E4: 1907-1941 | F4: UF Smathers / Internet Archive | G4: - | H4: https://ufdc.ufl.edu/UF00097368 | I4: US official | J4: High | K4: NA | N4: Week-by-week relocations. Full-text searchable at UFDC (bibid UF00097368, 28 digitized volumes 1907-1941); also on Internet Archive. Page-level harvest 2026-09: data/ufdc/. | O4: ARC-03
A5: S-004 | B5: Administrative | C5: Records of the Panama Canal (Record Group 185) | D5: US National Archives | E5: 1904-1979 | F5: NARA, College Park | G5: RG 185 | H5: https://www.archives.gov | I5: US official | J5: High | K5: NA | N5: Maps, ICC records, labor series. | O5: ARC-01
A6: S-005 | B6: Map | C6: Property Map of the Canal Zone | D6: ICC, Dept. of Law | E6: 1911 | F6: Library of Congress G&M | G6: g4872c.pcc00006 | H6: https://www.loc.gov/item/2... | I6: US official | J6: High | K6: Y | L6: 250 | N6: Who was dispossessed. | O6: ARC-02
A7: S-006 | B7: Map | C7: Isthmian Canal Commission Map of the Canal Zone (Annual Report) | D7: Isthmian Canal Commission | E7: 1910 | F7: LOC / NARA | G7: - | H7: - | I7: US official | J7: High | K7: Y | L7: 300 | N7: Towns + topography; georeference. | O7: ARC-02
A8: S-007 | B8: Administrative | C8: Museo del Canal Interoceánico de Panamá — Centro de Documentación y Archivo (including the Archivo de Historia Oral) | D8: Museo del Canal Interoceánico de Panamá | E8: c.1850-present | F8: Museo del Canal, Casco Antiguo, Panama City | G8: Koha OPAC (biblio); reserve + oral archive onsite | H8: typismuci.museodelcanal.com | I8: Panamanian | J8: High | K8: NA | N8: Panamanian-side counter-archive. Documentary Center holds >150 linear m of books, >32,000 archival folios, and an Archivo de Historia Oral (interviews with protagonistas de la historia de Panamá; UNESCO Memory of the World for the postal collection). Swept 2026-09-13 via the Koha OPAC (Spanish: Emperador, Gorgona, poblados, Chagres, + town names). CRITICAL ACCESS NOTE: catalog is metadata-only; ZERO digital objects served (cover images come from Amazon). Reserve cartography/photos/postcards and oral-history transcripts are ONSITE ONLY. Remote use beyond catalog metadata would require an email scan request to the Centro de Documentación or an on-site visit — not yet made. See data/museo/. | O8: ARC-04
A9: S-008 | B9: Administrative | C9: Silver Men: West Indian Labourers archive | D9: UNESCO Memory of the World | E9: 1880-1914 | F9: Multi-repository | G9: - | H9: https://www.unesco.org/en/memory-world | I9: Caribbean community | J9: Medium | K9: NA | N9: Silver Roll labor geography. | O9: ARC-05
A10: S-009 | B10: Newspaper | C10: Chronicling America digitized newspapers (searched in full text) | D10: various U.S. newspapers | E10: 1880-1920 | F10: Library of Congress | G10: - | H10: https://www.loc.gov/collections/chronicling-america/ | I10: US press | J10: Medium | K10: NA | L10: Umbrella source for harvested newspaper mentions (2026-09); per-issue LOC URL in each attestation note. Harvest files: data/chronicling-america/. | O10: ARC-10
A11: S-010 | B11: Newspaper | C11: Post offices in the Canal Zone (list), Evening Star, 16 February 1906, page 2 | D11: Evening Star (Washington, D.C.) | E11: 1906-02-16 | F11: LOC Chronicling America | G11: sn83045462 | H11: https://www.loc.gov/resource/sn83045462/1906-02-16/ed-1/?sp=2 | I11: US press | J11: High | K11: NA | L11: Official list of CZ post offices in operation 5 Feb 1906. | O11: ARC-10
A12: S-011 | B12: Newspaper | C12: Commissary-closure chronology, Der Sonntagsbote und der Seebote, 18 May 1913, page 1 | D12: Der Sonntagsbote und der Seebote (Milwaukee) | E12: 1913-05-18 | F12: LOC Chronicling America | G12: sn87082456 | H12: https://www.loc.gov/resource/sn87082456/1913-05-18/ed-1/?sp=1 | I12: US press | J12: Medium | K12: NA | L12: German-language. Dates the closure of ten commissary settlements 1911-1913. | O12: ARC-10
A13: S-012 | B13: Newspaper | C13: Canal Record 'vanishing villages' syndication (December 1911 - April 1912) | D13: The Canal Record via U.S. wire services | E13: 1911-1912 | F13: LOC Chronicling America | G13: sn92070417 et al. | H13: https://www.loc.gov/resource/sn92070417/1912-01-10/ed-1/?sp=2 | I13: US official | J13: High | K13: NA | L13: Names all Gatun Lake drowned villages; >=10 printings found. Richest: Las Vegas Optic 1912-01-10 p.2 (includes etymologies). | O13: ARC-10
A14: S-013 | B14: Newspaper | C14: St. Croix Avis French-era canal reports (1882-1887) | D14: St. Croix Avis (Christiansted) | E14: 1882-1887 | F14: LOC Chronicling America | G14: sn84037526 | H14: https://www.loc.gov/resource/sn84037526/1887-06-18/ed-1/?sp=4 | I14: Caribbean community | J14: Medium | K14: NA | L14: Brigade list 1882-06-10 p.2; per-site excavation table 1887-06-18 p.4. | O14: ARC-10
A15: S-014 | B15: Photograph | C15: Record Group 185 digitized photographs (United States National Archives catalog) | D15: Isthmian Canal Commission / The Panama Canal | E15: 1887-1960 | F15: NARA, College Park (Still Pictures) | G15: RG 185 (185-G, 185-CZ et al.) | H15: https://catalog.archives.gov/search?q=panama%20canal&recordGroupNumber=185 | I15: US official | J15: High | K15: NA | L15: Digitized items in catalog.archives.gov; series 185-G 'Photographs of the Construction of the Panama Canal 1887-1940' partially digitized. Harvest 2026-09: data/nara/. | O15: ARC-01
A16: S-015 | B16: Map | C16: Preliminary Inventory of the Cartographic Records of The Panama Canal (Preliminary Inventory 91, 1956) | D16: James Berton Rhoads / National Archives | E16: 1956 | F16: NARA, College Park (Cartographic) | G16: RG 185, ~9,240 items / 125 cu. ft. | H16: https://www.archives.gov/files/research/cartographic/pi-91-panama-canal.pdf | I16: US official | J16: High | K16: NA | L16: Finding aid, read cover-to-cover 2026-09. Appendix II is a place-name index; attestations cite its file designations. The maps themselves are PAPER, onsite-only - not full-text searchable. | O16: ARC-01
A17: S-016 | B17: Administrative | C17: Smithsonian Open Access collections | D17: Smithsonian Institution (NMNH, NPM, SIL et al.) | E17: 1850-1940s | F17: Smithsonian Institution | G17: EDAN edanmdm records | H17: https://collections.si.edu/search/ | I17: US official | J17: High | K17: NA | L17: 20,798 town-name matches in 45,040 records (2026-09 harvest, data/smithsonian/). Mostly NMNH specimens whose collecting locality is a Zone town - type-locality attestations. Dates in notes are year_guess only (may be taxon-description year); verify per record before citing as attested time. | O17: ARC-08
A18: S-017 | B18: Photograph | C18: W. A. Fishbaugh Panama Canal Photograph Album | D18: W. A. Fishbaugh (Empire, C.Z.); assembled by A. Bruce Minear | E18: 1905-1908 | F18: Archives Center, NMAH (NMAH.AC.1021) | G18: 27 of 100 views digitized | H18: https://sova.si.edu/record/nmah.ac.1021 | I18: US press | J18: High | K18: NA | L18: Commercial construction-era views, captions printed in the negative; all 27 digitized views read 2026-09. Fishbaugh's studio imprint 'Empire C.Z.' on every print. | O18: ARC-08
A19: S-018 | B19: Map | C19: The Panama Canal, plate from Shepherd's Historical Atlas (1911) | D19: William R. Shepherd | E19: 1911 | F19: PCL Map Collection, UT Austin | G19: shepherd-c-216 / panama_canal_shepherd.jpg | H19: https://maps.lib.utexas.edu/maps/historical/shepherd/panama_canal_shepherd.jpg | I19: Secondary | J19: Medium | K19: N | L19: 1:400,000 map + canal profile placing each line settlement at its statute mile. Tertiary source but the full village sequence on one sheet; read 2026-09, saved to ~/Desktop/PCL Canal Zone Maps. | O19: ARC-13
A20: S-019 | B20: Newspaper | C20: Eastern Reflector (Greenville, North Carolina) | E20: 1879-1919 | F20: ECU Digital Collections (Joyner Library) | G20: digital.lib.ecu.edu | H20: https://digital.lib.ecu.edu/ | I20: US press | J20: Medium | N20: Greenville NC weekly; full-text OCR embedded in ECU item pages. Carries window-era canal coverage incl. Old Gatun removal (1 May 1908). Harvest: data/ecu/ (2026-09-07). | O20: ARC-12
A21: S-020 | B21: Web compilation | C21: East Carolina University Digital Collections: Canal Zone material (Daily Reflector, oral histories, yearbooks) | E21: 1920-1990 | F21: ECU Digital Collections (Joyner Library) | G21: digital.lib.ecu.edu | H21: https://digital.lib.ecu.edu/ | I21: US press | J21: Medium | N21: Umbrella source for post-window ECU material: Daily Reflector, Navy/veteran oral histories, university records. 1,026 items scanned; 196 canal-context mentions. Harvest: data/ecu/. | O21: ARC-12
A22: S-021 | B22: Web compilation | C22: Internet Archive canal-era texts (1,315 digitized volumes) | E22: 1880-1980 | F22: Internet Archive | G22: archive.org | H22: https://archive.org/ | I22: Mixed | J22: Medium | N22: Umbrella source for IA full-text harvest (data/internet-archive/): ICC hearings, Governor annual reports, Canal Zone pilot 1908, memoirs, natural-history surveys. Each attestation names its text in page/plate. Overlaps Canal Record (S-003) for official serials; picks prefer non-duplicate texts. | O22: ARC-11
A23: S-022 | B23: Map | C23: General map of Empire (pcc00020) | D23: Office of Res. Engr., Empire | E23: c.1907-08 | F23: Library of Congress G&M | G23: g4872e.pcc00020 | H23: https://www.loc.gov/item/2007627522/ | I23: US official | J23: High | K23: Y | L23: 400 | M23: Empire pilot-town plan, 1:992 fitted; chained via ICC1911 | N23: #N/A | O23: ARC-02
A24: S-023 | B24: Map | C24: Map of Culebra (pcc00016) | D24: ICC Central Division, Office of Res. Engr. | E24: 1910 | F24: Library of Congress G&M | G24: g4874c.pcc00016 | H24: https://www.loc.gov/item/2007627520/ | I24: US official | J24: High | K24: Y | L24: 250 | M24: Faint photostat; along-canal anchor = K.54 arrow reading (corroborated by 1895 sheet) | N24: #N/A | O24: ARC-02
A25: S-024 | B25: Map | C25: Map of new town near Culebra, 1:1000 (pcc00015) | D25: ICC | E25: 1905 | F25: Library of Congress G&M | G25: g4874c.pcc00015 | H25: https://www.loc.gov/item/2007627519/ | I25: US official | J25: High | K25: Y | L25: 150 | M25: Planned New Culebra grid; centerline monuments Sta 1740/1750; fitted 1:996 | N25: #N/A | O25: ARC-02
A26: S-025 | B26: Map | C26: Map of Gorgona saloon-licensing areas, 1:2000 (pcc00017) | D26: ICC | E26: 1908 | F26: Library of Congress G&M | G26: g4874g.pcc00017 | H26: https://www.loc.gov/item/2007627521/ | I26: US official | J26: High | K26: Y | L26: 100 | M26: Building-level Gorgona; Tier-1 anchored | N26: #N/A | O26: ARC-02
A27: S-026 | B27: Map | C27: Plan du village de Guachapali, 1:500 (pcc00018) | D27: Cie Universelle du Canal | E27: 1890 | F27: Library of Congress G&M | G27: g4874g.pcc00018 | H27: https://www.loc.gov/item/2007627523/ | I27: French company | J27: High | K27: Y | L27: 50 | M27: Guachapali village plan; anchored to surviving Av Central / old PRR station | N27: #N/A | O27: ARC-02
A28: S-027 | B28: Map | C28: Surveys of the Panama Canal, Maps Numbers 1-2 (Isthmian Canal Commission 1905-06, published 1908) | D28: Isthmian Canal Commission | E28: 1908 | F28: Library of Congress G&M | G28: (2 sheets, 1:12,000) | H28: https://www.loc.gov/ | I28: US official | J28: High | K28: Y | L28: 200 | M28: Pre-flood village survey Colon-Gorgona; Map No.3 (Pacific reach) not held - hunt at LOC | N28: #N/A | O28: ARC-02
A29: S-028 | B29: Map | C29: Plano de tierras del Rio Chagres (pcc00023, dated May 1862) | D29: Panama Rail Road land survey | E29: 1862 | F29: Library of Congress G&M | G29: g4872c.pcc00023 | H29: https://www.loc.gov/item/2007627526/ | I29: PRR company | J29: Medium | K29: Y | L29: 800 | M29: Land-claims plano; lower river compressed ~45% - per-region honesty in GEOREF_LOG | N29: #N/A | O29: ARC-02
A30: S-029 | B30: Map | C30: Maps of proposed canal, Gorgona to Panama, 1895 (3 sheets) | D30: Cie Nouvelle du Canal de Panama | E30: 1895 | F30: Library of Congress G&M | G30: 93680805 | H30: https://www.loc.gov/item/93680805/ | I30: French company | J30: High | K30: Y | L30: 300 | M30: French K-posts drawn; K.54 corroborates CULEBRA1910 anchor | N30: #N/A | O30: ARC-02
A31: S-030 | B31: Map | C31: Plans showing location of buildings in the encampments, Culebra Division (21 sheets, 1:1000) | D31: Office of Res. Engr., Empire | E31: 2709 | F31: Library of Congress G&M | G31: 83694727 | H31: https://www.loc.gov/item/83694727/ | I31: US official | J31: High | K31: Y | L31: 200 | M31: Building-level camp/town plans Bas Obispo-Pedro Miguel; 20 of 21 sheets fitted via K-datum stationing | N31: #N/A | O31: ARC-02
A32: S-031 | B32: Map | C32: Canal Zone and Vicinity, 1:100,000 (pcc00002) | D32: Panama Canal / Corps of Engineers | E32: 1947 | F32: Library of Congress G&M | G32: g4872c.pcc00002 | H32: https://www.loc.gov/item/2007626685/ | I32: US official | J32: High | K32: Y | L32: 150 | M32: Epilogue-era zone sheet; graticule affine RMS 21-31 m; locks check 50-130 m | N32: #N/A | O32: ARC-02
A33: S-032 | B33: Secondary | C33: Presencia china en las construcciones del ferrocarril y del Canal de Panamá (1852-1914) | D33: Chen, Berta Alicia | E33: 2014 | F33: Museo del Canal Interoceánico (BiblioMUCI, biblio 6326) | G33: L 972.875 / ISBN 978-9962-633-39-6 | H33: http://typismuci.museodelcanal.com/cgi-bin/koha/opac-detail.pl?biblionumber=6326 | I33: Panamanian | J33: Medium | N33: Panamanian scholarship (MDC, 2014) documenting the Chinese community in the railroad and canal construction zones. Cited via its catalogued contents/figure list at Museo del Canal (physical book, no digital copy). Includes Cuadro 2: 'Censo de la población china en la Zona del Canal por pueblo (1908)' and captioned images of Chinese commerce in Emperador, Gorgona, Matachín, Cerro Paraíso. Counter-archive to the US official record's silence on the Asian population of these towns. | O33: ARC-04
A34: S-033 | B34: Map | C34: 1940 Census Enumeration District Maps - Panama Canal Zone (A3378) | D34: U.S. Census Bureau | E34: 1940 | F34: NARA (RG 29, via catalog.archives.gov) | G34: A3378/PC; naIds 5838606-5838626 | H34: https://catalog.archives.gov/id/5838606 | I34: US official | J34: High | N34: Building-level photostat town plans, hand-stamped 1940, one item per town/ED (Balboa + Cristobal counties). Downloaded 2026-09-05 into the NARA Desktop folder; recognised and mined 2026-09-13 (data/census/). Georeferencing candidates. | O34: ARC-14
A35: S-034 | B35: Map | C35: 1950 Census Enumeration District Maps - Panama Canal Zone | D35: U.S. Census Bureau | E35: 1950 | F35: NARA (RG 29, via catalog.archives.gov) | G35: naId 75639631 | H35: https://catalog.archives.gov/id/75639631 | I35: US official | J35: High | N35: Zone-wide ED map set (ED 1-1..1-55, 2-1..2-52); no single-place items - registered for era context, attests no individual place yet. | O35: ARC-14
A36: S-035 | B36: Newspaper | C36: Digital Library of the Caribbean, searched in full text (Caribbean Newspaper Digital Library and related collections) | D36: Digital Library of the Caribbean (UF/FIU consortium) | E36: 1880-1950 | F36: dLOC (open patron API, aggregation dloc1) | G36: aggregation dloc1 | H36: https://dloc.com | I36: Caribbean community | J36: Medium | N36: Bridgetown/Nassau/Hamilton/Kingston press + Caribbean serials, full-text. Swept 2026-09-13 (data/silvermen/): item-level probe, name + panama co-occurrence; KWIC verification pending per name. The Silver Men consortium's registers themselves are NOT online - see ARC-05. | O36: ARC-09
A37: S-036 | B37: Web compilation | C37: Isthmian Historical Society competition letters ('Silver People', 1963) | D37: West Indian canal workers (85+ first-person accounts); IHS | E37: 1963 (recalling 1904-14) | F37: dLOC (Digital Library of the Caribbean) | G37: bibid AA00016037 | H37: https://dloc.com/AA00016037 | I37: Caribbean community | J37: High | N37: THE first-person counter-archive: competition for 'best true stories of life and work' by surviving West Indian canal workers, full-text searchable on dLOC. Found 2026-09-13 during the Silver Men KWIC pass. Follow-up queued: probe all 157 place names against this bibid's page text. | Full-roster probe run 2026-09-13 (data/silvermen/silverpeople_probe.csv): 122 names, 62 present / 60 absent; positives + town-scale expected-absences imported as attestations. Building-scale absences NOT claimed (phrase-brittle: letters say 'comsy of Empire'); 'Cerro' excluded as generic Spanish. | Scope 2026-09-14: Colon-fringe places the letters name (Coolie Town, Pueblo Nuevo) DECLINED as outside the Zone model - documented in LETTER_GEOMETRY_NOTES.md; testimony preserved in town notes. | O37: ARC-09
A38: S-037 | B38: Map | C38: Map of Pacific Terminal Cities (Engineer Base Reproduction Plant, Panama Canal Department) | D38: Office of the Department Engineer; reprinted 7465th AU Engineers, Corozal C.Z. | E38: 1947-10 (printed 1952-53) | F38: Library of Congress G&M | G38: pcc00008 | I38: US military | J38: High | K38: Yes | L38: 20 | O38: ARC-02
A39: S-038 | B39: Map | C39: Plano de la Ciudad de Panama en 1904 (C. Bertoncini, 1:5000) | D39: C. Bertoncini | E39: 1904 | F39: Library of Congress G&M | G39: pcc00019 | I39: Panamanian | J39: High | K39: Yes | L39: 80 | O39: ARC-02
A40: S-039 | B40: Report | C40: Note sur la constitution geologique de l'isthme de Panama, au point de vue de l'execution du canal interoceanique | D40: Boutan, E. | E40: 1880 | F40: Bibliotheque nationale de France (Gallica) | G40: ark:/12148/bd6t5777148r | H40: https://gallica.bnf.fr/ark:/12148/bd6t5777148r | I40: French company | J40: High | N40: Harvested 2026-09-14 via Gallica open APIs (SRU + ContentSearch); French canal-era (pre-US) attestation. See data/gallica/. | O40: ARC-17
A41: S-040 | B41: Secondary | C41: A travers l'isthme de Panama: Trace interoceanique de L. N. B. Wyse et A. Reclus | D41: Verbrugghe, Louis | E41: 1879 | F41: Bibliotheque nationale de France (Gallica) | G41: ark:/12148/bpt6k5400855p | H41: https://gallica.bnf.fr/ark:/12148/bpt6k5400855p | I41: French company | J41: Medium | N41: Harvested 2026-09-14 via Gallica open APIs (SRU + ContentSearch); French canal-era (pre-US) attestation. See data/gallica/. | O41: ARC-17
A42: S-041 | B42: Report | C42: Le Canal de Panama en 1886, rapport presente par M. Jules-Charles Roux | D42: Charles-Roux, Jules | E42: 1886 | F42: Bibliotheque nationale de France (Gallica) | G42: ark:/12148/bpt6k1092498c | H42: https://gallica.bnf.fr/ark:/12148/bpt6k1092498c | I42: French company | J42: High | N42: Harvested 2026-09-14 via Gallica open APIs (SRU + ContentSearch); French canal-era (pre-US) attestation. See data/gallica/. | O42: ARC-17
A43: S-042 | B43: Map | C43: Map of the Isthmus of Panama representing the line of the Panama Rail Road (G.M. Totten, Chief Engineer, 1857; 8000ft/in = 1:96,000) | D43: George M. Totten / Panama Rail Road Co. | E43: 1857 | F43: Library of Congress G&M | G43: pcc00004 | I43: US corporate (PRR) | J43: Medium | K43: Yes | L43: 400 | O43: ARC-02
A44: S-043 | B44: Map | C44: Lands belonging to the Panama Rail Road Co., Panama City and environs (200 ft/in = 1:2,400) | D44: Panama Rail Road Company | E44: 1857 (c.) | F44: Library of Congress G&M | G44: pcc00013 | I44: US corporate (PRR) | J44: High | K44: Yes | L44: 120 | O44: ARC-02
A45: S-044 | B45: Newspaper | C45: La estrella de Panama (LOC World Newspapers, full-text) | D45: La Estrella de Panama | E45: 1849-current (digitized run at LOC) | F45: Library of Congress, Serial & Govt Publications | G45: lccn 2010225009 | H45: https://www.loc.gov/item/2010225009/ | I45: Panamanian | J45: Medium | N45: THE Panamanian newspaper of record, full-text searchable at LOC - found 2026-09-14 during the Matachin hunt; the first Panamanian full-text corpus in the model. Roster probe 2026-09-14 in data/estrella/ (163 names, page-context queries per the Cloudflare recipe). KWIC/page-level verification pending per name; Spanish OCR quality varies. | O45: ARC-18
A46: S-045 | B46: Map | C46: Cristobal-Colon-Mt. Hope (Engineer Base Reproduction Plant, Panama Canal Department, June 1947, 1:8,000) | D46: Office of the Department Engineer | E46: 1947-06 | F46: UF Smathers (Panama Canal Museum Collection) | G46: AA00038126 | I46: US military | J46: High | K46: Yes | L46: 20 | O46: ARC-19
A47: S-046 | B47: Map | C47: Map of the United States Canal Zone showing the completed Panama Canal (C.S. Hammond & Co. atlas page) | D47: C.S. Hammond & Co., N.Y. | E47: 1927 (base ~1912) | F47: UF Smathers (PCM AA00038443) | G47: AA00038443 | I47: US commercial | J47: Low | K47: No | O47: ARC-19
A48: S-047 | B48: Map | C48: Map of the Canal Zone and Vicinity 1:100,000, 1927 base revised 1973 | D48: The Panama Canal | E48: 1973 (rev. of 1927 base) | F48: ECU Digital Collections (Robert Morgan Papers, 56832) | G48: 56832 | I48: US official | J48: Medium | K48: No | O48: ARC-12
A49: S-048 | B49: Map | C49: Carte topographique de l'Isthme de Panama entre Panama et Chagres, avec le trace du canal maritime (Napoleon Garella, dressee 1844, pub. 1845, 1:200,000) | D49: Napoleon Garella / Corps Royal des Mines | E49: 1844 (pub. 1845) | F49: UF Smathers (UF00100942) | G49: UF00100942 | I49: French state survey | J49: Medium | K49: No | O49: ARC-19
A50: S-049 | B50: Map | C50: Chart of the Harbour of Chagres, surveyed 1829 (J.A. Lloyd; Phil. Trans. 1829 Plate V) | D50: J.A. Lloyd / Royal Society | E50: 1829 (surveyed) | F50: Wikimedia Commons (Phil. Trans. plates) | G50: 107889_0028 (+0027 Limon Bay, 0011/0017 isthmus) | I50: British survey | J50: Medium | K50: No | O50: ARC-16
A51: S-050 | B51: Map | C51: Plans des principaux chantiers au 1er juin 1883 (Compagnie Universelle du Canal Interoceanique de Panama) | D51: Compagnie Universelle du Canal Interoceanique; grave par Erhard, Paris | E51: 1883 | F51: Bibliotheque nationale de France (Gallica) | G51: ark:/12148/btv1b8439064m; BnF Ge D 152/153 | H51: https://gallica.bnf.fr/ark:/12148/btv1b8439064m | I51: French company | J51: High | K51: N | N51: Compagnie worksite plan, 1:20,000, 7 insets (Colon, Buhio-Soldado, San-Pablo, Gorgona, Matachin, Bas-Obispo, Emperador-Culebra). Canal/tracks/installations in RED; labor camps (campements) drawn as building clusters. Read 2026-09-14; towns recorded as Existence/mention with descriptive positions - NOT georeferenced to lat/lng (no unified graticule; GCP extraction is a follow-up). Full-res at data/georef/gallica_maps/. | O51: ARC-17
A52: S-051 | B52: Map | C52: Plan general du Canal (juillet 1886) + Profil geologique suivant l'axe du canal (Compagnie Universelle) | D52: Compagnie Universelle du Canal Interoceanique; grave par Erhard, Paris | E52: 1886 | F52: Bibliotheque nationale de France (Gallica) | G52: ark:/12148/btv1b53060301n; BnF Ge C 3134 | H52: https://gallica.bnf.fr/ark:/12148/btv1b53060301n | I52: French company | J52: High | K52: N | N52: 1:50,000 map of the whole canal line + a geological profile along the axis giving each town's kilometer position (PK) from Colon (PK 0) to Panama (PK 74.5). Read 2026-09-14; town PKs recorded as the French survey-grid positions (lat/long conversion via the canal alignment is a follow-up). Full-res at data/georef/gallica_maps/ (20045x7767). | O52: ARC-17
A53: S-052 | B53: Map | C53: Map of the Canal Zone and Vicinity, January 1927, 1:100,000 (The Panama Canal; NARA 185-G-2220 photo print) | D53: The Panama Canal (compiled under O.E. Malsbury, Section of Surveys) | E53: 1927-01 | F53: NARA (RG 185-G, naId 100999006; via catalog IIIF) | G53: 185-G-2220 | H53: https://catalog.archives.gov/id/100999006 | I53: US official | J53: High | K53: No | O53: ARC-01
A54: S-053 | B54: Map | C54: Map of the Canal route at the beginning of American occupation (manuscript topographic compilation, c.1904; LOC pcc00001) | D54: Isthmian Canal Commission (compilation) | E54: c.1904 | F54: Library of Congress G&M | G54: pcc00001 (82690134); local file 4.tif | H54: https://www.loc.gov/item/82690134/ | I54: US official | J54: High | K54: Yes | L54: 300 | O54: ARC-02
A55: S-054 | B55: Map | C55: The Panama Canal - Map of the Canal Zone, Aug. 1, 1920 (Governor; Raggi-file copy with manuscript route annotations) | D55: The Panama Canal (Governor Chester Harding) | E55: 1920-08-01 | F55: NARA (RG 185, Historical Files of Arthur Raggi, naId 6861830) | G55: RG185RaggiFilesFolder1-CanalZone | H55: https://catalog.archives.gov/id/6861830 | I55: Colonial power - US official | J55: High | K55: No | O55: ARC-01
A56: S-055 | B56: Map | C56: Planta y Perspectiva de la Ciudad de Panama y su Fortificacion, 1688 (1891 photographic copy) | D56: anon. (1688); 1891 copy | E56: 1688 (copy 1891) | F56: NARA (185-G-2156, naId 100998878) | G56: 185-G-2156 | H56: https://catalog.archives.gov/id/100998878 | I56: Colonized - Spanish colonial (via US archive) | J56: Medium | K56: No | O56: ARC-01
A57: S-056 | B57: Map | C57: Historical Map of Canal Zone and Vicinity: Routes, Settlements etc. between 1502 and 1855 (Section of Surveys, Feb 1 1934) | D57: The Panama Canal, Section of Surveys | E57: 1934-02-01 | F57: NARA (185-G-211, naId 100995004) | G57: 185-G-211 / 26-A-1-(11) | H57: https://catalog.archives.gov/id/100995004 | I57: Colonial power - US official (memory cartography) | J57: High | K57: No | O57: ARC-01
A58: S-057 | B58: Map | C58: Planos de las tierras baldias cuya adjudicacion pide la Compania Universal del Canal Interoceanico (3 lots, 1888: Tucuti, Darien, 204,500 ha; Catabella y San Pedro, Bocas del Toro, 109,200 ha; Sigsola y Robalo, Bocas del Toro, 190,500 ha) | D58: Compagnie Universelle du Canal Interoceanique | E58: 1888 | F58: Bibliotheque nationale de France (Gallica) | G58: ark:/12148/btv1b52525881g, btv1b52525883c, btv1b525258801 | H58: https://gallica.bnf.fr/ark:/12148/btv1b52525881g | I58: French canal company | J58: High | K58: No | N58: The company's petitions to Colombia for 504,200 hectares of 'tierras baldias' (vacant lands) - NONE on the canal line (the sweep registry's 'French line towns' expectation was wrong). The maps refute their own legal category: villages, named smallholder ranchos (M. Gonzales, Florencio Leon, J.B. Torres), an explicit CASERIO INDIO on Punta Bluefield, plantations and the Camino Real are all drawn INSIDE the lots, under 'FORETS VIERGES' lettering. Vacancy-declaration as erasure, 1888 - the mechanism the dissertation tracks in the Zone, a generation early and at territorial scale. Longitudes on the Bogota meridian; stated Escala 1/20.000 on the Bocas sheets (Tucuti scale digit uncertain, ~1/50.000 by graticule span). Out of the study frame: no attestations (PRRLANDS1857 precedent); inventory in TIERRAS1888_features.csv. | O58: ARC-17

Sheet attestations
A1: attestation_id (PK) | B1: place_id (FK) | C1: source_id (FK) | D1: attestation_type | E1: name_as_recorded | F1: name_lang | G1: att_lat | H1: att_lng | I1: positional_method | J1: positional_uncertainty_m | K1: when_start | L1: when_end | M1: temporal_confidence | N1: confidence | O1: page / plate | P1: transcript / note | Q1: medium (auto) | R1: medium_group (auto) | S1: source_origin (auto)
